Workbook

Sheet README
A1: Cancer in India - combined dataset (state forecasts, national NCRP estimates, registry data, Maharashtra profile)
A2: This workbook merges the original state-wise forecasting file (Kumar et al. 2026) with data extracted from three NCRP/ICMR PDFs: IJMR 2022 national estimates (S1), the Maharashtra cancer fact sheet 2021 (S2) and the JCO 2020 NCRP report (S3). Every table in the PDFs has been transcribed; figure-only data were read from the page images. Header colours: blue = source data, green = formula-derived.
A4: Sheet | B4: Source | C4: Contents | D4: Rows (approx.) | E4: Group
A5: Source Documents | B5: All | C5: Bibliographic details of the four source documents and which sheets come from each | D5: 4 | E5: Guide
A6: Key Findings (3 PDFs) | B6: S1-S3 | C6: Headline statistics, methods, coverage and data-quality facts from the three new PDFs, with page numbers | D6: 46 | E6: Guide
A7: Cross-Validation | B7: S1-S4 | C7: Formula checks between the sources (e.g. existing state totals vs NCRP national estimates) | D7: 24 | E7: Guide
A8: Data Notes | B8: All | C8: Assumptions, inferred readings, discrepancies and conventions | D8: 15 | E8: Guide
A9: State-wise Incidence | B9: S4 + S1 | C9: Original 37-state table, extended with region, PBCR representation, growth rates, shares and an all-India total | D9: 37 | E9: India - state
A10: India Sites 2022 | B10: S1 | C10: IJMR Table I: 2022 cases, crude and age-adjusted rates and cumulative risk by site and sex, with 2020 comparison | D10: 55 | E10: India - national
A11: India Sites 2020 | B11: S3 | C11: JCO Table 2: projected 2020 cases, crude rate and cumulative risk by site and sex | D11: 55 | E11: India - national
A12: India Age-Sex Sites | B12: S1 | C12: IJMR Table II: top five sites by age group (0-14, 15-39, 40-64, 65+) and sex | D12: 56 | E12: India - national
A13: India Top10 Sites 2022 | B13: S1 | C13: IJMR Fig. 1: top ten sites by sex, validated against Table I | D13: 20 | E13: India - national
A14: India Trend 2015-2025 | B14: S1 | C14: IJMR Table III: leading-site cases 2015, 2020, 2025 with growth rates | D14: 17 | E14: India - national
A15: India Age Structure | B15: S1 | C15: Population pyramid shares (census 2011 vs 2022 estimate) | D15: 16 | E15: India - national
A16: PBCR Incidence Table | B16: S3 | C16: JCO Table 1: incidence, cumulative risk and mortality for 28 PBCRs (plus 4 district rows) | D16: 32 | E16: India - registries
... A33: Full PDF Text | B33: S1-S4 | C33: Raw extracted text of every page of all four PDFs (new column A identifies the document) | D33: 43 | E33: Reference

Sheet Source Documents
A1: Ref | B1: File | C1: Title | D1: Authors / publisher | E1: Journal / series | F1: Year | G1: Volume / pages | H1: DOI / link | I1: Data period | J1: Geography and scope | K1: Sheets built from it
A2: S1 | B2: 1792240250346_cancer_dataset.pdf | C2: Cancer incidence estimates for 2022 & projection for 2025: Result from National Cancer Registry Programme, India | D2: Krishnan Sathishkumar, Meesha Chaturvedi, Priyanka Das, S. Stephen, Prashant Mathur (ICMR-NCDIR, Bengaluru) | E2: Indian Journal of Medical Research | F2: 2022 | G2: 156 (Oct & Nov), pp 598-607 | H2: DOI 10.4103/ijmr.ijmr_1821_22 | I2: Rates 2012-2016; estimates 2022; projection 2025 | J2: India national, by sex, age group and anatomical site; state/region PBCR representation | K2: India Sites 2022; India Age-Sex Sites; India Top10 Sites 2022; India Trend 2015-2025; India Age Structure; Method Comparison; State-wise Incidence (cols I-J); Key Findings
A3: S2 | B3: 1792240259450_FS_Maharashtra.pdf | C3: Profile of Cancer and Related Factors - Maharashtra | D3: ICMR-National Centre for Disease Informatics and Research (NCDIR), Bengaluru | E3: Cancer fact sheet series (NCRP) | F3: 2021 | G3: 11 pages (9 content pages) | H3: https://www.ncdirindia.org/ | I3: Registry data 2012-2016; projections 2020 and 2025 | J3: Maharashtra state: 8 PBCRs, 5 HBCRs, socio-demographic, health indicators and infrastructure | K3: MH PBCR Profile; MH Childhood Cancer; MH Sites & Tobacco; MH Projections; MH Socio-Health Profile; MH Health Infrastructure; Clinical Stage
A4: S3 | B4: 1792240259452_cancer_dataset_2.pdf | C4: Cancer Statistics, 2020: Report From National Cancer Registry Programme, India | D4: Prashant Mathur, Krishnan Sathishkumar, Meesha Chaturvedi, Priyanka Das, Kondalli Lakshminarayana Sudarshan, Stephen Santhappan, Vinodh Nallasamy, Anish John, Sandeep Narasimhan, Francis Selvaraj Roselind; ICMR-NCDIR-NCRP Investigator Group | E4: JCO Global Oncology (ASCO) | F4: 2020 | G4: 6:1063-1075 | H4: DOI 10.1200/GO.20.00122 | I4: Registry data 2012-2016; trends from 1982; projection 2020 | J4: India: 28 PBCRs and 58 HBCRs; incidence, mortality, trends, stage, treatment | K4: PBCR Incidence Table; Tobacco-related Cancers; Cancer Trends (APC); Clinical Stage; India Sites 2020; Key Findings
A5: S4 | B5: 1792240265018_final_excel.xlsx (existing content) | C5: State-wise forecasting of cancer incidence in India using a moderated exponential regression model incorporating healthcare system determinants | D5: Dileep Kumar, Navin Upadhyay, Himanshu Pandey | E5: International Journal of Community Medicine and Public Health | F5: 2026 | G5: 13(4):1867-1873 | H5: https://dx.doi.org/10.18203/2394-6040.ijcmph20261025 | I5: Observed 2019-2022; predicted 2026, 2030, 2045 | J5: India, 37 states/UTs | K5: State-wise Incidence; Article Details; Summary & Findings; Healthcare Moderators; Model & Forecasts; References; Full PDF Text (pages 1-7)

Sheet Key Findings (3 PDFs)
A1: Source | B1: Topic | C1: Finding / metric | D1: Value | E1: Unit | F1: Context / detail | G1: Page
A2: IJMR 2022 (Sathishkumar) | B2: Burden | C2: Estimated new cancer cases in India, 2022 | D2: 1461427 | E2: cases | F2: Crude rate 100.4 per 100,000; age-adjusted rate 107.0 per 100,000 | G2: 598, 600
A3: IJMR 2022 (Sathishkumar) | B3: Burden | C3: Estimated cases among females, 2022 | D3: 749251 | E3: cases | F3: Crude rate 105.4 per 100,000 | G3: 600
A4: IJMR 2022 (Sathishkumar) | B4: Burden | C4: Estimated cases among males, 2022 | D4: 712176 | E4: cases | F4: Crude rate 95.6 per 100,000 | G4: 600
A5: IJMR 2022 (Sathishkumar) | B5: Risk | C5: Lifetime risk of cancer (0-74 years) | D5: 1 in 9 | F5: Both sexes; lung cancer in males 1 in 67; breast cancer in females 1 in 29 | G5: 598, 600
A6: IJMR 2022 (Sathishkumar) | B6: Burden | C6: Largest site groups, both sexes | D6: Digestive 288,054; breast 221,757; genital 218,319; oral cavity & pharynx 198,438; respiratory 143,062 | E6: cases | F6: Five highest-burden groups | G6: 600
A7: IJMR 2022 (Sathishkumar) | B7: Leading sites | C7: Top five male sites, 2022 | D7: Lung 10.6; mouth 8.4; prostate 6.1; tongue 5.9; stomach 4.8 | E7: % of male cancers | F7: Liver (3.9%) is in the male top ten but not the female | G7: 600
A8: IJMR 2022 (Sathishkumar) | B8: Leading sites | C8: Top five female sites, 2022 | D8: Breast 28.8; cervix 10.6; ovary 6.2; corpus uteri 3.7; lung 3.7 | E8: % of female cancers | F8: Thyroid (3.6%) and gallbladder (2.7%) are in the female top ten but not the male | G8: 600
A9: IJMR 2022 (Sathishkumar) | B9: Childhood | C9: Leading childhood (0-14 yr) cancer | D9: Lymphoid leukaemia: boys 29.3%, girls 24.3% | F9: Abstract prints 29.2% / 24.2%; Table II prints 29.3% / 24.3%. Next: brain/NS (boys 12.4%, girls 14.3%) | G9: 598, 600, 604
A10: IJMR 2022 (Sathishkumar) | B10: Childhood | C10: Childhood share of all cancers | D10: Boys 3.0%; girls 1.8% | E10: of cancers in age group 0-14 | F10: Rural childhood incidence is lower, attributed to under-reporting | G10: 606
A11: IJMR 2022 (Sathishkumar) | B11: Age | C11: Cancer cases in 40-64 year olds | D11: Males 341,230; females 425,918 | E11: cases | F11: Half of India's estimated burden is in this age group; globally half is aged 65+, in India one-third | G11: 600, 604, 606
A12: IJMR 2022 (Sathishkumar) | B12: Age | C12: Age-specific incidence rate pattern | D12: Rises from age 25; female > male at 25-59; male > female above 60 | F12: At 75+: males 710.6 vs females 451.7 per 100,000 | G12: 600
A13: IJMR 2022 (Sathishkumar) | B13: Age | C13: Peak number of cases by age group | D13: Age 60-64: males 106,296; females 105,139 | E13: cases | G13: 600
A14: IJMR 2022 (Sathishkumar) | B14: Projection | C14: Cases projected for 2025 | D14: 1.57 million (2025) vs 1.46 million (2022) | F14: Increase of 12.8% in 2025 vs 2020; +27.7% from 2015 to 2025 | G14: 598, 600
A15: IJMR 2022 (Sathishkumar) | B15: Projection | C15: 2025 leading-site projections | D15: Lung (males) 81,219; breast (females) 232,832 | E15: cases | F15: Table III | G15: 600, 605
A16: IJMR 2022 (Sathishkumar) | B16: Comparison | C16: 2022 estimate vs 2020 estimate (1,392,179) | D16: About +5% | F16: 13,92,179 in 2020 to 14,61,427 in 2022 | G16: 603
A17: IJMR 2022 (Sathishkumar) | B17: Comparison | C17: Lung cancer cases 2022 | D17: 103371 | E17: cases | F17: Top-five site for both sexes | G17: 603
A18: IJMR 2022 (Sathishkumar) | B18: Comparison | C18: GLOBOCAN context | D18: 19.3 million cases worldwide (2020); India third; India 2.08 million by 2040 (+57.5% vs 2020) | F18: NCRP 2020 estimate was 5.1% higher than GLOBOCAN | G18: 598, 604
A19: IJMR 2022 (Sathishkumar) | B19: Population | C19: Share of population aged 60+ | D19: 8.6% (2011) to 9.7% (2022) | F19: Ageing drives most of the projected rise because rates are held constant | G19: 605
A20: IJMR 2022 (Sathishkumar) | B20: Coverage | C20: PBCR coverage | D20: 28 PBCRs cover ~10% of population; NCRP coverage 16.4% (urban 31.6%, rural 9.5%) | F20: Of 28 PBCRs: 1 rural (3.5%), 12 urban (42.9%), 15 semi-urban (53.6%). Four NE states (Sikkim, Manipur, Mizoram, Tripura) have 100% PBCR coverage | G20: 599, 604, 605
A21: IJMR 2022 (Sathishkumar) | B21: Method | C21: Estimation approach | D21: 2012-16 age-specific rates by site applied to 2022 population estimates | F21: Constant incidence assumed; census 2021 delayed; fertility, mortality, migration and COVID-19 impact not modelled; only 6 PBCRs have >25 years of data | G21: 599-600, 604-605
A22: IJMR 2022 (Sathishkumar) | B22: Risk factors | C22: Attributable risk (DALYs) | D22: Alcohol 30.1% (pharyngeal); tobacco 43% and air pollution 43% (lung); diet 43.2% (colorectal) | F22: Rising incidence: tongue, mouth, colon, rectum, liver, lung, breast, corpus uteri, ovary, thyroid, prostate, gallbladder, pancreas, kidney, bladder, brain, NHL, lymphoid leukaemia. Falling: hypopharynx, oesophagus, stomach, cervix | G22: 605
A23: IJMR 2022 (Sathishkumar) | B23: Burden | C23: Projected DALYs from cancer by 2025 | D23: 29.8 million | E23: DALYs | F23: Separate NCRP publication cited in the paper | G23: 606
A24: JCO 2020 (Mathur) | B24: Projection | C24: Projected cases in India, 2020 | D24: 1392179 | E24: cases | F24: Males 679,421 (94.1 per 100,000); females 712,758 (103.6); crude rate both sexes 98.7 | G24: 1063, 1069
A25: JCO 2020 (Mathur) | B25: Risk | C25: Lifetime risk | D25: 1 in 68 males (lung); 1 in 29 females (breast); 1 in 9 Indians | F25: Cumulative risk age 0-74 | G25: 1069
A26: JCO 2020 (Mathur) | B26: Leading sites | C26: Five most common projected cancers 2020 | D26: Males: lung, mouth, prostate, tongue, stomach = 36% of male cancers; females: breast, cervix, ovary, corpus uteri, lung = 53% | G26: 1069
A27: JCO 2020 (Mathur) | B27: Geography | C27: Highest age-adjusted incidence | D27: Males: Aizawl district 269.4 (mortality 152.7); females: Papumpare district 219.8 | E27: per 100,000 | F27: Aizawl ~2x Delhi (147.0); East Khasi Hills 227.9, Kamrup urban 213.0, Mizoram state 207.0 follow | G27: 1066
A28: JCO 2020 (Mathur) | B28: Geography | C28: Highest outside the North-East | D28: Males: Delhi 147.0, Thiruvananthapuram 137.8; females: Bangalore 146.8, Delhi 141.0 | E28: per 100,000 | G28: 1066
A29: JCO 2020 (Mathur) | B29: Geography | C29: Lowest age-adjusted incidence | D29: Osmanabad and Beed: males 39.5, females 49.4 | E29: per 100,000 | F29: Aizawl male rate ~7x and Papumpare female rate ~4x that of Osmanabad & Beed; Barshi rural is ~1/3 of urban PBCRs | G29: 1068-1070
A30: JCO 2020 (Mathur) | B30: Geography | C30: One in four lifetime risk | D30: Males in Aizawl, Papumpare, East Khasi Hills, Kamrup urban; females in Papumpare (1 in 4) and Mizoram (1 in 5) | F30: Cumulative risk 0-74 | G30: 1066
A31: JCO 2020 (Mathur) | B31: Tobacco | C31: Tobacco-associated share of cancers | D31: East Khasi Hills: 70.4% males, 46.5% females | E31: % | F31: About one-third of cancers in India are tobacco-associated; NE highest, then West and Central registries | G31: 1066-1067, 1071
A32: JCO 2020 (Mathur) | B32: Patterns | C32: Most common sites in registries | D32: Men: lung (9 PBCRs), mouth (9), oesophagus (5), stomach (4), nasopharynx (1); women: breast (19 PBCRs), cervix (7) | F32: Thyroid second in Thiruvananthapuram and Kollam; lung in Manipur and Mizoram (women) | G32: 1067, 1069
A33: JCO 2020 (Mathur) | B33: Stage | C33: Loco-regional at diagnosis | D33: Breast 57.0%; cervix 60.0%; head & neck 66.6%; stomach 50.8% | E33: % | F33: Lung: distant metastasis 44.0% (males), 47.6% (females). See sheet Clinical Stage | G33: 1063, 1068
A34: JCO 2020 (Mathur) | B34: Treatment | C34: Multimodality treatment share | D34: Loco-regional 79.5%; localised 74.4%; distant metastasis 47.6% | E34: % | F34: Systemic therapy most common for lung and stomach; chemoradiation for cervix | G34: 1068, 1071
A35: JCO 2020 (Mathur) | B35: Trends | C35: Annual percentage change | D35: All sites increasing in 12 PBCRs (males) and 13 (females); highest Kamrup urban 3.8% | E35: % per year | F35: Breast: significant increase everywhere except Nagpur; cervix: significant decrease in 10 PBCRs; lung (females): significant increase in 11. See sheet Cancer Trends (APC) | G35: 1063, 1068
A36: JCO 2020 (Mathur) | B36: Data quality | C36: Quality indices across 28 PBCRs | D36: MV% 77 (Patiala) to 96.7 (Hyderabad); DCO% <0.05 (Osmanabad & Beed) to 19.4 (Patiala); O&U% 1.8 (Hyderabad) to 13.0 (Patiala) | F36: Highest mortality-to-incidence ratio: Barshi rural 67.2%, Wardha 59.2%, Mumbai 56.0% | G36: 1068
A37: JCO 2020 (Mathur) | B37: Coverage | C37: Registry network analysed | D37: 28 PBCRs and 58 HBCRs (667,666 patients) of 36 PBCRs and 236 HBCRs registered | F37: PBCRs cover ~100 million person-years (~10% of India); trend analysis uses 16 PBCRs with 11-35 years of data | G37: 1064-1065, 1071
A38: JCO 2020 (Mathur) | B38: Comparison | C38: NCRP vs IARC/GLOBOCAN 2018 national estimate | D38: 1,392,179 (NCRP, 2020) vs 1,157,294 (2018) | E38: cases | F38: Difference attributed to methodology and use of recent data | G38: 1072
A39: JCO 2020 (Mathur) | B39: Prevention | C39: Preventable share of cancers | D39: Approximately 70% | F39: Tobacco and air pollution main lung-cancer risk factors; breast and cervix need screening/awareness | G39: 1071
A40: JCO 2020 (Mathur) | B40: Context | C40: NCD burden | D40: NCDs: 71% of deaths globally, 63% in India; cancer 9% of deaths in India | G40: 1063
A41: Maharashtra Fact Sheet 2021 | B41: Context | C41: Cancer in India's NCD burden | D41: NCDs 63% of deaths in India; cancers 9%; close to half of cancer deaths avoidable | G41: 1
A42: Maharashtra Fact Sheet 2021 | B42: Registries | C42: Maharashtra registry network | D42: 8 PBCRs (Aurangabad, Osmanabad & Beed, Barshi rural, Mumbai, Pune, Wardha, Nagpur, Nagpur rural) and 5 HBCRs | F42: Nagpur rural established 2020; PBCRs 1963 (Mumbai) to 2020 | G42: 2
A43: Maharashtra Fact Sheet 2021 | B43: Risk | C43: Cumulative risk 0-74 by registry | D43: Highest Mumbai: males 1 in 9, females 1 in 8; lowest Osmanabad & Beed: males 1 in 23, females 1 in 19 | G43: 4
A44: Maharashtra Fact Sheet 2021 | B44: Leading sites | C44: Five leading sites | D44: Males: mouth 11.1, lung 8.4, prostate 7.0, tongue 6.1, liver 4.9; females: breast 29.9, cervix 11.0, ovary 6.3, lung 4.2, mouth 3.7 | E44: % | F44: See sheet MH Sites & Tobacco | G44: 4
A45: Maharashtra Fact Sheet 2021 | B45: Tobacco | C45: Tobacco-associated cancers | D45: Males 40.6%; females 15.6% | E45: % of cancers | F45: Male: mouth 27, lung 21, tongue 15; female: lung 27, mouth 24, oesophagus 19 | G45: 5
A46: Maharashtra Fact Sheet 2021 | B46: Projection | C46: Projected cases Maharashtra | D46: 2020: 54,961 M + 61,160 F; 2025: 61,703 M + 68,762 F | E46: cases | F46: See sheet MH Projections | G46: 6
A47: Maharashtra Fact Sheet 2021 | B47: Age pattern | C47: Age-specific incidence (all sites, 2020) | D47: Rates rise steeply after age 40; women higher through the mid-60s, men higher after | F47: Chart only, no printed values | G47: 6

Sheet Cross-Validation
A1: # | B1: Check | C1: Value A - description | D1: Value A | E1: Value B - description | F1: Value B | G1: Difference (A - B) | H1: Tolerance | I1: Status | J1: Comment
A2: 1 | B2: India 2020 cases | C2: Sum of 37 states, "2020 Observed" (existing sheet) | D2: ='State-wise Incidence'!C39 -> 1392179 | E2: JCO 2020 projected national cases | F2: ='India Sites 2020'!J2 -> 1392179 | G2: =D2-F2 -> 0 | H2: 0 | I2: =IF(ABS(G2)<=H2,"Match","Check") -> Match | J2: Identical: the existing "observed" 2020 column is the NCRP national projection, not raw registry counts.
A3: 2 | B3: India 2022 cases | C3: Sum of 37 states, "2022 Observed" (existing sheet) | D3: ='State-wise Incidence'!E39 -> 1461427 | E3: IJMR 2022 estimated national cases (Table I) | F3: ='India Sites 2022'!L2 -> 1461427 | G3: =D3-F3 -> 0 | H3: 0 | I3: =IF(ABS(G3)<=H3,"Match","Check") -> Match | J3: Identical: the existing "2022 Observed" column equals the IJMR NCRP estimate.
A4: 3 | B4: Maharashtra 2020 cases | C4: Maharashtra "2020 Observed" (existing sheet) | D4: =INDEX('State-wise Incidence'!$C$2:$C$38,MATCH("Maharashtra",'State-wise Incidence'!$A$2:$A$38,0)) -> 116121 | E4: Fact sheet projection 2020 (M + F) | F4: ='MH Projections'!D2 -> 116121 | G4: =D4-F4 -> 0 | H4: 0 | I4: =IF(ABS(G4)<=H4,"Match","Check") -> Match | J4: Identical: state data trace back to NCRP projections.
A5: 4 | B5: Maharashtra share of India, 2020 | C5: Existing-sheet Maharashtra / India 2020 | D5: =INDEX('State-wise Incidence'!$C$2:$C$38,MATCH("Maharashtra",'State-wise Incidence'!$A$2:$A$38,0))/'State-wise Incidence'!C39 -> 0.083409533 | E5: Fact-sheet Maharashtra / JCO India 2020 | F5: ='MH Projections'!G2 -> 0.083409533 | G5: =D5-F5 -> 0 | H5: 1e-05 | I5: =IF(ABS(G5)<=H5,"Match","Check") -> Match
A6: 5 | B6: India 2020 cases across papers | C6: IJMR Table III both sexes 2020 | D6: ='India Trend 2015-2025'!D18 -> 1392179 | E6: JCO Table 2 all sites 2020 | F6: ='India Sites 2020'!J2 -> 1392179 | G6: =D6-F6 -> 0 | H6: 0 | I6: =IF(ABS(G6)<=H6,"Match","Check") -> Match | J6: Two NCRP papers agree on the 2020 projection.
A7: 6 | B7: IJMR 2022 male + female = both sexes | C7: Male + female cases (Table I) | D7: ='India Sites 2022'!D2+'India Sites 2022'!H2 -> 1461427 | E7: Both sexes cases (Table I) | F7: ='India Sites 2022'!L2 -> 1461427 | G7: =D7-F7 -> 0 | H7: 0 | I7: =IF(ABS(G7)<=H7,"Match","Check") -> Match | J7: Internal consistency of Table I.
A8: 7 | B8: 2025 vs 2020 growth (%) | C8: Computed from Table III (rounded to 0.1) | D8: =ROUND('India Trend 2015-2025'!G18*100,1) -> 12.8 | E8: Paper text | F8: 12.8 | G8: =D8-F8 -> 0 | H8: 0.05 | I8: =IF(ABS(G8)<=H8,"Match","Check") -> Match
A9: 8 | B9: 2025 vs 2015 growth (%) | C9: Computed from Table III (rounded to 0.1) | D9: =ROUND('India Trend 2015-2025'!H18*100,1) -> 27.7 | E9: Paper text | F9: 27.7 | G9: =D9-F9 -> 0 | H9: 0.05 | I9: =IF(ABS(G9)<=H9,"Match","Check") -> Match
A10: 9 | B10: 2022 vs 2020 growth (%) | C10: Computed from Table I and JCO Table 2 | D10: =ROUND(('India Sites 2022'!L2/'India Sites 2020'!J2-1)*100,1) -> 5 | E10: Paper text ("five per cent") | F10: 5 | G10: =D10-F10 -> 0 | H10: 0.1 | I10: =IF(ABS(G10)<=H10,"Match","Check") -> Match | J10: Text rounds 4.98% to 5%.
A11: 10 | B11: Lung cancer cases 2022 | C11: Table I, lung and bronchus, both sexes | D11: =INDEX('India Sites 2022'!$L$2:$L$58,MATCH("Lung and bronchus",'India Sites 2022'!$A$2:$A$58,0)) -> 103371 | E11: Paper discussion text (1,03,371) | F11: 103371 | G11: =D11-F11 -> 0 | H11: 0 | I11: =IF(ABS(G11)<=H11,"Match","Check") -> Match
A12: 11 | B12: Population aged 60+, 2022 (%) | C12: Pyramid data, male/female average | D12: =ROUND('India Age Structure'!D21,1) -> 9.7 | E12: Paper text | F12: 9.7 | G12: =D12-F12 -> 0 | H12: 0.05 | I12: =IF(ABS(G12)<=H12,"Match","Check") -> Match | J12: Confirms which pyramid is 2022.
A13: 12 | B13: Population aged 60+, 2011 (%) | C13: Pyramid data, male/female average | D13: =ROUND('India Age Structure'!B21,1) -> 8.6 | E13: Paper text | F13: 8.6 | G13: =D13-F13 -> 0 | H13: 0.05 | I13: =IF(ABS(G13)<=H13,"Match","Check") -> Match | J13: Confirms which pyramid is 2011.
A14: 13 | B14: Lymphoid leukaemia share, boys 0-14 (%) | C14: Table II (printed) | D14: ='India Age-Sex Sites'!G2 -> 29.3 | E14: Abstract (printed) | F14: 29.2 | G14: =D14-F14 -> 0.1 | H14: 0.05 | I14: =IF(ABS(G14)<=H14,"Match","Check") -> Check | J14: Source discrepancy: abstract 29.2% vs table 29.3% (table used in workbook).
A15: 14 | B15: Lymphoid leukaemia share, girls 0-14 (%) | C15: Table II (printed) | D15: ='India Age-Sex Sites'!G9 -> 24.3 | E15: Abstract (printed) | F15: 24.2 | G15: =D15-F15 -> 0.1 | H15: 0.05 | I15: =IF(ABS(G15)<=H15,"Match","Check") -> Check | J15: Source discrepancy: abstract 24.2% vs table 24.3% (table used in workbook).
A16: 15 | B16: Tobacco shares: printed vs recomputed | C16: Mean absolute difference, 32 registries x 2 sexes (pct-pts) | D16: =(SUMPRODUCT(ABS('Tobacco-related Cancers'!I2:I33-'Tobacco-related Cancers'!C2:C33))+SUMPRODUCT(ABS('Tobacco-related Cancers'!J2:J33-'Tobacco-related Cancers'!F2:F33)))/64 -> 0.098638006 | E16: Expected | F16: 0 | G16: =D16-F16 -> 0.098638006 | H16: 0.5 | I16: =IF(ABS(G16)<=H16,"Match","Check") -> Match | J16: Small differences are rounding in the printed rates.
A17: 16 | B17: Stage rows not summing to ~100% | C17: Rows with |total - 100| > 0.15 | D17: =SUMPRODUCT(--(ABS('Clinical Stage'!I2:I15-100)>0.15)) -> 0 | E17: Expected | F17: 0 | G17: =D17-F17 -> 0 | H17: 0 | I17: =IF(ABS(G17)<=H17,"Match","Check") -> Match
A18: 17 | B18: Breast: significant APC increases | C18: Count in Cancer Trends (APC) | D18: =COUNTIFS('Cancer Trends (APC)'!A2:A153,"Breast",'Cancer Trends (APC)'!F2:F153,"Yes") -> 15 | E18: Paper: all registries except Nagpur (16 analysed) | F18: 15 | G18: =D18-F18 -> 0 | H18: 0 | I18: =IF(ABS(G18)<=H18,"Match","Check") -> Match
A19: 18 | B19: Cervix: significant APC decreases | C19: Count in Cancer Trends (APC) | D19: =COUNTIFS('Cancer Trends (APC)'!A2:A153,"Cervix uteri",'Cancer Trends (APC)'!F2:F153,"Yes") -> 10 | E19: Paper text | F19: 10 | G19: =D19-F19 -> 0 | H19: 0 | I19: =IF(ABS(G19)<=H19,"Match","Check") -> Match
A20: 19 | B20: Lung (female): significant APC increases | C20: Count in Cancer Trends (APC) | D20: =COUNTIFS('Cancer Trends (APC)'!A2:A153,"Lung",'Cancer Trends (APC)'!B2:B153,"Female",'Cancer Trends (APC)'!F2:F153,"Yes") -> 11 | E20: Paper text | F20: 11 | G20: =D20-F20 -> 0 | H20: 0 | I20: =IF(ABS(G20)<=H20,"Match","Check") -> Match
A21: 20 | B21: All sites (male): registries with rising trend | C21: Count APC > 0 | D21: =COUNTIFS('Cancer Trends (APC)'!A2:A153,"All sites",'Cancer Trends (APC)'!B2:B153,"Male",'Cancer Trends (APC)'!E2:E153,">0") -> 12 | E21: Paper text | F21: 12 | G21: =D21-F21 -> 0 | H21: 0 | I21: =IF(ABS(G21)<=H21,"Match","Check") -> Match
A22: 21 | B22: All sites (female): registries with rising trend | C22: Count APC > 0 | D22: =COUNTIFS('Cancer Trends (APC)'!A2:A153,"All sites",'Cancer Trends (APC)'!B2:B153,"Female",'Cancer Trends (APC)'!E2:E153,">0") -> 13 | E22: Paper text | F22: 13 | G22: =D22-F22 -> 0 | H22: 0 | I22: =IF(ABS(G22)<=H22,"Match","Check") -> Match
A23: 22 | B23: Gender ratio, Maharashtra | C23: Recomputed from population | D23: ='MH Socio-Health Profile'!E17 -> 929.4031 | E23: Fact sheet (printed) | F23: 929 | G23: =D23-F23 -> 0.40310344 | H23: 0.5 | I23: =IF(ABS(G23)<=H23,"Match","Check") -> Match | J23: Printed value is rounded.
A24: 23 | B24: Existing 2026 projection vs IJMR 2025 projection | C24: Sum of states, Predicted 2026 (Kumar 2026) | D24: ='State-wise Incidence'!F39 -> 1604194 | E24: IJMR 2022 projected 2025 (both sexes) | F24: ='India Trend 2015-2025'!E18 -> 1569793 | G24: =D24-F24 -> 34401 | I24: Info only | J24: Different target years (2026 vs 2025) and different models; shown for context only.
A25: 24 | B25: Fact-sheet map values vs JCO Table 1 | C25: Annual cases, crude rates and age-adjusted rates for the 7 Maharashtra PBCRs (fact sheet p3) | E25: JCO 2020 Table 1 | I25: Match (manual) | J25: All 7 registries x 2 sexes x 3 measures were compared by eye; no differences. The childhood-cancer map has no counterpart in JCO.
B27: Summary: checks passing | I27: =COUNTIF(I2:I25,"Match*")&" of "&COUNTA(I2:I25) -> 21 of 24

Sheet State-wise Incidence
A1: State/UT | B1: 2019 Observed | C1: 2020 Observed | D1: 2021 Observed | E1: 2022 Observed | F1: Predicted 2026 | G1: Predicted 2030 | H1: Predicted 2045 | I1: Region (NCRP zone) | J1: NCRP PBCR representation used for state estimates | K1: CAGR 2019-22 (observed) | L1: CAGR 2022-26 (projected) | M1: CAGR 2022-45 (projected) | N1: Share of all-India 2022 cases | O1: Projected 2045 / 2022 (x)
A2: Jammu and Kashmir | B2: 12396 | C2: 12726 | D2: 13060 | E2: 13395 | F2: 14857 | G2: 16475 | H2: 24277 | I2: North | J2: Pooled Rest of India | K2: =(E2/B2)^(1/3)-1 -> 0.026172527 | L2: =(F2/E2)^(1/4)-1 -> 0.026235659 | M2: =(H2/E2)^(1/23)-1 -> 0.026191377 | N2: =E2/E$39 -> 0.009165699 | O2: =H2/E2 -> 1.8123927
A3: Ladakh | B3: 279 | C3: 286 | D3: 294 | E3: 302 | F3: 336 | G3: 373 | H3: 556 | I3: North | J3: Pooled Rest of India | K3: =(E3/B3)^(1/3)-1 -> 0.026756781 | L3: =(F3/E3)^(1/4)-1 -> 0.027029891 | M3: =(H3/E3)^(1/23)-1 -> 0.026891807 | N3: =E3/E$39 -> 0.00020664734 | O3: =H3/E3 -> 1.8410596
A4: Himachal Pradesh | B4: 8589 | C4: 8799 | D4: 8978 | E4: 9164 | F4: 9992 | G4: 10887 | H4: 15021 | I4: North | J4: Pooled Rest of India | K4: =(E4/B4)^(1/3)-1 -> 0.021835122 | L4: =(F4/E4)^(1/4)-1 -> 0.021861028 | M4: =(H4/E4)^(1/23)-1 -> 0.021717973 | N4: =E4/E$39 -> 0.0062705835 | O4: =H4/E4 -> 1.6391314
A5: Punjab | B5: 37744 | C5: 38636 | D5: 39521 | E5: 40435 | F5: 44322 | G5: 48578 | H5: 68516 | I5: North | J5: Patiala | K5: =(E5/B5)^(1/3)-1 -> 0.023221934 | L5: =(F5/E5)^(1/4)-1 -> 0.023211648 | M5: =(H5/E5)^(1/23)-1 -> 0.023194093 | N5: =E5/E$39 -> 0.027668163 | O5: =H5/E5 -> 1.6944726
A6: Chandigarh | B6: 994 | C6: 1024 | D6: 1053 | E6: 1088 | F6: 1225 | G6: 1381 | H6: 2162 | I6: North | J6: Pooled Rest of India | K6: =(E6/B6)^(1/3)-1 -> 0.030577928 | L6: =(F6/E6)^(1/4)-1 -> 0.03009386 | M6: =(H6/E6)^(1/23)-1 -> 0.030306364 | N6: =E6/E$39 -> 0.00074447783 | O6: =H6/E6 -> 1.9871324
A7: Uttaranchal | B7: 11216 | C7: 11482 | D7: 11779 | E7: 12065 | F7: 13305 | G7: 14671 | H7: 21170 | I7: North | J7: Pooled Rest of India | K7: =(E7/B7)^(1/3)-1 -> 0.02462066 | L7: =(F7/E7)^(1/4)-1 -> 0.024759347 | M7: =(H7/E7)^(1/23)-1 -> 0.024748072 | N7: =E7/E$39 -> 0.0082556296 | O7: =H7/E7 -> 1.7546622
A8: Haryana | B8: 28453 | C8: 29219 | D8: 30015 | E8: 30851 | F8: 34356 | G8: 38269 | H8: 57344 | I8: North | J8: Pooled Rest of India | K8: =(E8/B8)^(1/3)-1 -> 0.027338887 | L8: =(F8/E8)^(1/4)-1 -> 0.027267 | M8: =(H8/E8)^(1/23)-1 -> 0.027318627 | N8: =E8/E$39 -> 0.021110189 | O8: =H8/E8 -> 1.8587404
A9: Delhi | B9: 24436 | C9: 25178 | D9: 25969 | E9: 26735 | F9: 30163 | G9: 34017 | H9: 53405 | I9: North | J9: Delhi | K9: =(E9/B9)^(1/3)-1 -> 0.030425721 | L9: =(F9/E9)^(1/4)-1 -> 0.030620048 | M9: =(H9/E9)^(1/23)-1 -> 0.030541042 | N9: =E9/E$39 -> 0.018293764 | O9: =H9/E9 -> 1.9975687
A10: Rajasthan | B10: 69156 | C10: 70987 | D10: 72825 | E10: 74725 | F10: 82850 | G10: 91854 | H10: 135242 | I10: Central | J10: Pooled Rest of India | K10: =(E10/B10)^(1/3)-1 -> 0.026152764 | L10: =(F10/E10)^(1/4)-1 -> 0.026140071 | M10: =(H10/E10)^(1/23)-1 -> 0.026129056 | N10: =E10/E$39 -> 0.051131531 | O10: =H10/E10 -> 1.8098628
A11: Uttar Pradesh | B11: 196652 | C11: 201319 | D11: 206088 | E11: 210958 | F11: 231671 | G11: 254411 | H11: 361432 | I11: Central | J11: Pooled Rest of India | K11: =(E11/B11)^(1/3)-1 -> 0.02368391 | L11: =(F11/E11)^(1/4)-1 -> 0.023691079 | M11: =(H11/E11)^(1/23)-1 -> 0.023685491 | N11: =E11/E$39 -> 0.14435069 | O11: =H11/E11 -> 1.7132889
A12: Bihar | B12: 101014 | C12: 103711 | D12: 106435 | E12: 109274 | F12: 121330 | G12: 134721 | H12: 199495 | I12: East | J12: Pooled Rest of India | K12: =(E12/B12)^(1/3)-1 -> 0.026546021 | L12: =(F12/E12)^(1/4)-1 -> 0.026509184 | M12: =(H12/E12)^(1/23)-1 -> 0.026516364 | N12: =E12/E$39 -> 0.074772123 | O12: =H12/E12 -> 1.8256401
A13: Sikkim | B13: 443 | C13: 445 | D13: 465 | E13: 496 | F13: 570 | G13: 664 | H13: 1180 | I13: North East | J13: Sikkim state | K13: =(E13/B13)^(1/3)-1 -> 0.038387178 | L13: =(F13/E13)^(1/4)-1 -> 0.035376479 | M13: =(H13/E13)^(1/23)-1 -> 0.038401321 | N13: =E13/E$39 -> 0.0003393943 | O13: =H13/E13 -> 2.3790323
... A38: Andaman and Nicobar Islands | B38: 357 | C38: 366 | D38: 380 | E38: 393 | F38: 447 | G38: 509 | H38: 830 | I38: South | J38: Pooled South | K38: =(E38/B38)^(1/3)-1 -> 0.032542916 | L38: =(F38/E38)^(1/4)-1 -> 0.032710858 | M38: =(H38/E38)^(1/23)-1 -> 0.033039107 | N38: =E38/E$39 -> 0.00026891525 | O38: =H38/E38 -> 2.1119593
A39: All India (sum of 37 states/UTs) | B39: =SUM(B2:B38) -> 1358415 | C39: =SUM(C2:C38) -> 1392179 | D39: =SUM(D2:D38) -> 1426447 | E39: =SUM(E2:E38) -> 1461427 | F39: =SUM(F2:F38) -> 1604194 | G39: =SUM(G2:G38) -> 1766486 | H39: =SUM(H2:H38) -> 2547851 | K39: =(E39/B39)^(1/3)-1 -> 0.024664176 | L39: =(F39/E39)^(1/4)-1 -> 0.023575637 | M39: =(H39/E39)^(1/23)-1 -> 0.024461206 | N39: =E39/E$39 -> 1 | O39: =H39/E39 -> 1.7433994
A40: Source note | B40: Values transcribed from Table 1 in the uploaded PDF. State/UT labels are retained as printed in the source (e.g., Uttaranchal, Orissa, Pondicherry, Daman).
A41: Added columns | B41: Columns I-J: region and PBCR representation from Supplementary Table I of the IJMR 2022 paper (Sathishkumar et al.). Columns K-O (green headers) are formulas derived from columns B-H; row 39 sums the 37 states/UTs.
A42: Important caveat | B42: The all-India sums for "2020 Observed" (1,392,179) and "2022 Observed" (1,461,427) equal the NCRP national ESTIMATES published in the JCO 2020 and IJMR 2022 papers; Maharashtra 2020 (116,121) equals the NCRP Maharashtra projection (54,961 + 61,160). These columns are therefore model-based NCRP estimates, not raw registry counts. See sheet Cross-Validation.

Sheet India Sites 2022
A1: Site (ICD-10 group) | B1: Level | C1: Parent group | D1: Male - estimated cases 2022 | E1: Male - crude rate /100,000 | F1: Male - age-adjusted rate /100,000 | G1: Male - cum. risk 0-74 (1 in N) | H1: Female - estimated cases 2022 | I1: Female - crude rate /100,000 | J1: Female - age-adjusted rate /100,000 | K1: Female - cum. risk 0-74 (1 in N) | L1: Both sexes - estimated cases 2022 | M1: Both sexes - crude rate /100,000 | N1: Both sexes - age-adjusted rate /100,000 | O1: Both sexes - cum. risk 0-74 (1 in N) | P1: Share of all-site cases (both sexes) | Q1: Female : male case ratio | R1: Both sexes - 2020 projected cases (JCO) | S1: Change in cases 2020 to 2022
A2: All sites | B2: Total | D2: 712176 | E2: 95.6 | F2: 105.7 | G2: 9 | H2: 749251 | I2: 105.4 | J2: 109 | K2: 9 | L2: 1461427 | M2: 100.4 | N2: 107 | O2: 9 | P2: =L2/L$2 -> 1 | Q2: =IF(AND(ISNUMBER(D2),ISNUMBER(H2)),H2/D2,"") -> 1.0520588 | R2: ='India Sites 2020'!J2 -> 1392179 | S2: =L2/R2-1 -> 0.04974073
A3: Oral cavity and pharynx | B3: Group | D3: 145844 | E3: 19.6 | F3: 21.2 | G3: 42 | H3: 52594 | I3: 7.4 | J3: 7.7 | K3: 115 | L3: 198438 | M3: 13.6 | N3: 14.4 | O3: 62 | P3: =L3/L$2 -> 0.13578372 | Q3: =IF(AND(ISNUMBER(D3),ISNUMBER(H3)),H3/D3,"") -> 0.36061819 | R3: ='India Sites 2020'!J3 -> 188969 | S3: =L3/R3-1 -> 0.050108748
A4: Tongue | B4: Site | C4: Oral cavity and pharynx | D4: 41845 | E4: 5.6 | F4: 6 | G4: 147 | H4: 14611 | I4: 2.1 | J4: 2.1 | K4: 400 | L4: 56456 | M4: 3.9 | N4: 4.1 | O4: 215 | P4: =L4/L$2 -> 0.038630736 | Q4: =IF(AND(ISNUMBER(D4),ISNUMBER(H4)),H4/D4,"") -> 0.34916955 | R4: ='India Sites 2020'!J4 -> 53772 | S4: =L4/R4-1 -> 0.049914454
A5: Mouth | B5: Site | C5: Oral cavity and pharynx | D5: 60164 | E5: 8.1 | F5: 8.6 | G5: 103 | H5: 23675 | I5: 3.3 | J5: 3.5 | K5: 241 | L5: 83839 | M5: 5.8 | N5: 6.1 | O5: 144 | P5: =L5/L$2 -> 0.057367901 | Q5: =IF(AND(ISNUMBER(D5),ISNUMBER(H5)),H5/D5,"") -> 0.39350775 | R5: ='India Sites 2020'!J5 -> 79863 | S5: =L5/R5-1 -> 0.049785257
A6: Pharynx | B6: Site | C6: Oral cavity and pharynx | D6: 3177 | E6: 0.4 | F6: 0.5 | G6: 1793 | H6: 1168 | I6: 0.2 | J6: 0.2 | K6: 5482 | L6: 4345 | M6: 0.3 | N6: 0.3 | O6: 2704 | P6: =L6/L$2 -> 0.0029731215 | Q6: =IF(AND(ISNUMBER(D6),ISNUMBER(H6)),H6/D6,"") -> 0.36764243 | R6: ='India Sites 2020'!J6 -> 4131 | S6: =L6/R6-1 -> 0.051803437
A7: Other oral cavity | B7: Site | C7: Oral cavity and pharynx | D7: 40658 | E7: 5.5 | F7: 6.1 | G7: 137 | H7: 13140 | I7: 1.8 | J7: 1.9 | K7: 475 | L7: 53798 | M7: 3.7 | N7: 4 | O7: 213 | P7: =L7/L$2 -> 0.036811965 | Q7: =IF(AND(ISNUMBER(D7),ISNUMBER(H7)),H7/D7,"") -> 0.32318363 | R7: ='India Sites 2020'!J7 -> 51203 | S7: =L7/R7-1 -> 0.050680624
A8: Digestive system | B8: Group | D8: 172025 | E8: 23.1 | F8: 25.9 | G8: 32 | H8: 116029 | I8: 16.3 | J8: 17 | K8: 50 | L8: 288054 | M8: 19.8 | N8: 21.4 | O8: 39 | P8: =L8/L$2 -> 0.19710461 | Q8: =IF(AND(ISNUMBER(D8),ISNUMBER(H8)),H8/D8,"") -> 0.67448917 | R8: ='India Sites 2020'!J8 -> 273982 | S8: =L8/R8-1 -> 0.051361038
A9: Oesophagus | B9: Site | C9: Digestive system | D9: 34272 | E9: 4.6 | F9: 5.2 | G9: 159 | H9: 21300 | I9: 3 | J9: 3.1 | K9: 263 | L9: 55572 | M9: 3.8 | N9: 4.2 | O9: 198 | P9: =L9/L$2 -> 0.038025847 | Q9: =IF(AND(ISNUMBER(D9),ISNUMBER(H9)),H9/D9,"") -> 0.6214986 | R9: ='India Sites 2020'!J9 -> 52828 | S9: =L9/R9-1 -> 0.051942152
A10: Stomach | B10: Site | C10: Digestive system | D10: 34353 | E10: 4.6 | F10: 5.2 | G10: 160 | H10: 18353 | I10: 2.6 | J10: 2.7 | K10: 319 | L10: 52706 | M10: 3.6 | N10: 3.9 | O10: 213 | P10: =L10/L$2 -> 0.03606475 | Q10: =IF(AND(ISNUMBER(D10),ISNUMBER(H10)),H10/D10,"") -> 0.53424737 | R10: ='India Sites 2020'!J10 -> 50143 | S10: =L10/R10-1 -> 0.051113814
A11: Small intestine | B11: Site | C11: Digestive system | D11: 2255 | E11: 0.3 | F11: 0.3 | G11: 2498 | H11: 1533 | I11: 0.2 | J11: 0.2 | K11: 3877 | L11: 3788 | M11: 0.3 | N11: 0.3 | O11: 3041 | P11: =L11/L$2 -> 0.0025919871 | Q11: =IF(AND(ISNUMBER(D11),ISNUMBER(H11)),H11/D11,"") -> 0.67982262 | R11: ='India Sites 2020'!J11 -> 3606 | S11: =L11/R11-1 -> 0.050471436
A12: Colon | B12: Site | C12: Digestive system | D12: 21595 | E12: 2.9 | F12: 3.2 | G12: 260 | H12: 16512 | I12: 2.3 | J12: 2.4 | K12: 348 | L12: 38107 | M12: 2.6 | N12: 2.8 | O12: 298 | P12: =L12/L$2 -> 0.026075199 | Q12: =IF(AND(ISNUMBER(D12),ISNUMBER(H12)),H12/D12,"") -> 0.76462144 | R12: ='India Sites 2020'!J12 -> 36257 | S12: =L12/R12-1 -> 0.05102463
A13: Rectum | B13: Site | C13: Digestive system | D13: 22985 | E13: 3.1 | F13: 3.4 | G13: 244 | H13: 15767 | I13: 2.2 | J13: 2.3 | K13: 372 | L13: 38752 | M13: 2.7 | N13: 2.8 | O13: 295 | P13: =L13/L$2 -> 0.026516549 | Q13: =IF(AND(ISNUMBER(D13),ISNUMBER(H13)),H13/D13,"") -> 0.68596911 | R13: ='India Sites 2020'!J13 -> 36900 | S13: =L13/R13-1 -> 0.050189702
A14: Anus, anal canal | B14: Site | C14: Digestive system | D14: 3037 | E14: 0.4 | F14: 0.4 | G14: 1865 | H14: 2131 | I14: 0.3 | J14: 0.3 | K14: 2682 | L14: 5168 | M14: 0.4 | N14: 0.4 | O14: 2200 | P14: =L14/L$2 -> 0.0035362697 | Q14: =IF(AND(ISNUMBER(D14),ISNUMBER(H14)),H14/D14,"") -> 0.70167929 | R14: ='India Sites 2020'!J14 -> 4925 | S14: =L14/R14-1 -> 0.049340102
A15: Liver and intrahepatic bile duct | B15: Site | C15: Digestive system | D15: 28020 | E15: 3.8 | F15: 4.3 | G15: 189 | H15: 11306 | I15: 1.6 | J15: 1.7 | K15: 514 | L15: 39326 | M15: 2.7 | N15: 3 | O15: 276 | P15: =L15/L$2 -> 0.026909315 | Q15: =IF(AND(ISNUMBER(D15),ISNUMBER(H15)),H15/D15,"") -> 0.4034975 | R15: ='India Sites 2020'!J15 -> 37410 | S15: =L15/R15-1 -> 0.051216252
A16: Gallbladder and other biliary | B16: Site | C16: Digestive system | D16: 12997 | E16: 1.7 | F16: 1.9 | G16: 423 | H16: 20570 | I16: 2.9 | J16: 3 | K16: 283 | L16: 33567 | M16: 2.3 | N16: 2.5 | O16: 339 | P16: =L16/L$2 -> 0.022968646 | Q16: =IF(AND(ISNUMBER(D16),ISNUMBER(H16)),H16/D16,"") -> 1.5826729 | R16: ='India Sites 2020'!J16 -> 31895 | S16: =L16/R16-1 -> 0.05242201
A17: Pancreas | B17: Site | C17: Digestive system | D17: 12511 | E17: 1.7 | F17: 1.9 | G17: 429 | H17: 8557 | I17: 1.2 | J17: 1.3 | K17: 656 | L17: 21068 | M17: 1.4 | N17: 1.6 | O17: 519 | P17: =L17/L$2 -> 0.014416047 | Q17: =IF(AND(ISNUMBER(D17),ISNUMBER(H17)),H17/D17,"") -> 0.68395812 | R17: ='India Sites 2020'!J17 -> 20018 | S17: =L17/R17-1 -> 0.052452792
A18: Respiratory system | B18: Group | D18: 108848 | E18: 14.6 | F18: 16.2 | G18: 48 | H18: 34214 | I18: 4.8 | J18: 4.8 | K18: 165 | L18: 143062 | M18: 9.8 | N18: 10.4 | O18: 74 | P18: =L18/L$2 -> 0.097891992 | Q18: =IF(AND(ISNUMBER(D18),ISNUMBER(H18)),H18/D18,"") -> 0.31432824 | R18: ='India Sites 2020'!J18 -> 136032 | S18: =L18/R18-1 -> 0.051679017
A19: Larynx | B19: Site | C19: Respiratory system | D19: 28542 | E19: 3.8 | F19: 4.3 | G19: 184 | H19: 3498 | I19: 0.5 | J19: 0.5 | K19: 1629 | L19: 32040 | M19: 2.2 | N19: 2.4 | O19: 331 | P19: =L19/L$2 -> 0.021923777 | Q19: =IF(AND(ISNUMBER(D19),ISNUMBER(H19)),H19/D19,"") -> 0.12255623 | R19: ='India Sites 2020'!J19 -> 30462 | S19: =L19/R19-1 -> 0.051802245
A20: Lung and bronchus | B20: Site | C20: Respiratory system | D20: 75474 | E20: 10.1 | F20: 11.6 | G20: 67 | H20: 27897 | I20: 3.9 | J20: 4.1 | K20: 209 | L20: 103371 | M20: 7.1 | N20: 7.8 | O20: 101 | P20: =L20/L$2 -> 0.070732921 | Q20: =IF(AND(ISNUMBER(D20),ISNUMBER(H20)),H20/D20,"") -> 0.36962398 | R20: ='India Sites 2020'!J20 -> 98278 | S20: =L20/R20-1 -> 0.051822381
A21: Other respiratory organs | B21: Site | C21: Respiratory system | D21: 4832 | E21: 0.6 | F21: 0.3 | G21: 1274 | H21: 2819 | I21: 0.4 | J21: 0.2 | K21: 2149 | L21: 7651 | M21: 0.5 | N21: 0.2 | O21: 1602 | P21: =L21/L$2 -> 0.005235294 | Q21: =IF(AND(ISNUMBER(D21),ISNUMBER(H21)),H21/D21,"") -> 0.58340232 | R21: ='India Sites 2020'!J21 -> 7292 | S21: =L21/R21-1 -> 0.049232035
A22: Bones and joints | B22: Group | D22: 8426 | E22: 1.1 | F22: 1.1 | G22: 1011 | H22: 6087 | I22: 0.9 | J22: 0.8 | K22: 1365 | L22: 14513 | M22: 1 | N22: 1 | O22: 1160 | P22: =L22/L$2 -> 0.0099307047 | Q22: =IF(AND(ISNUMBER(D22),ISNUMBER(H22)),H22/D22,"") -> 0.72240684 | R22: ='India Sites 2020'!J22 -> 13955 | S22: =L22/R22-1 -> 0.039985668
A23: Soft tissue | B23: Group | D23: 8380 | E23: 1.1 | F23: 1.2 | G23: 844 | H23: 6895 | I23: 1 | J23: 1 | K23: 1050 | L23: 15275 | M23: 1 | N23: 1.1 | O23: 936 | P23: =L23/L$2 -> 0.010452113 | Q23: =IF(AND(ISNUMBER(D23),ISNUMBER(H23)),H23/D23,"") -> 0.82279236 | R23: ='India Sites 2020'!J23 -> 14637 | S23: =L23/R23-1 -> 0.043588167
A24: Skin (excluding basal and squamous) | B24: Group | D24: 11745 | E24: 1.6 | F24: 1.7 | G24: 510 | H24: 9412 | I24: 1.3 | J24: 1.4 | K24: 641 | L24: 21157 | M24: 1.5 | N24: 1.5 | O24: 569 | P24: =L24/L$2 -> 0.014476946 | Q24: =IF(AND(ISNUMBER(D24),ISNUMBER(H24)),H24/D24,"") -> 0.80136228 | R24: ='India Sites 2020'!J24 -> 20165 | S24: =L24/R24-1 -> 0.049194148
A25: Melanoma of the skin | B25: Site | C25: Skin (excluding basal and squamous) | D25: 3145 | E25: 0.4 | F25: 0.5 | G25: 1909 | H25: 2479 | I25: 0.3 | J25: 0.4 | K25: 2288 | L25: 5624 | M25: 0.4 | N25: 0.4 | O25: 2081 | P25: =L25/L$2 -> 0.0038482935 | Q25: =IF(AND(ISNUMBER(D25),ISNUMBER(H25)),H25/D25,"") -> 0.78823529 | R25: ='India Sites 2020'!J25 -> 5367 | S25: =L25/R25-1 -> 0.047885225
A26: Other non-epithelial skin | B26: Site | C26: Skin (excluding basal and squamous) | D26: 8600 | E26: 1.2 | F26: 1.3 | G26: 696 | H26: 6933 | I26: 1 | J26: 1 | K26: 891 | L26: 15533 | M26: 1.1 | N26: 1.1 | O26: 782 | P26: =L26/L$2 -> 0.010628653 | Q26: =IF(AND(ISNUMBER(D26),ISNUMBER(H26)),H26/D26,"") -> 0.80616279 | R26: ='India Sites 2020'!J26 -> 14798 | S26: =L26/R26-1 -> 0.049668874
A27: Breast | B27: Group | D27: 5649 | E27: 0.8 | F27: 0.8 | G27: 1021 | H27: 216108 | I27: 30.4 | J27: 31.2 | K27: 29 | L27: 221757 | M27: 15.2 | N27: 16 | O27: 56 | P27: =L27/L$2 -> 0.15174005 | Q27: =IF(AND(ISNUMBER(D27),ISNUMBER(H27)),H27/D27,"") -> 38.255975 | R27: ='India Sites 2020'!J27 -> 210801 | S27: =L27/R27-1 -> 0.051973188
A28: Genital system | B28: Group | D28: 54625 | E28: 7.3 | F28: 8.4 | G28: 105 | H28: 163694 | I28: 23 | J28: 23.9 | K28: 37 | L28: 218319 | M28: 15 | N28: 16 | O28: 53 | P28: =L28/L$2 -> 0.14938755 | Q28: =IF(AND(ISNUMBER(D28),ISNUMBER(H28)),H28/D28,"") -> 2.9966865 | R28: ='India Sites 2020'!J28 -> 207624 | S28: =L28/R28-1 -> 0.051511386
A29: Uterine cervix | B29: Site | C29: Genital system | H29: 79103 | I29: 11.1 | J29: 11.6 | K29: 75 | L29: 79103 | M29: 11.1 | N29: 11.6 | O29: 75 | P29: =L29/L$2 -> 0.054127233 | Q29: =IF(AND(ISNUMBER(D29),ISNUMBER(H29)),H29/D29,"") | R29: ='India Sites 2020'!J29 -> 75209 | S29: =L29/R29-1 -> 0.051775718
A30: Uterine corpus | B30: Site | C30: Genital system | H30: 27922 | I30: 3.9 | J30: 4.2 | K30: 190 | L30: 27922 | M30: 3.9 | N30: 4.2 | O30: 190 | P30: =L30/L$2 -> 0.019105983 | Q30: =IF(AND(ISNUMBER(D30),ISNUMBER(H30)),H30/D30,"") | R30: ='India Sites 2020'!J30 -> 26514 | S30: =L30/R30-1 -> 0.053104021
A31: Ovary | B31: Site | C31: Genital system | H31: 46126 | I31: 6.5 | J31: 6.7 | K31: 133 | L31: 46126 | M31: 6.5 | N31: 6.7 | O31: 133 | P31: =L31/L$2 -> 0.031562302 | Q31: =IF(AND(ISNUMBER(D31),ISNUMBER(H31)),H31/D31,"") | R31: ='India Sites 2020'!J31 -> 43886 | S31: =L31/R31-1 -> 0.051041334
A32: Vulva | B32: Site | C32: Genital system | H32: 2258 | I32: 0.3 | J32: 0.3 | K32: 2454 | L32: 2258 | M32: 0.3 | N32: 0.3 | O32: 2454 | P32: =L32/L$2 -> 0.0015450652 | Q32: =IF(AND(ISNUMBER(D32),ISNUMBER(H32)),H32/D32,"") | R32: ='India Sites 2020'!J32 -> 2138 | S32: =L32/R32-1 -> 0.056127222
A33: Vagina and other genital, female | B33: Site | C33: Genital system | H33: 7961 | I33: 1.1 | J33: 1.2 | K33: 747 | L33: 7961 | M33: 1.1 | N33: 1.2 | O33: 747 | P33: =L33/L$2 -> 0.0054474154 | Q33: =IF(AND(ISNUMBER(D33),ISNUMBER(H33)),H33/D33,"") | R33: ='India Sites 2020'!J33 -> 7570 | S33: =L33/R33-1 -> 0.051651255
A34: Placenta | B34: Site | C34: Genital system | H34: 324 | I34: 0 | J34: 0 | K34: 31252 | L34: 324 | M34: 0 | N34: 0 | O34: 31252 | P34: =L34/L$2 -> 0.00022170112 | Q34: =IF(AND(ISNUMBER(D34),ISNUMBER(H34)),H34/D34,"") | R34: ='India Sites 2020'!J34 -> 313 | S34: =L34/R34-1 -> 0.03514377
A35: Prostate | B35: Site | C35: Genital system | D35: 43691 | E35: 5.9 | F35: 6.8 | G35: 125 | L35: 43691 | M35: 5.9 | N35: 6.8 | O35: 125 | P35: =L35/L$2 -> 0.029896122 | Q35: =IF(AND(ISNUMBER(D35),ISNUMBER(H35)),H35/D35,"") | R35: ='India Sites 2020'!J35 -> 41532 | S35: =L35/R35-1 -> 0.051984012
A36: Testis | B36: Site | C36: Genital system | D36: 4521 | E36: 0.6 | F36: 0.6 | G36: 2092 | L36: 4521 | M36: 0.6 | N36: 0.6 | O36: 2092 | P36: =L36/L$2 -> 0.0030935517 | Q36: =IF(AND(ISNUMBER(D36),ISNUMBER(H36)),H36/D36,"") | R36: ='India Sites 2020'!J36 -> 4352 | S36: =L36/R36-1 -> 0.038832721
A37: Penis and other genital, male | B37: Site | C37: Genital system | D37: 6413 | E37: 0.8 | F37: 1 | G37: 917 | L37: 6413 | M37: 0.8 | N37: 1 | O37: 917 | P37: =L37/L$2 -> 0.0043881768 | Q37: =IF(AND(ISNUMBER(D37),ISNUMBER(H37)),H37/D37,"") | R37: ='India Sites 2020'!J37 -> 6110 | S37: =L37/R37-1 -> 0.049590835
A38: Urinary system | B38: Group | D38: 34942 | E38: 4.7 | F38: 5.3 | G38: 158 | H38: 11861 | I38: 1.7 | J38: 1.8 | K38: 500 | L38: 46803 | M38: 3.2 | N38: 3.5 | O38: 240 | P38: =L38/L$2 -> 0.032025548 | Q38: =IF(AND(ISNUMBER(D38),ISNUMBER(H38)),H38/D38,"") -> 0.33944823 | R38: ='India Sites 2020'!J38 -> 44534 | S38: =L38/R38-1 -> 0.050949836
A39: Urinary bladder | B39: Site | C39: Urinary system | D39: 21523 | E39: 2.9 | F39: 3.3 | G39: 250 | H39: 5713 | I39: 0.8 | J39: 0.8 | K39: 1011 | L39: 27236 | M39: 1.9 | N39: 2 | O39: 402 | P39: =L39/L$2 -> 0.018636579 | Q39: =IF(AND(ISNUMBER(D39),ISNUMBER(H39)),H39/D39,"") -> 0.26543697 | R39: ='India Sites 2020'!J39 -> 25873 | S39: =L39/R39-1 -> 0.0526804
A40: Kidney and renal pelvis | B40: Site | C40: Urinary system | D40: 12963 | E40: 1.7 | F40: 2 | G40: 442 | H40: 5930 | I40: 0.8 | J40: 0.9 | K40: 1036 | L40: 18893 | M40: 1.3 | N40: 1.4 | O40: 619 | P40: =L40/L$2 -> 0.012927775 | Q40: =IF(AND(ISNUMBER(D40),ISNUMBER(H40)),H40/D40,"") -> 0.45745584 | R40: ='India Sites 2020'!J40 -> 18020 | S40: =L40/R40-1 -> 0.048446171
A41: Ureter and other urinary organs | B41: Site | C41: Urinary system | D41: 456 | E41: 0.1 | F41: 0.1 | G41: 10755 | H41: 218 | I41: 0 | J41: 0 | K41: 21739 | L41: 674 | M41: 0 | N41: 0.1 | O41: 14422 | P41: =L41/L$2 -> 0.00046119307 | Q41: =IF(AND(ISNUMBER(D41),ISNUMBER(H41)),H41/D41,"") -> 0.47807018 | R41: ='India Sites 2020'!J41 -> 641 | S41: =L41/R41-1 -> 0.051482059
A42: Eye and orbit | B42: Group | D42: 1326 | E42: 0.2 | F42: 0.2 | G42: 6887 | H42: 977 | I42: 0.1 | J42: 0.2 | K42: 9049 | L42: 2303 | M42: 0.2 | N42: 0.2 | O42: 7799 | P42: =L42/L$2 -> 0.001575857 | Q42: =IF(AND(ISNUMBER(D42),ISNUMBER(H42)),H42/D42,"") -> 0.73680241 | R42: ='India Sites 2020'!J42 -> 2257 | S42: =L42/R42-1 -> 0.020381037
A43: Brain and other nervous system | B43: Group | D43: 20811 | E43: 2.8 | F43: 2.9 | G43: 341 | H43: 13296 | I43: 1.9 | J43: 1.9 | K43: 546 | L43: 34107 | M43: 2.3 | N43: 2.4 | O43: 419 | P43: =L43/L$2 -> 0.023338148 | Q43: =IF(AND(ISNUMBER(D43),ISNUMBER(H43)),H43/D43,"") -> 0.63889289 | R43: ='India Sites 2020'!J43 -> 32729 | S43: =L43/R43-1 -> 0.042103333
A44: Endocrine system | B44: Group | D44: 9682 | E44: 1.3 | F44: 1.4 | G44: 708 | H44: 27847 | I44: 3.9 | J44: 3.8 | K44: 280 | L44: 37529 | M44: 2.6 | N44: 2.5 | O44: 402 | P44: =L44/L$2 -> 0.025679695 | Q44: =IF(AND(ISNUMBER(D44),ISNUMBER(H44)),H44/D44,"") -> 2.876162 | R44: ='India Sites 2020'!J44 -> 35928 | S44: =L44/R44-1 -> 0.044561345
A45: Thyroid | B45: Site | C45: Endocrine system | D45: 8967 | E45: 1.2 | F45: 1.2 | G45: 758 | H45: 27253 | I45: 3.8 | J45: 3.7 | K45: 285 | L45: 36220 | M45: 2.5 | N45: 2.4 | O45: 416 | P45: =L45/L$2 -> 0.024783995 | Q45: =IF(AND(ISNUMBER(D45),ISNUMBER(H45)),H45/D45,"") -> 3.039255 | R45: ='India Sites 2020'!J45 -> 34665 | S45: =L45/R45-1 -> 0.044857926
A46: Adrenal gland | B46: Site | C46: Endocrine system | D46: 715 | E46: 0.1 | F46: 0.1 | G46: 10776 | H46: 594 | I46: 0.1 | J46: 0.1 | K46: 13920 | L46: 1309 | M46: 0.1 | N46: 0.1 | O46: 12146 | P46: =L46/L$2 -> 0.00089569989 | Q46: =IF(AND(ISNUMBER(D46),ISNUMBER(H46)),H46/D46,"") -> 0.83076923 | R46: ='India Sites 2020'!J46 -> 1263 | S46: =L46/R46-1 -> 0.036421219
A47: Lymphoma | B47: Group | D47: 34116 | E47: 4.6 | F47: 4.9 | G47: 197 | H47: 21233 | I47: 3 | J47: 3.1 | K47: 296 | L47: 55349 | M47: 3.8 | N47: 4 | O47: 236 | P47: =L47/L$2 -> 0.037873257 | Q47: =IF(AND(ISNUMBER(D47),ISNUMBER(H47)),H47/D47,"") -> 0.6223766 | R47: ='India Sites 2020'!J47 -> 52942 | S47: =L47/R47-1 -> 0.045464848
A48: Hodgkin lymphoma | B48: Site | C48: Lymphoma | D48: 7561 | E48: 1 | F48: 1 | G48: 1150 | H48: 4113 | I48: 0.6 | J48: 0.6 | K48: 1866 | L48: 11674 | M48: 0.8 | N48: 0.8 | O48: 1416 | P48: =L48/L$2 -> 0.0079880829 | Q48: =IF(AND(ISNUMBER(D48),ISNUMBER(H48)),H48/D48,"") -> 0.54397566 | R48: ='India Sites 2020'!J48 -> 11230 | S48: =L48/R48-1 -> 0.039536955
A49: Non-Hodgkin lymphoma | B49: Site | C49: Lymphoma | D49: 26497 | E49: 3.6 | F49: 3.8 | G49: 238 | H49: 17070 | I49: 2.4 | J49: 2.5 | K49: 352 | L49: 43567 | M49: 3 | N49: 3.2 | O49: 284 | P49: =L49/L$2 -> 0.029811274 | Q49: =IF(AND(ISNUMBER(D49),ISNUMBER(H49)),H49/D49,"") -> 0.64422387 | R49: ='India Sites 2020'!J49 -> 41607 | S49: =L49/R49-1 -> 0.047107458
A50: Malignant immunoproliferative diseases | B50: Group | D50: 58 | E50: 0 | F50: 0 | G50: 103646 | H50: 50 | I50: 0 | J50: 0 | K50: 163299 | L50: 108 | M50: 0 | N50: 0 | O50: 127221 | P50: =L50/L$2 -> 7.3900373e-05 | Q50: =IF(AND(ISNUMBER(D50),ISNUMBER(H50)),H50/D50,"") -> 0.86206897 | R50: ='India Sites 2020'!J50 -> 105 | S50: =L50/R50-1 -> 0.028571429
A51: Multiple myeloma | B51: Group | D51: 11261 | E51: 1.5 | F51: 1.7 | G51: 465 | H51: 8165 | I51: 1.1 | J51: 1.2 | K51: 646 | L51: 19426 | M51: 1.3 | N51: 1.5 | O51: 541 | P51: =L51/L$2 -> 0.013292487 | Q51: =IF(AND(ISNUMBER(D51),ISNUMBER(H51)),H51/D51,"") -> 0.72506882 | R51: ='India Sites 2020'!J51 -> 18481 | S51: =L51/R51-1 -> 0.051133597
A52: Leukaemia | B52: Group | D52: 33604 | E52: 4.5 | F52: 4.8 | G52: 239 | H52: 21969 | I52: 3.1 | J52: 3.2 | K52: 352 | L52: 55573 | M52: 3.8 | N52: 4 | O52: 284 | P52: =L52/L$2 -> 0.038026532 | Q52: =IF(AND(ISNUMBER(D52),ISNUMBER(H52)),H52/D52,"") -> 0.65376146 | R52: ='India Sites 2020'!J52 -> 53613 | S52: =L52/R52-1 -> 0.036558297
A53: Lymphoid leukaemia | B53: Site | C53: Leukaemia | D53: 14546 | E53: 2 | F53: 2.1 | G53: 609 | H53: 7638 | I53: 1.1 | J53: 1.2 | K53: 1137 | L53: 22184 | M53: 1.5 | N53: 1.7 | O53: 790 | P53: =L53/L$2 -> 0.015179684 | Q53: =IF(AND(ISNUMBER(D53),ISNUMBER(H53)),H53/D53,"") -> 0.52509281 | R53: ='India Sites 2020'!J53 -> 21578 | S53: =L53/R53-1 -> 0.02808416
A54: Myeloid leukaemia | B54: Site | C54: Leukaemia | D54: 15531 | E54: 2.1 | F54: 2.2 | G54: 474 | H54: 11788 | I54: 1.7 | J54: 1.7 | K54: 616 | L54: 27319 | M54: 1.9 | N54: 1.9 | O54: 536 | P54: =L54/L$2 -> 0.018693373 | Q54: =IF(AND(ISNUMBER(D54),ISNUMBER(H54)),H54/D54,"") -> 0.75899813 | R54: ='India Sites 2020'!J54 -> 26188 | S54: =L54/R54-1 -> 0.04318772
A55: Leukaemia unspecified | B55: Site | C55: Leukaemia | D55: 3527 | E55: 0.5 | F55: 0.5 | G55: 2292 | H55: 2543 | I55: 0.4 | J55: 0.4 | K55: 2974 | L55: 6070 | M55: 0.4 | N55: 0.4 | O55: 2585 | P55: =L55/L$2 -> 0.0041534747 | Q55: =IF(AND(ISNUMBER(D55),ISNUMBER(H55)),H55/D55,"") -> 0.72100936 | R55: ='India Sites 2020'!J55 -> 5847 | S55: =L55/R55-1 -> 0.038139217
A56: Other and unspecified primary sites | B56: Group | D56: 50892 | E56: 6.8 | F56: 7.6 | G56: 114 | H56: 38870 | I56: 5.5 | J56: 5.7 | K56: 153 | L56: 89762 | M56: 6.2 | N56: 6.6 | O56: 131 | P56: =L56/L$2 -> 0.061420789 | Q56: =IF(AND(ISNUMBER(D56),ISNUMBER(H56)),H56/D56,"") -> 0.76377427 | R56: ='India Sites 2020'!J56 -> 85530 | S56: =L56/R56-1 -> 0.049479715
A58: Source: Sathishkumar K et al. Cancer incidence estimates for 2022 & projection for 2025. Indian J Med Res 2022;156:598-607, Table I. Blank = site not applicable to that sex. "Malig Imn.Prol D" in the source = malignant immunoproliferative diseases. Column R links to sheet India Sites 2020 (same row order).

Sheet India Sites 2020
A1: Site (ICD-10 group) | B1: Level | C1: Parent group | D1: Male - projected cases 2020 | E1: Male - crude rate /100,000 | F1: Male - cum. risk 0-74 (1 in N) | G1: Female - projected cases 2020 | H1: Female - crude rate /100,000 | I1: Female - cum. risk 0-74 (1 in N) | J1: Both sexes - projected cases 2020 | K1: Both sexes - crude rate /100,000 | L1: Both sexes - cum. risk 0-74 (1 in N) | M1: Share of all-site cases (both sexes) | N1: Female : male case ratio
A2: All sites | B2: Total | D2: 679421 | E2: 94.1 | F2: 9 | G2: 712758 | H2: 103.6 | I2: 9 | J2: 1392179 | K2: 98.7 | L2: 9 | M2: =J2/J$2 -> 1 | N2: =IF(AND(ISNUMBER(D2),ISNUMBER(G2)),G2/D2,"") -> 1.0490668
A3: Oral cavity and pharynx | B3: Group | D3: 139018 | E3: 19.2 | F3: 41 | G3: 49951 | H3: 7.3 | I3: 112 | J3: 188969 | K3: 13.4 | L3: 60 | M3: =J3/J$2 -> 0.13573614 | N3: =IF(AND(ISNUMBER(D3),ISNUMBER(G3)),G3/D3,"") -> 0.35931318
A4: Tongue | B4: Site | C4: Oral cavity and pharynx | D4: 39902 | E4: 5.5 | F4: 147 | G4: 13870 | H4: 2 | I4: 401 | J4: 53772 | K4: 3.8 | L4: 215 | M4: =J4/J$2 -> 0.038624344 | N4: =IF(AND(ISNUMBER(D4),ISNUMBER(G4)),G4/D4,"") -> 0.34760162
A5: Mouth | B5: Site | C5: Oral cavity and pharynx | D5: 57380 | E5: 7.9 | F5: 103 | G5: 22483 | H5: 3.3 | I5: 241 | J5: 79863 | K5: 5.7 | L5: 144 | M5: =J5/J$2 -> 0.057365468 | N5: =IF(AND(ISNUMBER(D5),ISNUMBER(G5)),G5/D5,"") -> 0.39182642
A6: Pharynx | B6: Site | C6: Oral cavity and pharynx | D6: 3029 | E6: 0.4 | F6: 1793 | G6: 1102 | H6: 0.2 | I6: 5475 | J6: 4131 | K6: 0.3 | L6: 2701 | M6: =J6/J$2 -> 0.0029672908 | N6: =IF(AND(ISNUMBER(D6),ISNUMBER(G6)),G6/D6,"") -> 0.36381644
A7: Other oral cavity | B7: Site | C7: Oral cavity and pharynx | D7: 38707 | E7: 5.4 | F7: 137 | G7: 12496 | H7: 1.8 | I7: 476 | J7: 51203 | K7: 3.6 | L7: 213 | M7: =J7/J$2 -> 0.036779035 | N7: =IF(AND(ISNUMBER(D7),ISNUMBER(G7)),G7/D7,"") -> 0.32283566
A8: Digestive system | B8: Group | D8: 163845 | E8: 22.7 | F8: 32 | G8: 110137 | H8: 16 | I8: 50 | J8: 273982 | K8: 19.4 | L8: 39 | M8: =J8/J$2 -> 0.19680084 | N8: =IF(AND(ISNUMBER(D8),ISNUMBER(G8)),G8/D8,"") -> 0.67220239
A9: Oesophagus | B9: Site | C9: Digestive system | D9: 32622 | E9: 4.5 | F9: 159 | G9: 20206 | H9: 2.9 | I9: 264 | J9: 52828 | K9: 3.7 | L9: 198 | M9: =J9/J$2 -> 0.03794627 | N9: =IF(AND(ISNUMBER(D9),ISNUMBER(G9)),G9/D9,"") -> 0.61939795
A10: Stomach | B10: Site | C10: Digestive system | D10: 32713 | E10: 4.5 | F10: 160 | G10: 17430 | H10: 2.5 | I10: 319 | J10: 50143 | K10: 3.6 | L10: 213 | M10: =J10/J$2 -> 0.036017639 | N10: =IF(AND(ISNUMBER(D10),ISNUMBER(G10)),G10/D10,"") -> 0.5328157
A11: Small intestine | B11: Site | C11: Digestive system | D11: 2155 | E11: 0.3 | F11: 2492 | G11: 1451 | H11: 0.2 | I11: 3901 | J11: 3606 | K11: 0.3 | L11: 3044 | M11: =J11/J$2 -> 0.0025901842 | N11: =IF(AND(ISNUMBER(D11),ISNUMBER(G11)),G11/D11,"") -> 0.67331787
A12: Colon | B12: Site | C12: Digestive system | D12: 20572 | E12: 2.8 | F12: 260 | G12: 15685 | H12: 2.3 | I12: 348 | J12: 36257 | K12: 2.6 | L12: 298 | M12: =J12/J$2 -> 0.026043346 | N12: =IF(AND(ISNUMBER(D12),ISNUMBER(G12)),G12/D12,"") -> 0.7624441
A13: Rectum | B13: Site | C13: Digestive system | D13: 21915 | E13: 3 | F13: 244 | G13: 14985 | H13: 2.2 | I13: 372 | J13: 36900 | K13: 2.6 | L13: 295 | M13: =J13/J$2 -> 0.026505212 | N13: =IF(AND(ISNUMBER(D13),ISNUMBER(G13)),G13/D13,"") -> 0.68377823
A14: Anus, anal canal | B14: Site | C14: Digestive system | D14: 2897 | E14: 0.4 | F14: 1865 | G14: 2028 | H14: 0.3 | I14: 2682 | J14: 4925 | K14: 0.3 | L14: 2200 | M14: =J14/J$2 -> 0.0035376198 | N14: =IF(AND(ISNUMBER(D14),ISNUMBER(G14)),G14/D14,"") -> 0.70003452
A15: Liver and intrahepatic bile duct | B15: Site | C15: Digestive system | D15: 26678 | E15: 3.7 | F15: 189 | G15: 10732 | H15: 1.6 | I15: 514 | J15: 37410 | K15: 2.7 | L15: 277 | M15: =J15/J$2 -> 0.026871545 | N15: =IF(AND(ISNUMBER(D15),ISNUMBER(G15)),G15/D15,"") -> 0.40227903
A16: Gallbladder and other biliary | B16: Site | C16: Digestive system | D16: 12385 | E16: 1.7 | F16: 422 | G16: 19510 | H16: 2.8 | I16: 284 | J16: 31895 | K16: 2.3 | L16: 340 | M16: =J16/J$2 -> 0.022910129 | N16: =IF(AND(ISNUMBER(D16),ISNUMBER(G16)),G16/D16,"") -> 1.5752927
A17: Pancreas | B17: Site | C17: Digestive system | D17: 11908 | E17: 1.6 | F17: 429 | G17: 8110 | H17: 1.2 | I17: 657 | J17: 20018 | K17: 1.4 | L17: 519 | M17: =J17/J$2 -> 0.014378898 | N17: =IF(AND(ISNUMBER(D17),ISNUMBER(G17)),G17/D17,"") -> 0.68105475
A18: Respiratory system | B18: Group | D18: 103552 | E18: 14.3 | F18: 48 | G18: 32480 | H18: 4.7 | I18: 165 | J18: 136032 | K18: 9.6 | L18: 74 | M18: =J18/J$2 -> 0.097711573 | N18: =IF(AND(ISNUMBER(D18),ISNUMBER(G18)),G18/D18,"") -> 0.31365884
A19: Larynx | B19: Site | C19: Respiratory system | D19: 27146 | E19: 3.8 | F19: 184 | G19: 3316 | H19: 0.5 | I19: 1633 | J19: 30462 | K19: 2.2 | L19: 331 | M19: =J19/J$2 -> 0.021880807 | N19: =IF(AND(ISNUMBER(D19),ISNUMBER(G19)),G19/D19,"") -> 0.12215428
A20: Lung and bronchus | B20: Site | C20: Respiratory system | D20: 71788 | E20: 9.9 | F20: 68 | G20: 26490 | H20: 3.9 | I20: 201 | J20: 98278 | K20: 7 | L20: 101 | M20: =J20/J$2 -> 0.070592934 | N20: =IF(AND(ISNUMBER(D20),ISNUMBER(G20)),G20/D20,"") -> 0.36900318
A21: Other respiratory organs | B21: Site | C21: Respiratory system | D21: 4618 | E21: 0.6 | F21: 1273 | G21: 2674 | H21: 0.4 | I21: 2156 | J21: 7292 | K21: 0.5 | L21: 1600 | M21: =J21/J$2 -> 0.0052378322 | N21: =IF(AND(ISNUMBER(D21),ISNUMBER(G21)),G21/D21,"") -> 0.57903854
A22: Bones and joints | B22: Group | D22: 8115 | E22: 1.1 | F22: 1013 | G22: 5840 | H22: 0.8 | I22: 1370 | J22: 13955 | K22: 1 | L22: 1162 | M22: =J22/J$2 -> 0.010023855 | N22: =IF(AND(ISNUMBER(D22),ISNUMBER(G22)),G22/D22,"") -> 0.71965496
A23: Soft tissue | B23: Group | D23: 8047 | E23: 1.1 | F23: 842 | G23: 6590 | H23: 1 | I23: 1052 | J23: 14637 | K23: 1 | L23: 936 | M23: =J23/J$2 -> 0.010513734 | N23: =IF(AND(ISNUMBER(D23),ISNUMBER(G23)),G23/D23,"") -> 0.81893873
A24: Skin (excluding basal and squamous) | B24: Group | D24: 11203 | E24: 1.6 | F24: 510 | G24: 8962 | H24: 1.3 | I24: 640 | J24: 20165 | K24: 1.4 | L24: 568 | M24: =J24/J$2 -> 0.014484488 | N24: =IF(AND(ISNUMBER(D24),ISNUMBER(G24)),G24/D24,"") -> 0.7999643
A25: Melanoma of the skin | B25: Site | C25: Skin (excluding basal and squamous) | D25: 3003 | E25: 0.4 | F25: 1904 | G25: 2364 | H25: 0.3 | I25: 2281 | J25: 5367 | K25: 0.4 | L25: 2075 | M25: =J25/J$2 -> 0.0038551077 | N25: =IF(AND(ISNUMBER(D25),ISNUMBER(G25)),G25/D25,"") -> 0.78721279
A26: Other non-epithelial skin | B26: Site | C26: Skin (excluding basal and squamous) | D26: 8200 | E26: 1.1 | F26: 695 | G26: 6598 | H26: 1 | I26: 890 | J26: 14798 | K26: 1 | L26: 781 | M26: =J26/J$2 -> 0.01062938 | N26: =IF(AND(ISNUMBER(D26),ISNUMBER(G26)),G26/D26,"") -> 0.80463415
A27: Breast | B27: Group | D27: 5377 | E27: 0.7 | F27: 1022 | G27: 205424 | H27: 29.9 | I27: 29 | J27: 210801 | K27: 15 | L27: 56 | M27: =J27/J$2 -> 0.15141803 | N27: =IF(AND(ISNUMBER(D27),ISNUMBER(G27)),G27/D27,"") -> 38.204203
A28: Genital system | B28: Group | D28: 51994 | E28: 7.2 | F28: 105 | G28: 155630 | H28: 22.6 | I28: 36 | J28: 207624 | K28: 14.7 | L28: 54 | M28: =J28/J$2 -> 0.14913599 | N28: =IF(AND(ISNUMBER(D28),ISNUMBER(G28)),G28/D28,"") -> 2.99323
A29: Uterine cervix | B29: Site | C29: Genital system | G29: 75209 | H29: 10.9 | I29: 75 | J29: 75209 | K29: 10.9 | L29: 75 | M29: =J29/J$2 -> 0.054022507 | N29: =IF(AND(ISNUMBER(D29),ISNUMBER(G29)),G29/D29,"")
A30: Uterine corpus | B30: Site | C30: Genital system | G30: 26514 | H30: 3.9 | I30: 190 | J30: 26514 | K30: 3.9 | L30: 190 | M30: =J30/J$2 -> 0.019044965 | N30: =IF(AND(ISNUMBER(D30),ISNUMBER(G30)),G30/D30,"")
A31: Ovary | B31: Site | C31: Genital system | G31: 43886 | H31: 6.4 | I31: 133 | J31: 43886 | K31: 6.4 | L31: 133 | M31: =J31/J$2 -> 0.031523245 | N31: =IF(AND(ISNUMBER(D31),ISNUMBER(G31)),G31/D31,"")
A32: Vulva | B32: Site | C32: Genital system | G32: 2138 | H32: 0.3 | I32: 2459 | J32: 2138 | K32: 0.3 | L32: 2459 | M32: =J32/J$2 -> 0.0015357221 | N32: =IF(AND(ISNUMBER(D32),ISNUMBER(G32)),G32/D32,"")
A33: Vagina and other genital, female | B33: Site | C33: Genital system | G33: 7570 | H33: 1.1 | I33: 745 | J33: 7570 | K33: 1.1 | L33: 745 | M33: =J33/J$2 -> 0.0054375192 | N33: =IF(AND(ISNUMBER(D33),ISNUMBER(G33)),G33/D33,"")
A34: Placenta | B34: Site | C34: Genital system | G34: 313 | H34: 0 | I34: 30912 | J34: 313 | K34: 0 | L34: 30912 | M34: =J34/J$2 -> 0.00022482741 | N34: =IF(AND(ISNUMBER(D34),ISNUMBER(G34)),G34/D34,"")
A35: Prostate | B35: Site | C35: Genital system | D35: 41532 | E35: 5.7 | F35: 125 | J35: 41532 | K35: 5.7 | L35: 125 | M35: =J35/J$2 -> 0.029832371 | N35: =IF(AND(ISNUMBER(D35),ISNUMBER(G35)),G35/D35,"")
A36: Testis | B36: Site | C36: Genital system | D36: 4352 | E36: 0.6 | F36: 2095 | J36: 4352 | K36: 0.6 | L36: 2095 | M36: =J36/J$2 -> 0.0031260348 | N36: =IF(AND(ISNUMBER(D36),ISNUMBER(G36)),G36/D36,"")
A37: Penis and other genital, male | B37: Site | C37: Genital system | D37: 6110 | E37: 0.8 | F37: 916 | J37: 6110 | K37: 0.8 | L37: 916 | M37: =J37/J$2 -> 0.0043888035 | N37: =IF(AND(ISNUMBER(D37),ISNUMBER(G37)),G37/D37,"")
A38: Urinary system | B38: Group | D38: 33269 | E38: 4.6 | F38: 158 | G38: 11265 | H38: 1.6 | I38: 502 | J38: 44534 | K38: 3.2 | L38: 240 | M38: =J38/J$2 -> 0.031988703 | N38: =IF(AND(ISNUMBER(D38),ISNUMBER(G38)),G38/D38,"") -> 0.3386035
A39: Urinary bladder | B39: Site | C39: Urinary system | D39: 20470 | E39: 2.8 | F39: 250 | G39: 5403 | H39: 0.8 | I39: 1014 | J39: 25873 | K39: 1.8 | L39: 402 | M39: =J39/J$2 -> 0.018584535 | N39: =IF(AND(ISNUMBER(D39),ISNUMBER(G39)),G39/D39,"") -> 0.26394724
A40: Kidney and renal pelvis | B40: Site | C40: Urinary system | D40: 12363 | E40: 1.7 | F40: 442 | G40: 5657 | H40: 0.8 | I40: 1038 | J40: 18020 | K40: 1.3 | L40: 620 | M40: =J40/J$2 -> 0.012943738 | N40: =IF(AND(ISNUMBER(D40),ISNUMBER(G40)),G40/D40,"") -> 0.45757502
A41: Ureter and other urinary organs | B41: Site | C41: Urinary system | D41: 436 | E41: 0.1 | F41: 10843 | G41: 205 | H41: 0 | I41: 21892 | J41: 641 | K41: 0 | L41: 14531 | M41: =J41/J$2 -> 0.0004604293 | N41: =IF(AND(ISNUMBER(D41),ISNUMBER(G41)),G41/D41,"") -> 0.47018349
A42: Eye and orbit | B42: Group | D42: 1304 | E42: 0.2 | F42: 6870 | G42: 953 | H42: 0.1 | I42: 9063 | J42: 2257 | K42: 0.2 | L42: 7792 | M42: =J42/J$2 -> 0.0016211996 | N42: =IF(AND(ISNUMBER(D42),ISNUMBER(G42)),G42/D42,"") -> 0.73082822
A43: Brain and other nervous system | B43: Group | D43: 19979 | E43: 2.8 | F43: 341 | G43: 12750 | H43: 1.9 | I43: 546 | J43: 32729 | K43: 2.3 | L43: 419 | M43: =J43/J$2 -> 0.02350919 | N43: =IF(AND(ISNUMBER(D43),ISNUMBER(G43)),G43/D43,"") -> 0.63817008
A44: Endocrine system | B44: Group | D44: 9263 | E44: 1.3 | F44: 709 | G44: 26665 | H44: 3.9 | I44: 279 | J44: 35928 | K44: 2.5 | L44: 402 | M44: =J44/J$2 -> 0.025807026 | N44: =IF(AND(ISNUMBER(D44),ISNUMBER(G44)),G44/D44,"") -> 2.878657
A45: Thyroid | B45: Site | C45: Endocrine system | D45: 8570 | E45: 1.2 | F45: 759 | G45: 26095 | H45: 3.8 | I45: 285 | J45: 34665 | K45: 2.5 | L45: 416 | M45: =J45/J$2 -> 0.024899815 | N45: =IF(AND(ISNUMBER(D45),ISNUMBER(G45)),G45/D45,"") -> 3.0449242
A46: Adrenal gland | B46: Site | C46: Endocrine system | D46: 693 | E46: 0.1 | F46: 10797 | G46: 570 | H46: 0.1 | I46: 14053 | J46: 1263 | K46: 0.1 | L46: 12209 | M46: =J46/J$2 -> 0.00090721093 | N46: =IF(AND(ISNUMBER(D46),ISNUMBER(G46)),G46/D46,"") -> 0.82251082
A47: Lymphoma | B47: Group | D47: 32695 | E47: 4.5 | F47: 197 | G47: 20247 | H47: 2.9 | I47: 296 | J47: 52942 | K47: 3.8 | L47: 236 | M47: =J47/J$2 -> 0.038028156 | N47: =IF(AND(ISNUMBER(D47),ISNUMBER(G47)),G47/D47,"") -> 0.619269
A48: Hodgkin lymphoma | B48: Site | C48: Lymphoma | D48: 7294 | E48: 1 | F48: 1150 | G48: 3936 | H48: 0.6 | I48: 1871 | J48: 11230 | K48: 0.8 | L48: 1418 | M48: =J48/J$2 -> 0.0080664914 | N48: =IF(AND(ISNUMBER(D48),ISNUMBER(G48)),G48/D48,"") -> 0.53962161
A49: Non-Hodgkin lymphoma | B49: Site | C49: Lymphoma | D49: 25344 | E49: 3.5 | F49: 238 | G49: 16263 | H49: 2.4 | I49: 352 | J49: 41607 | K49: 3 | L49: 284 | M49: =J49/J$2 -> 0.029886243 | N49: =IF(AND(ISNUMBER(D49),ISNUMBER(G49)),G49/D49,"") -> 0.64169034
A50: Malignant immunoproliferative diseases | B50: Group | D50: 57 | E50: 0 | F50: 101774 | G50: 48 | H50: 0 | I50: 164355 | J50: 105 | K50: 0 | L50: 126050 | M50: =J50/J$2 -> 7.5421336e-05 | N50: =IF(AND(ISNUMBER(D50),ISNUMBER(G50)),G50/D50,"") -> 0.84210526
A51: Multiple myeloma | B51: Group | D51: 10725 | E51: 1.5 | F51: 465 | G51: 7756 | H51: 1.1 | I51: 646 | J51: 18481 | K51: 1.3 | L51: 541 | M51: =J51/J$2 -> 0.013274873 | N51: =IF(AND(ISNUMBER(D51),ISNUMBER(G51)),G51/D51,"") -> 0.72317016
A52: Leukaemia | B52: Group | D52: 32481 | E52: 4.5 | F52: 239 | G52: 21132 | H52: 3.1 | I52: 353 | J52: 53613 | K52: 3.8 | L52: 284 | M52: =J52/J$2 -> 0.038510134 | N52: =IF(AND(ISNUMBER(D52),ISNUMBER(G52)),G52/D52,"") -> 0.65059573
A53: Lymphoid leukaemia | B53: Site | C53: Leukaemia | D53: 14159 | E53: 2 | F53: 608 | G53: 7419 | H53: 1.1 | I53: 1138 | J53: 21578 | K53: 1.5 | L53: 789 | M53: =J53/J$2 -> 0.015499444 | N53: =IF(AND(ISNUMBER(D53),ISNUMBER(G53)),G53/D53,"") -> 0.52397768
A54: Myeloid leukaemia | B54: Site | C54: Leukaemia | D54: 14913 | E54: 2.1 | F54: 474 | G54: 11275 | H54: 1.6 | I54: 617 | J54: 26188 | K54: 1.9 | L54: 536 | M54: =J54/J$2 -> 0.018810799 | N54: =IF(AND(ISNUMBER(D54),ISNUMBER(G54)),G54/D54,"") -> 0.75605177
A55: Leukaemia unspecified | B55: Site | C55: Leukaemia | D55: 3409 | E55: 0.5 | F55: 2287 | G55: 2438 | H55: 0.4 | I55: 2980 | J55: 5847 | K55: 0.4 | L55: 2583 | M55: =J55/J$2 -> 0.004199891 | N55: =IF(AND(ISNUMBER(D55),ISNUMBER(G55)),G55/D55,"") -> 0.71516574
A56: Other and unspecified primary sites | B56: Group | D56: 48554 | E56: 6.7 | F56: 114 | G56: 36976 | H56: 5.4 | I56: 153 | J56: 85530 | K56: 6.1 | L56: 131 | M56: =J56/J$2 -> 0.061436065 | N56: =IF(AND(ISNUMBER(D56),ISNUMBER(G56)),G56/D56,"") -> 0.76154385
A58: Source: Mathur P et al. Cancer Statistics, 2020: Report from NCRP, India. JCO Glob Oncol 2020;6:1063-75, Table 2 (Projected incidence of cancer, India 2020). Blank = site not applicable to that sex. Cum. risk is stored as N for "1 in N". Based on 2012-2016 registry rates assumed constant to 2020.

Sheet India Age-Sex Sites
A1: Age group | B1: Sex | C1: Rank | D1: Cancer site | E1: ICD-10 codes | F1: Estimated cases 2022 (n) | G1: Share of age-sex total (% as printed) | H1: Share recomputed (%) | I1: Row type | J1: Check: listed rows - All sites
A2: 0-14 yr | B2: Male | C2: 1 | D2: Lymphoid leukaemia | E2: C91 | F2: 6233 | G2: 29.3 | H2: =F2/F$8*100 -> 29.251924 | I2: Top-5 site
A3: 0-14 yr | B3: Male | C3: 2 | D3: Brain and NS | E3: C70-C72 | F3: 2643 | G3: 12.4 | H3: =F3/F$8*100 -> 12.403792 | I3: Top-5 site
A4: 0-14 yr | B4: Male | C4: 3 | D4: NHL | E4: C82-86, C96 | F4: 1679 | G4: 7.9 | H4: =F4/F$8*100 -> 7.8796696 | I4: Top-5 site
A5: 0-14 yr | B5: Male | C5: 4 | D5: Hodgkin's disease | E5: C81 | F5: 1513 | G5: 7.1 | H5: =F5/F$8*100 -> 7.1006195 | I5: Top-5 site
A6: 0-14 yr | B6: Male | C6: 5 | D6: Myeloid leukaemia | E6: C92-C94 | F6: 1498 | G6: 7 | H6: =F6/F$8*100 -> 7.0302234 | I6: Top-5 site
A7: 0-14 yr | B7: Male | D7: Other sites | F7: 7742 | G7: 36.3 | H7: =F7/F$8*100 -> 36.333771 | I7: Other
A8: 0-14 yr | B8: Male | D8: All sites | F8: 21308 | G8: 100 | H8: =F8/F$8*100 -> 100 | I8: Total | J8: =SUM(F2:F7)-F8 -> 0
A9: 0-14 yr | B9: Female | C9: 1 | D9: Lymphoid leukaemia | E9: C91 | F9: 3328 | G9: 24.3 | H9: =F9/F$15*100 -> 24.276023 | I9: Top-5 site
A10: 0-14 yr | B10: Female | C10: 2 | D10: Brain and NS | E10: C70-C72 | F10: 1956 | G10: 14.3 | H10: =F10/F$15*100 -> 14.267999 | I10: Top-5 site
A11: 0-14 yr | B11: Female | C11: 3 | D11: Bone | E11: C40-C41 | F11: 1140 | G11: 8.3 | H11: =F11/F$15*100 -> 8.315705 | I11: Top-5 site
A12: 0-14 yr | B12: Female | C12: 4 | D12: Myeloid leukaemia | E12: C92-C94 | F12: 1099 | G12: 8 | H12: =F12/F$15*100 -> 8.0166314 | I12: Top-5 site
A13: 0-14 yr | B13: Female | C13: 5 | D13: NHL | E13: C82-86, C96 | F13: 783 | G13: 5.7 | H13: =F13/F$15*100 -> 5.7115763 | I13: Top-5 site
A14: 0-14 yr | B14: Female | D14: Other sites | F14: 5403 | G14: 39.4 | H14: =F14/F$15*100 -> 39.412065 | I14: Other
A15: 0-14 yr | B15: Female | D15: All sites | F15: 13709 | G15: 100 | H15: =F15/F$15*100 -> 100 | I15: Total | J15: =SUM(F9:F14)-F15 -> 0
A16: 15-39 yr | B16: Male | C16: 1 | D16: Mouth | E16: C03-C06 | F16: 9013 | G16: 12 | H16: =F16/F$22*100 -> 12.037878 | I16: Top-5 site
A17: 15-39 yr | B17: Male | C17: 2 | D17: Tongue | E17: C01-C02 | F17: 6597 | G17: 8.8 | H17: =F17/F$22*100 -> 8.8110375 | I17: Top-5 site
A18: 15-39 yr | B18: Male | C18: 3 | D18: Brain and NS | E18: C70-C72 | F18: 5230 | G18: 7 | H18: =F18/F$22*100 -> 6.9852548 | I18: Top-5 site
A19: 15-39 yr | B19: Male | C19: 4 | D19: Myeloid leukaemia | E19: C92-C94 | F19: 4881 | G19: 6.5 | H19: =F19/F$22*100 -> 6.519126 | I19: Top-5 site
A20: 15-39 yr | B20: Male | C20: 5 | D20: NHL | E20: C82-86, C96 | F20: 4444 | G20: 5.9 | H20: =F20/F$22*100 -> 5.9354632 | I20: Top-5 site
A21: 15-39 yr | B21: Male | D21: Other sites | F21: 44707 | G21: 59.7 | H21: =F21/F$22*100 -> 59.711241 | I21: Other
A22: 15-39 yr | B22: Male | D22: All sites | F22: 74872 | G22: 100 | H22: =F22/F$22*100 -> 100 | I22: Total | J22: =SUM(F16:F21)-F22 -> 0
A23: 15-39 yr | B23: Female | C23: 1 | D23: Breast | E23: C50 | F23: 25710 | G23: 27.3 | H23: =F23/F$29*100 -> 27.302848 | I23: Top-5 site
A24: 15-39 yr | B24: Female | C24: 2 | D24: Thyroid | E24: C73 | F24: 11453 | G24: 12.2 | H24: =F24/F$29*100 -> 12.162564 | I24: Top-5 site
A25: 15-39 yr | B25: Female | C25: 3 | D25: Ovary | E25: C56 | F25: 6877 | G25: 7.3 | H25: =F25/F$29*100 -> 7.3030606 | I25: Top-5 site
A26: 15-39 yr | B26: Female | C26: 4 | D26: Cervix | E26: C53 | F26: 6714 | G26: 7.1 | H26: =F26/F$29*100 -> 7.129962 | I26: Top-5 site
A27: 15-39 yr | B27: Female | C27: 5 | D27: Myeloid leukaemia | E27: C92-C94 | F27: 3503 | G27: 3.7 | H27: =F27/F$29*100 -> 3.7200263 | I27: Top-5 site
A28: 15-39 yr | B28: Female | D28: Other sites | F28: 39909 | G28: 42.4 | H28: =F28/F$29*100 -> 42.381539 | I28: Other
A29: 15-39 yr | B29: Female | D29: All sites | F29: 94166 | G29: 100 | H29: =F29/F$29*100 -> 100 | I29: Total | J29: =SUM(F23:F28)-F29 -> 0
A30: 40-64 yr | B30: Male | C30: 1 | D30: Lung | E30: C33-34 | F30: 37376 | G30: 11 | H30: =F30/F$36*100 -> 10.953316 | I30: Top-5 site
A31: 40-64 yr | B31: Male | C31: 2 | D31: Mouth | E31: C03-C06 | F31: 37067 | G31: 10.9 | H31: =F31/F$36*100 -> 10.862761 | I31: Top-5 site
A32: 40-64 yr | B32: Male | C32: 3 | D32: Tongue | E32: C01-C02 | F32: 24951 | G32: 7.3 | H32: =F32/F$36*100 -> 7.3120769 | I32: Top-5 site
A33: 40-64 yr | B33: Male | C33: 4 | D33: Oesophagus | E33: C15 | F33: 18390 | G33: 5.4 | H33: =F33/F$36*100 -> 5.3893268 | I33: Top-5 site
A34: 40-64 yr | B34: Male | C34: 5 | D34: Stomach | E34: C16 | F34: 17741 | G34: 5.2 | H34: =F34/F$36*100 -> 5.1991325 | I34: Top-5 site
A35: 40-64 yr | B35: Male | D35: Other sites | F35: 205705 | G35: 60.3 | H35: =F35/F$36*100 -> 60.283387 | I35: Other
A36: 40-64 yr | B36: Male | D36: All sites | F36: 341230 | G36: 100 | H36: =F36/F$36*100 -> 100 | I36: Total | J36: =SUM(F30:F35)-F36 -> 0
A37: 40-64 yr | B37: Female | C37: 1 | D37: Breast | E37: C50 | F37: 140384 | G37: 33 | H37: =F37/F$43*100 -> 32.960335 | I37: Top-5 site
A38: 40-64 yr | B38: Female | C38: 2 | D38: Cervix | E38: C53 | F38: 52560 | G38: 12.3 | H38: =F38/F$43*100 -> 12.340404 | I38: Top-5 site
A39: 40-64 yr | B39: Female | C39: 3 | D39: Ovary | E39: C56 | F39: 27562 | G39: 6.5 | H39: =F39/F$43*100 -> 6.4711987 | I39: Top-5 site
A40: 40-64 yr | B40: Female | C40: 4 | D40: Corpus uteri | E40: C54 | F40: 18108 | G40: 4.3 | H40: =F40/F$43*100 -> 4.2515226 | I40: Top-5 site
A41: 40-64 yr | B41: Female | C41: 5 | D41: Lung | E41: C33-34 | F41: 14341 | G41: 3.4 | H41: =F41/F$43*100 -> 3.36708 | I41: Top-5 site
A42: 40-64 yr | B42: Female | D42: Other sites | F42: 172963 | G42: 40.6 | H42: =F42/F$43*100 -> 40.60946 | I42: Other
A43: 40-64 yr | B43: Female | D43: All sites | F43: 425918 | G43: 100 | H43: =F43/F$43*100 -> 100 | I43: Total | J43: =SUM(F37:F42)-F43 -> 0
A44: 65+ yr | B44: Male | C44: 1 | D44: Lung | E44: C33-34 | F44: 36013 | G44: 13.1 | H44: =F44/F$50*100 -> 13.106789 | I44: Top-5 site
A45: 65+ yr | B45: Male | C45: 2 | D45: Prostate | E45: C61 | F45: 33695 | G45: 12.3 | H45: =F45/F$50*100 -> 12.263162 | I45: Top-5 site
A46: 65+ yr | B46: Male | C46: 3 | D46: Oesophagus | E46: C15 | F46: 14668 | G46: 5.3 | H46: =F46/F$50*100 -> 5.3383606 | I46: Top-5 site
A47: 65+ yr | B47: Male | C47: 4 | D47: Stomach | E47: C16 | F47: 14435 | G47: 5.3 | H47: =F47/F$50*100 -> 5.2535612 | I47: Top-5 site
A48: 65+ yr | B48: Male | C48: 5 | D48: Mouth | E48: C03-C06 | F48: 14035 | G48: 5.1 | H48: =F48/F$50*100 -> 5.1079828 | I48: Top-5 site
A49: 65+ yr | B49: Male | D49: Other sites | F49: 161920 | G49: 58.9 | H49: =F49/F$50*100 -> 58.930144 | I49: Other
A50: 65+ yr | B50: Male | D50: All sites | F50: 274766 | G50: 100 | H50: =F50/F$50*100 -> 100 | I50: Total | J50: =SUM(F44:F49)-F50 -> 0
A51: 65+ yr | B51: Female | C51: 1 | D51: Breast | E51: C50 | F51: 49946 | G51: 23.2 | H51: =F51/F$57*100 -> 23.181316 | I51: Top-5 site
A52: 65+ yr | B52: Female | C52: 2 | D52: Cervix | E52: C53 | F52: 19814 | G52: 9.2 | H52: =F52/F$57*100 -> 9.1962239 | I52: Top-5 site
A53: 65+ yr | B53: Female | C53: 3 | D53: Lung | E53: C33-34 | F53: 11793 | G53: 5.5 | H53: =F53/F$57*100 -> 5.4734565 | I53: Top-5 site
A54: 65+ yr | B54: Female | C54: 4 | D54: Ovary | E54: C56 | F54: 11188 | G54: 5.2 | H54: =F54/F$57*100 -> 5.1926594 | I54: Top-5 site
A55: 65+ yr | B55: Female | C55: 5 | D55: Mouth | E55: C03-C06 | F55: 9060 | G55: 4.2 | H55: =F55/F$57*100 -> 4.2049959 | I55: Top-5 site
A56: 65+ yr | B56: Female | D56: Other sites | F56: 113657 | G56: 52.8 | H56: =F56/F$57*100 -> 52.751348 | I56: Other
A57: 65+ yr | B57: Female | D57: All sites | F57: 215458 | G57: 100 | H57: =F57/F$57*100 -> 100 | I57: Total | J57: =SUM(F51:F56)-F57 -> 0
A59: Source: IJMR 2022 (Sathishkumar et al.), Table II - top five leading cancer sites by age group and sex, India 2022. NS = nervous system; NHL = non-Hodgkin lymphoma. Abstract text gives lymphoid leukaemia in boys/girls as 29.2%/24.2%; Table II prints 29.3%/24.3% (used here).

Sheet India Top10 Sites 2022
A1: Sex | B1: Rank | C1: Site (as in Fig. 1) | D1: Share of all cancers (%) - Fig. 1 | E1: Matching site in Table I | F1: Estimated cases 2022 (Table I) | G1: Share recomputed from Table I (%) | H1: Difference (pct-points)
A2: Male | B2: 1 | C2: Lung | D2: 10.6 | E2: Lung and bronchus | F2: =INDEX('India Sites 2022'!$D$2:$D$56,MATCH(E2,'India Sites 2022'!$A$2:$A$56,0)) -> 75474 | G2: =F2/'India Sites 2022'!$D$2*100 -> 10.597661 | H2: =G2-D2 -> -0.0023387477
A3: Male | B3: 2 | C3: Mouth | D3: 8.4 | E3: Mouth | F3: =INDEX('India Sites 2022'!$D$2:$D$56,MATCH(E3,'India Sites 2022'!$A$2:$A$56,0)) -> 60164 | G3: =F3/'India Sites 2022'!$D$2*100 -> 8.4479118 | H3: =G3-D3 -> 0.047911752
A4: Male | B4: 3 | C4: Prostate | D4: 6.1 | E4: Prostate | F4: =INDEX('India Sites 2022'!$D$2:$D$56,MATCH(E4,'India Sites 2022'!$A$2:$A$56,0)) -> 43691 | G4: =F4/'India Sites 2022'!$D$2*100 -> 6.1348599 | H4: =G4-D4 -> 0.034859922
A5: Male | B5: 4 | C5: Tongue | D5: 5.9 | E5: Tongue | F5: =INDEX('India Sites 2022'!$D$2:$D$56,MATCH(E5,'India Sites 2022'!$A$2:$A$56,0)) -> 41845 | G5: =F5/'India Sites 2022'!$D$2*100 -> 5.8756543 | H5: =G5-D5 -> -0.024345667
A6: Male | B6: 5 | C6: Stomach | D6: 4.8 | E6: Stomach | F6: =INDEX('India Sites 2022'!$D$2:$D$56,MATCH(E6,'India Sites 2022'!$A$2:$A$56,0)) -> 34353 | G6: =F6/'India Sites 2022'!$D$2*100 -> 4.8236672 | H6: =G6-D6 -> 0.023667183
A7: Male | B7: 6 | C7: Oesophagus | D7: 4.8 | E7: Oesophagus | F7: =INDEX('India Sites 2022'!$D$2:$D$56,MATCH(E7,'India Sites 2022'!$A$2:$A$56,0)) -> 34272 | G7: =F7/'India Sites 2022'!$D$2*100 -> 4.8122936 | H7: =G7-D7 -> 0.01229359
A8: Male | B8: 7 | C8: Larynx | D8: 4 | E8: Larynx | F8: =INDEX('India Sites 2022'!$D$2:$D$56,MATCH(E8,'India Sites 2022'!$A$2:$A$56,0)) -> 28542 | G8: =F8/'India Sites 2022'!$D$2*100 -> 4.0077172 | H8: =G8-D8 -> 0.0077171935
A9: Male | B9: 8 | C9: Liver | D9: 3.9 | E9: Liver and intrahepatic bile duct | F9: =INDEX('India Sites 2022'!$D$2:$D$56,MATCH(E9,'India Sites 2022'!$A$2:$A$56,0)) -> 28020 | G9: =F9/'India Sites 2022'!$D$2*100 -> 3.9344207 | H9: =G9-D9 -> 0.034420705
A10: Male | B10: 9 | C10: NHL | D10: 3.7 | E10: Non-Hodgkin lymphoma | F10: =INDEX('India Sites 2022'!$D$2:$D$56,MATCH(E10,'India Sites 2022'!$A$2:$A$56,0)) -> 26497 | G10: =F10/'India Sites 2022'!$D$2*100 -> 3.7205691 | H10: =G10-D10 -> 0.020569073
A11: Male | B11: 10 | C11: Rectum | D11: 3.2 | E11: Rectum | F11: =INDEX('India Sites 2022'!$D$2:$D$56,MATCH(E11,'India Sites 2022'!$A$2:$A$56,0)) -> 22985 | G11: =F11/'India Sites 2022'!$D$2*100 -> 3.2274325 | H11: =G11-D11 -> 0.027432545
A12: Female | B12: 1 | C12: Breast | D12: 28.8 | E12: Breast | F12: =INDEX('India Sites 2022'!$H$2:$H$56,MATCH(E12,'India Sites 2022'!$A$2:$A$56,0)) -> 216108 | G12: =F12/'India Sites 2022'!$H$2*100 -> 28.843205 | H12: =G12-D12 -> 0.043204747
A13: Female | B13: 2 | C13: Cervix | D13: 10.6 | E13: Uterine cervix | F13: =INDEX('India Sites 2022'!$H$2:$H$56,MATCH(E13,'India Sites 2022'!$A$2:$A$56,0)) -> 79103 | G13: =F13/'India Sites 2022'!$H$2*100 -> 10.55761 | H13: =G13-D13 -> -0.0423898
A14: Female | B14: 3 | C14: Ovary | D14: 6.2 | E14: Ovary | F14: =INDEX('India Sites 2022'!$H$2:$H$56,MATCH(E14,'India Sites 2022'!$A$2:$A$56,0)) -> 46126 | G14: =F14/'India Sites 2022'!$H$2*100 -> 6.1562814 | H14: =G14-D14 -> -0.043718594
A15: Female | B15: 4 | C15: Corpus uteri | D15: 3.7 | E15: Uterine corpus | F15: =INDEX('India Sites 2022'!$H$2:$H$56,MATCH(E15,'India Sites 2022'!$A$2:$A$56,0)) -> 27922 | G15: =F15/'India Sites 2022'!$H$2*100 -> 3.726655 | H15: =G15-D15 -> 0.026655019
A16: Female | B16: 5 | C16: Lung | D16: 3.7 | E16: Lung and bronchus | F16: =INDEX('India Sites 2022'!$H$2:$H$56,MATCH(E16,'India Sites 2022'!$A$2:$A$56,0)) -> 27897 | G16: =F16/'India Sites 2022'!$H$2*100 -> 3.7233184 | H16: =G16-D16 -> 0.023318354
A17: Female | B17: 6 | C17: Thyroid | D17: 3.6 | E17: Thyroid | F17: =INDEX('India Sites 2022'!$H$2:$H$56,MATCH(E17,'India Sites 2022'!$A$2:$A$56,0)) -> 27253 | G17: =F17/'India Sites 2022'!$H$2*100 -> 3.6373658 | H17: =G17-D17 -> 0.037365849
A18: Female | B18: 7 | C18: Mouth | D18: 3.2 | E18: Mouth | F18: =INDEX('India Sites 2022'!$H$2:$H$56,MATCH(E18,'India Sites 2022'!$A$2:$A$56,0)) -> 23675 | G18: =F18/'India Sites 2022'!$H$2*100 -> 3.1598223 | H18: =G18-D18 -> -0.040177724
A19: Female | B19: 8 | C19: Oesophagus | D19: 2.8 | E19: Oesophagus | F19: =INDEX('India Sites 2022'!$H$2:$H$56,MATCH(E19,'India Sites 2022'!$A$2:$A$56,0)) -> 21300 | G19: =F19/'India Sites 2022'!$H$2*100 -> 2.842839 | H19: =G19-D19 -> 0.042839049
A20: Female | B20: 9 | C20: Gallbladder | D20: 2.7 | E20: Gallbladder and other biliary | F20: =INDEX('India Sites 2022'!$H$2:$H$56,MATCH(E20,'India Sites 2022'!$A$2:$A$56,0)) -> 20570 | G20: =F20/'India Sites 2022'!$H$2*100 -> 2.7454084 | H20: =G20-D20 -> 0.045408415
A21: Female | B21: 10 | C21: Stomach | D21: 2.4 | E21: Stomach | F21: =INDEX('India Sites 2022'!$H$2:$H$56,MATCH(E21,'India Sites 2022'!$A$2:$A$56,0)) -> 18353 | G21: =F21/'India Sites 2022'!$H$2*100 -> 2.4495129 | H21: =G21-D21 -> 0.049512914
A23: Source: IJMR 2022, Fig. 1 (estimated proportion of top 10 leading cancer sites by sex, India 2022). Cases are pulled from sheet India Sites 2022 to validate the printed percentages (differences are rounding only).

Sheet India Trend 2015-2025
A1: Sex | B1: Site (ICD-10) | C1: Cases 2015 | D1: Cases 2020 | E1: Cases 2025 (projected) | F1: Change 2015-2020 | G1: Change 2020-2025 | H1: Change 2015-2025 | I1: CAGR 2015-2025 | J1: Share of sex all-site cases 2025
A2: Male | B2: Lung (C33-34) | C2: 63087 | D2: 71788 | E2: 81219 | F2: =D2/C2-1 -> 0.13792065 | G2: =E2/D2-1 -> 0.13137293 | H2: =E2/C2-1 -> 0.28741262 | I2: =(E2/C2)^(1/10)-1 -> 0.025585274 | J2: =E2/E$8 -> 0.10636676
A3: Male | B3: Mouth (C03-C06) | C3: 50779 | D3: 57380 | E3: 64519 | F3: =D3/C3-1 -> 0.12999468 | G3: =E3/D3-1 -> 0.12441617 | H3: =E3/C3-1 -> 0.2705843 | I3: =(E3/C3)^(1/10)-1 -> 0.024236736 | J3: =E3/E$8 -> 0.084495957
A4: Male | B4: Prostate (C61) | C4: 36419 | D4: 41532 | E4: 47068 | F4: =D4/C4-1 -> 0.14039375 | G4: =E4/D4-1 -> 0.13329481 | H4: =E4/C4-1 -> 0.29240232 | I4: =(E4/C4)^(1/10)-1 -> 0.025982074 | J4: =E4/E$8 -> 0.06164162
A5: Male | B5: Tongue (C01-C02) | C5: 35336 | D5: 39902 | E5: 44861 | F5: =D5/C5-1 -> 0.12921666 | G5: =E5/D5-1 -> 0.12427948 | H5: =E5/C5-1 -> 0.26955513 | I5: =(E5/C5)^(1/10)-1 -> 0.024153743 | J5: =E5/E$8 -> 0.058751269
A6: Male | B6: Stomach (C16) | C6: 28815 | D6: 32713 | E6: 36938 | F6: =D6/C6-1 -> 0.13527677 | G6: =E6/D6-1 -> 0.12915355 | H6: =E6/C6-1 -> 0.28190179 | I6: =(E6/C6)^(1/10)-1 -> 0.025145419 | J6: =E6/E$8 -> 0.048375078
A7: Male | B7: Others | C7: 387301 | D7: 436106 | E7: 488970 | F7: =D7/C7-1 -> 0.1260131 | G7: =E7/D7-1 -> 0.12121824 | H7: =E7/C7-1 -> 0.26250642 | I7: =(E7/C7)^(1/10)-1 -> 0.023583696 | J7: =E7/E$8 -> 0.64036932
A8: Male | B8: All sites | C8: 601737 | D8: 679421 | E8: 763575 | F8: =D8/C8-1 -> 0.12909959 | G8: =E8/D8-1 -> 0.12386135 | H8: =E8/C8-1 -> 0.26895139 | I8: =(E8/C8)^(1/10)-1 -> 0.024105028 | J8: =E8/E$8 -> 1
A9: Male | B9: Check: listed sites - All sites (should be 0) | C9: =SUM(C2:C7)-C8 -> 0 | D9: =SUM(D2:D7)-D8 -> 0 | E9: =SUM(E2:E7)-E8 -> 0
A10: Female | B10: Breast (C50) | C10: 180252 | D10: 205424 | E10: 232832 | F10: =D10/C10-1 -> 0.13964894 | G10: =E10/D10-1 -> 0.13342161 | H10: =E10/C10-1 -> 0.29170273 | I10: =(E10/C10)^(1/10)-1 -> 0.025926523 | J10: =E10/E$16 -> 0.28879534
A11: Female | B11: Cervix (C53) | C11: 65978 | D11: 75209 | E11: 85241 | F11: =D11/C11-1 -> 0.13991027 | G11: =E11/D11-1 -> 0.13338829 | H11: =E11/C11-1 -> 0.29196096 | I11: =(E11/C11)^(1/10)-1 -> 0.025947031 | J11: =E11/E$16 -> 0.10572947
A12: Female | B12: Ovary (C56) | C12: 38607 | D12: 43886 | E12: 49644 | F12: =D12/C12-1 -> 0.13673686 | G12: =E12/D12-1 -> 0.13120357 | H12: =E12/C12-1 -> 0.2858808 | I12: =(E12/C12)^(1/10)-1 -> 0.02546318 | J12: =E12/E$16 -> 0.061576397
A13: Female | B13: Corpus uteri (C54) | C13: 23175 | D13: 26514 | E13: 30121 | F13: =D13/C13-1 -> 0.14407767 | G13: =E13/D13-1 -> 0.13604134 | H13: =E13/C13-1 -> 0.29971953 | I13: =(E13/C13)^(1/10)-1 -> 0.026561481 | J13: =E13/E$16 -> 0.037360863
A14: Female | B14: Lung (C33-34) | C14: 23163 | D14: 26490 | E14: 30109 | F14: =D14/C14-1 -> 0.14363424 | G14: =E14/D14-1 -> 0.13661759 | H14: =E14/C14-1 -> 0.2998748 | I14: =(E14/C14)^(1/10)-1 -> 0.026573744 | J14: =E14/E$16 -> 0.037345978
A15: Female | B15: Others | C15: 296027 | D15: 335235 | E15: 378271 | F15: =D15/C15-1 -> 0.13244738 | G15: =E15/D15-1 -> 0.12837562 | H15: =E15/C15-1 -> 0.27782601 | I15: =(E15/C15)^(1/10)-1 -> 0.024819009 | J15: =E15/E$16 -> 0.46919196
A16: Female | B16: All sites | C16: 627202 | D16: 712758 | E16: 806218 | F16: =D16/C16-1 -> 0.136409 | G16: =E16/D16-1 -> 0.13112445 | H16: =E16/C16-1 -> 0.28542001 | I16: =(E16/C16)^(1/10)-1 -> 0.025426427 | J16: =E16/E$16 -> 1
A17: Female | B17: Check: listed sites - All sites (should be 0) | C17: =SUM(C10:C15)-C16 -> 0 | D17: =SUM(D10:D15)-D16 -> 0 | E17: =SUM(E10:E15)-E16 -> 0
A18: Both | B18: All sites (both sexes) | C18: =C8+C16 -> 1228939 | D18: =D8+D16 -> 1392179 | E18: =E8+E16 -> 1569793 | F18: =D18/C18-1 -> 0.13283003 | G18: =E18/D18-1 -> 0.12757986 | H18: =E18/C18-1 -> 0.27735632 | I18: =(E18/C18)^(1/10)-1 -> 0.024781334
A20: Source: IJMR 2022, Table III - estimated trends in number of cancer cases for the leading sites in India (2015, 2020, 2025). Paper states: +12.8% in 2025 vs 2020; +27.7% from 2015 to 2025 (compare column G/H of the both-sexes row). Constant 2012-16 age-specific rates are applied to growing and ageing populations.

Sheet India Age Structure
A1: Age group (years) | B1: Census 2011 - Male (%) | C1: Census 2011 - Female (%) | D1: Estimated 2022 - Male (%) | E1: Estimated 2022 - Female (%) | F1: Change in male share (pct-pts) | G1: Change in female share (pct-pts)
A2: 0-4 | B2: 9.4 | C2: 9.3 | D2: 8.2 | E2: 7.8 | F2: =D2-B2 -> -1.2 | G2: =E2-C2 -> -1.5
A3: 5-9 | B3: 10.7 | C3: 10.4 | D3: 8.9 | E3: 8.4 | F3: =D3-B3 -> -1.8 | G3: =E3-C3 -> -2
A4: 10-14 | B4: 11.2 | C4: 10.8 | D4: 10 | E4: 9.7 | F4: =D4-B4 -> -1.2 | G4: =E4-C4 -> -1.1
A5: 15-19 | B5: 10.3 | C5: 9.7 | D5: 10.4 | E5: 10 | F5: =D5-B5 -> 0.1 | G5: =E5-C5 -> 0.3
A6: 20-24 | B6: 9.3 | C6: 9.2 | D6: 9.8 | E6: 9.6 | F6: =D6-B6 -> 0.5 | G6: =E6-C6 -> 0.4
A7: 25-29 | B7: 8.3 | C7: 8.6 | D7: 8.7 | E7: 8.6 | F7: =D7-B7 -> 0.4 | G7: =E7-C7 -> 0
A8: 30-34 | B8: 7.2 | C8: 7.5 | D8: 7.3 | E8: 7.6 | F8: =D8-B8 -> 0.1 | G8: =E8-C8 -> 0.1
A9: 35-39 | B9: 6.9 | C9: 7.2 | D9: 7 | E9: 7.4 | F9: =D9-B9 -> 0.1 | G9: =E9-C9 -> 0.2
A10: 40-44 | B10: 6 | C10: 6 | D10: 6.4 | E10: 6.7 | F10: =D10-B10 -> 0.4 | G10: =E10-C10 -> 0.7
A11: 45-49 | B11: 5.2 | C11: 5.2 | D11: 5.6 | E11: 5.7 | F11: =D11-B11 -> 0.4 | G11: =E11-C11 -> 0.5
A12: 50-54 | B12: 4.2 | C12: 4 | D12: 4.6 | E12: 4.5 | F12: =D12-B12 -> 0.4 | G12: =E12-C12 -> 0.5
A13: 55-59 | B13: 3.1 | C13: 3.4 | D13: 3.7 | E13: 3.9 | F13: =D13-B13 -> 0.6 | G13: =E13-C13 -> 0.5
... A17: 75+ | B17: 1.6 | C17: 1.8 | D17: 1.8 | E17: 2.2 | F17: =D17-B17 -> 0.2 | G17: =E17-C17 -> 0.4
A18: Column total (should be ~100) | B18: =SUM(B2:B17) -> 100.1 | C18: =SUM(C2:C17) -> 100.2 | D18: =SUM(D2:D17) -> 99.9 | E18: =SUM(E2:E17) -> 100
A19: Aged 60+ (60-64 to 75+) | B19: =SUM(B14:B17) -> 8.3 | C19: =SUM(C14:C17) -> 8.9 | D19: =SUM(D14:D17) -> 9.3 | E19: =SUM(E14:E17) -> 10.1
A20: Aged 0-14 | B20: =SUM(B2:B4) -> 31.3 | C20: =SUM(C2:C4) -> 30.5 | D20: =SUM(D2:D4) -> 27.1 | E20: =SUM(E2:E4) -> 25.9
A21: Aged 60+, both sexes (simple average of male and female %) | B21: =AVERAGE(B19:C19) -> 8.6 | D21: =AVERAGE(D19:E19) -> 9.7
A23: Source: IJMR 2022 Supplementary Figure (population pyramids, % of population by age group, census 2011 vs estimated 2022). The text layer of the PDF does not label the two pyramids; assignment of the first 32 values to "2022" and the last 32 to "2011" was inferred because only that assignment reproduces the paper's statement that the 60+ share rose from 8.6% (2011) to 9.7% (2022).

Sheet PBCR Incidence Table
A1: Registry | B1: Level | C1: Region | D1: Maharashtra registry | E1: Reference period | F1: Male - annual avg cases | G1: Male - crude rate /100,000 | H1: Male - age-adj. rate /100,000 | I1: Male - cum. risk 0-74 (1 in N) | J1: Male - age-adj. mortality rate /100,000 | K1: Female - annual avg cases | L1: Female - crude rate /100,000 | M1: Female - age-adj. rate /100,000 | N1: Female - cum. risk 0-74 (1 in N) | O1: Female - age-adj. mortality rate /100,000 | P1: Total annual avg cases (M+F) | Q1: Female : male case ratio | R1: Male AAMR / AAR (%) | S1: Female AAMR / AAR (%)
A2: Delhi | B2: PBCR | C2: North | E2: 2012-14 | F2: 10344 | G2: 112.3 | H2: 147 | I2: 6 | J2: 22.2 | K2: 9688 | L2: 119.6 | M2: 141 | N2: 7 | O2: 17.8 | P2: =F2+K2 -> 20032 | Q2: =K2/F2 -> 0.93658159 | R2: =J2/H2 -> 0.15102041 | S2: =O2/M2 -> 0.12624113
A3: Patiala district | B3: PBCR | C3: North | E3: 2012-16 | F3: 1079 | G3: 101.6 | H3: 108.2 | I3: 9 | J3: 32.7 | K3: 1215 | L3: 127.7 | M3: 124.6 | N3: 8 | O3: 30.1 | P3: =F3+K3 -> 2294 | Q3: =K3/F3 -> 1.1260426 | R3: =J3/H3 -> 0.30221811 | S3: =O3/M3 -> 0.24157303
A4: Hyderabad district | B4: PBCR | C4: South | E4: 2014-16 | F4: 1714 | G4: 84.2 | H4: 101.6 | I4: 9 | J4: 15.5 | K4: 2151 | L4: 109.8 | M4: 136 | N4: 7 | O4: 12.5 | P4: =F4+K4 -> 3865 | Q4: =K4/F4 -> 1.2549592 | R4: =J4/H4 -> 0.15255906 | S4: =O4/M4 -> 0.091911765
A5: Kollam district | B5: PBCR | C5: South | E5: 2012-16 | F5: 1986 | G5: 159.4 | H5: 127.7 | I5: 7 | J5: 66.5 | K5: 1956 | L5: 139.1 | M5: 107.1 | N5: 9 | O5: 38.3 | P5: =F5+K5 -> 3942 | Q5: =K5/F5 -> 0.98489426 | R5: =J5/H5 -> 0.52075176 | S5: =O5/M5 -> 0.35760971
A6: Thiruvananthapuram district | B6: PBCR | C6: South | E6: 2012-16 | F6: 2701 | G6: 170.4 | H6: 137.8 | I6: 7 | J6: 57.7 | K6: 2865 | L6: 164.8 | M6: 127.3 | N6: 8 | O6: 39.5 | P6: =F6+K6 -> 5566 | Q6: =K6/F6 -> 1.0607183 | R6: =J6/H6 -> 0.41872279 | S6: =O6/M6 -> 0.31029065
A7: Bangalore | B7: PBCR | C7: South | E7: 2012-14 | F7: 4407 | G7: 96.8 | H7: 122.1 | I7: 7 | J7: 42.6 | K7: 5276 | L7: 125.1 | M7: 146.8 | N7: 6 | O7: 41.5 | P7: =F7+K7 -> 9683 | Q7: =K7/F7 -> 1.1971863 | R7: =J7/H7 -> 0.34889435 | S7: =O7/M7 -> 0.28269755
A8: Chennai | B8: PBCR | C8: South | E8: 2012-16 | F8: 2894 | G8: 121.8 | H8: 119.9 | I8: 8 | J8: 35.7 | K8: 3361 | L8: 141.4 | M8: 132.8 | N8: 7 | O8: 28.8 | P8: =F8+K8 -> 6255 | Q8: =K8/F8 -> 1.1613683 | R8: =J8/H8 -> 0.29774812 | S8: =O8/M8 -> 0.21686747
A9: Kolkata | B9: PBCR | C9: East | E9: 2012-15 | F9: 2547 | G9: 109.9 | H9: 91.2 | I9: 10 | J9: 37.9 | K9: 2288 | L9: 105.9 | M9: 89.2 | N9: 11 | O9: 32.1 | P9: =F9+K9 -> 4835 | Q9: =K9/F9 -> 0.89831174 | R9: =J9/H9 -> 0.41557018 | S9: =O9/M9 -> 0.35986547
A10: Ahmedabad urban | B10: PBCR | C10: West | E10: 2012-16 | F10: 2916 | G10: 89.1 | H10: 98.3 | I10: 9 | J10: 27 | K10: 2205 | L10: 74.7 | M10: 76.7 | N10: 12 | O10: 16.9 | P10: =F10+K10 -> 5121 | Q10: =K10/F10 -> 0.75617284 | R10: =J10/H10 -> 0.27466938 | S10: =O10/M10 -> 0.22033898
A11: Aurangabad | B11: PBCR | C11: West | D11: Yes | E11: 2012-16 | F11: 385 | G11: 56.6 | H11: 70.9 | I11: 13 | J11: 13.5 | K11: 400 | L11: 62.9 | M11: 75.1 | N11: 12 | O11: 8.5 | P11: =F11+K11 -> 785 | Q11: =K11/F11 -> 1.038961 | R11: =J11/H11 -> 0.19040903 | S11: =O11/M11 -> 0.11318242
A12: Osmanabad and Beed | B12: PBCR | C12: West | D12: Yes | E12: 2012-15 | F12: 909 | G12: 39.3 | H12: 39.5 | I12: 23 | J12: 10.3 | K12: 1117 | L12: 52.8 | M12: 49.4 | N12: 19 | O12: 10.4 | P12: =F12+K12 -> 2026 | Q12: =K12/F12 -> 1.2288229 | R12: =J12/H12 -> 0.26075949 | S12: =O12/M12 -> 0.21052632
A13: Barshi Rural | B13: PBCR | C13: West | D13: Yes | E13: 2012-16 | F13: 145 | G13: 53.9 | H13: 50.6 | I13: 17 | J13: 35 | K13: 163 | L13: 67.2 | M13: 61 | N13: 15 | O13: 36.1 | P13: =F13+K13 -> 308 | Q13: =K13/F13 -> 1.1241379 | R13: =J13/H13 -> 0.6916996 | S13: =O13/M13 -> 0.59180328
A14: Mumbai | B14: PBCR | C14: West | D14: Yes | E14: 2012-15 | F14: 6564 | G14: 97.3 | H14: 108.4 | I14: 9 | J14: 66 | K14: 6865 | L14: 117.6 | M14: 116.2 | N14: 8 | O14: 61.4 | P14: =F14+K14 -> 13429 | Q14: =K14/F14 -> 1.0458562 | R14: =J14/H14 -> 0.60885609 | S14: =O14/M14 -> 0.52839931
A15: Pune | B15: PBCR | C15: West | D15: Yes | E15: 2012-16 | F15: 1937 | G15: 67.5 | H15: 83 | I15: 11 | J15: 35.3 | K15: 2164 | L15: 83.3 | M15: 94 | N15: 10 | O15: 35.3 | P15: =F15+K15 -> 4101 | Q15: =K15/F15 -> 1.1171915 | R15: =J15/H15 -> 0.4253012 | S15: =O15/M15 -> 0.37553191
A16: Wardha district | B16: PBCR | C16: Central | D16: Yes | E16: 2012-16 | F16: 478 | G16: 70.4 | H16: 64.5 | I16: 14 | J16: 42.3 | K16: 507 | L16: 78.7 | M16: 69.9 | N16: 14 | O16: 37.1 | P16: =F16+K16 -> 985 | Q16: =K16/F16 -> 1.0606695 | R16: =J16/H16 -> 0.65581395 | S16: =O16/M16 -> 0.53075823
A17: Bhopal | B17: PBCR | C17: Central | E17: 2012-15 | F17: 892 | G17: 83.3 | H17: 101 | I17: 9 | J17: 38.3 | K17: 897 | L17: 90.4 | M17: 106.9 | N17: 8 | O17: 30.9 | P17: =F17+K17 -> 1789 | Q17: =K17/F17 -> 1.0056054 | R17: =J17/H17 -> 0.37920792 | S17: =O17/M17 -> 0.28905519
A18: Nagpur | B18: PBCR | C18: Central | D18: Yes | E18: 2012-16 | F18: 1190 | G18: 89 | H18: 91.1 | I18: 10 | J18: 21.3 | K18: 1209 | L18: 93.1 | M18: 89.8 | N18: 11 | O18: 17.7 | P18: =F18+K18 -> 2399 | Q18: =K18/F18 -> 1.0159664 | R18: =J18/H18 -> 0.233809 | S18: =O18/M18 -> 0.19710468
A19: Manipur state | B19: PBCR | C19: North East | E19: 2012-16 | F19: 740 | G19: 47 | H19: 62.8 | I19: 14 | J19: 20.5 | K19: 900 | L19: 57.8 | M19: 71.1 | N19: 12 | O19: 17.3 | P19: =F19+K19 -> 1640 | Q19: =K19/F19 -> 1.2162162 | R19: =J19/H19 -> 0.32643312 | S19: =O19/M19 -> 0.24331927
A20: Imphal West district | B20: District within Manipur PBCR | C20: North East | E20: 2012-16 | F20: 227 | G20: 85.1 | H20: 95.3 | I20: 9 | J20: 29.6 | K20: 300 | L20: 107.9 | M20: 110.9 | N20: 8 | O20: 24.3 | P20: =F20+K20 -> 527 | Q20: =K20/F20 -> 1.3215859 | R20: =J20/H20 -> 0.31059811 | S20: =O20/M20 -> 0.21911632
A21: Mizoram state | B21: PBCR | C21: North East | E21: 2012-16 | F21: 865 | G21: 146.1 | H21: 207 | I21: 5 | J21: 121.4 | K21: 747 | L21: 127.5 | M21: 172.3 | N21: 5 | O21: 76.4 | P21: =F21+K21 -> 1612 | Q21: =K21/F21 -> 0.86358382 | R21: =J21/H21 -> 0.58647343 | S21: =O21/M21 -> 0.44341265
A22: Aizawl district | B22: District within Mizoram PBCR | C22: North East | E22: 2012-16 | F22: 436 | G22: 206.2 | H22: 269.4 | I22: 4 | J22: 152.7 | K22: 380 | L22: 174.6 | M22: 214.1 | N22: 5 | O22: 89.5 | P22: =F22+K22 -> 816 | Q22: =K22/F22 -> 0.87155963 | R22: =J22/H22 -> 0.56681514 | S22: =O22/M22 -> 0.41802896
A23: Sikkim state | B23: PBCR | C23: North East | E23: 2012-16 | F23: 234 | G23: 69.9 | H23: 88.7 | I23: 10 | J23: 46.4 | K23: 226 | L23: 75.3 | M23: 97 | N23: 10 | O23: 46.2 | P23: =F23+K23 -> 460 | Q23: =K23/F23 -> 0.96581197 | R23: =J23/H23 -> 0.52311161 | S23: =O23/M23 -> 0.47628866
A24: Tripura state | B24: PBCR | C24: North East | E24: 2012-16 | F24: 1312 | G24: 67 | H24: 80.9 | I24: 11 | J24: 46 | K24: 983 | L24: 52 | M24: 58.3 | N24: 16 | O24: 28.9 | P24: =F24+K24 -> 2295 | Q24: =K24/F24 -> 0.7492378 | R24: =J24/H24 -> 0.56860321 | S24: =O24/M24 -> 0.49571184
A25: West Arunachal | B25: PBCR | C25: North East | E25: 2012-16 | F25: 244 | G25: 56.6 | H25: 101.1 | I25: 8 | J25: 27.3 | K25: 234 | L25: 56.3 | M25: 96.3 | N25: 10 | O25: 18.9 | P25: =F25+K25 -> 478 | Q25: =K25/F25 -> 0.95901639 | R25: =J25/H25 -> 0.27002967 | S25: =O25/M25 -> 0.19626168
A26: Papumpare district | B26: District within West Arunachal PBCR | C26: North East | E26: 2012-16 | F26: 94 | G26: 94.8 | H26: 201.2 | I26: 4 | J26: 56.5 | K26: 106 | L26: 105.1 | M26: 219.8 | N26: 4 | O26: 37.9 | P26: =F26+K26 -> 200 | Q26: =K26/F26 -> 1.1276596 | R26: =J26/H26 -> 0.28081511 | S26: =O26/M26 -> 0.17242948
A27: Meghalaya | B27: PBCR | C27: North East | E27: 2012-16 | F27: 938 | G27: 92.6 | H27: 176.8 | I27: 5 | J27: 71.7 | K27: 566 | L27: 55.7 | M27: 96.5 | N27: 9 | O27: 38.1 | P27: =F27+K27 -> 1504 | Q27: =K27/F27 -> 0.60341151 | R27: =J27/H27 -> 0.40554299 | S27: =O27/M27 -> 0.39481865
A28: East Khasi Hills | B28: District within Meghalaya PBCR | C28: North East | E28: 2012-16 | F28: 577 | G28: 131 | H28: 227.9 | I28: 4 | J28: 95 | K28: 346 | L28: 76.9 | M28: 118.6 | N28: 8 | O28: 51.5 | P28: =F28+K28 -> 923 | Q28: =K28/F28 -> 0.59965338 | R28: =J28/H28 -> 0.4168495 | S28: =O28/M28 -> 0.43423272
A29: Nagaland | B29: PBCR | C29: North East | E29: 2012-16 | F29: 281 | G29: 74.5 | H29: 124.5 | I29: 7 | J29: 27.8 | K29: 198 | L29: 56.3 | M29: 88.2 | N29: 10 | O29: 11.1 | P29: =F29+K29 -> 479 | Q29: =K29/F29 -> 0.70462633 | R29: =J29/H29 -> 0.22329317 | S29: =O29/M29 -> 0.12585034
A30: Pasighat | B30: PBCR | C30: North East | E30: 2012-16 | F30: 64 | G30: 90.7 | H30: 120.4 | I30: 7 | J30: 30.9 | K30: 61 | L30: 88.1 | M30: 116.2 | N30: 8 | O30: 22 | P30: =F30+K30 -> 125 | Q30: =K30/F30 -> 0.953125 | R30: =J30/H30 -> 0.25664452 | S30: =O30/M30 -> 0.18932874
... A33: Kamrup urban | B33: PBCR | C33: North East | E33: 2012-16 | F33: 1245 | G33: 190.5 | H33: 213 | I33: 4 | J33: 66.7 | K33: 958 | L33: 150.8 | M33: 169.6 | N33: 6 | O33: 37.3 | P33: =F33+K33 -> 2203 | Q33: =K33/F33 -> 0.76947791 | R33: =J33/H33 -> 0.31314554 | S33: =O33/M33 -> 0.21992925
A35: Source: JCO Glob Oncol 2020;6:1063-75, Table 1 (annual average number of patients, incidence rate per 100,000, cumulative risk and mortality rate for 28 PBCRs). Rows with Level = District are sub-registry districts printed beneath their parent PBCR. Meghalaya covers East Khasi Hills, West Khasi Hills, Jaintia Hills and Ri Bhoi; Nagaland covers Kohima and Dimapur; Pasighat covers East Siang and Upper Siang; West Arunachal covers Tawang, West Kameng, East Kameng, Upper Subansiri, Lower Subansiri, Kurung Kumey, Papumpare and West Siang. AAMR/AAR is a derived crude proxy; the paper's own mortality-to-incidence ratios (M:I%) are in Key Findings. Do not sum district rows with their parent PBCR.

Sheet Tobacco-related Cancers
A1: Registry | B1: Region | C1: Male - share of cancers tobacco-associated (%) | D1: Male - tobacco-assoc. crude rate /100,000 | E1: Male - tobacco-assoc. age-adj. rate /100,000 | F1: Female - share of cancers tobacco-associated (%) | G1: Female - tobacco-assoc. crude rate /100,000 | H1: Female - tobacco-assoc. age-adj. rate /100,000 | I1: Male share recomputed (tobacco CR / all-site CR, %) | J1: Female share recomputed (%)
A2: Delhi | B2: North | C2: 41.2 | D2: 46.3 | E2: 62.1 | F2: 12.4 | G2: 14.8 | H2: 18.5 | I2: =D2/INDEX('PBCR Incidence Table'!$G$2:$G$33,MATCH(A2,'PBCR Incidence Table'!$A$2:$A$33,0))*100 -> 41.228851 | J2: =G2/INDEX('PBCR Incidence Table'!$L$2:$L$33,MATCH(A2,'PBCR Incidence Table'!$A$2:$A$33,0))*100 -> 12.374582
A3: Patiala district | B3: North | C3: 36.4 | D3: 36.9 | E3: 39.9 | F3: 13.1 | G3: 16.8 | H3: 16.6 | I3: =D3/INDEX('PBCR Incidence Table'!$G$2:$G$33,MATCH(A3,'PBCR Incidence Table'!$A$2:$A$33,0))*100 -> 36.318898 | J3: =G3/INDEX('PBCR Incidence Table'!$L$2:$L$33,MATCH(A3,'PBCR Incidence Table'!$A$2:$A$33,0))*100 -> 13.155834
A4: Kollam district | B4: South | C4: 42.5 | D4: 67.7 | E4: 52.9 | F4: 12.4 | G4: 17.2 | H4: 12.4 | I4: =D4/INDEX('PBCR Incidence Table'!$G$2:$G$33,MATCH(A4,'PBCR Incidence Table'!$A$2:$A$33,0))*100 -> 42.471769 | J4: =G4/INDEX('PBCR Incidence Table'!$L$2:$L$33,MATCH(A4,'PBCR Incidence Table'!$A$2:$A$33,0))*100 -> 12.365205
A5: Hyderabad district | B5: South | C5: 42.2 | D5: 35.6 | E5: 42.6 | F5: 13.5 | G5: 14.8 | H5: 19.1 | I5: =D5/INDEX('PBCR Incidence Table'!$G$2:$G$33,MATCH(A5,'PBCR Incidence Table'!$A$2:$A$33,0))*100 -> 42.280285 | J5: =G5/INDEX('PBCR Incidence Table'!$L$2:$L$33,MATCH(A5,'PBCR Incidence Table'!$A$2:$A$33,0))*100 -> 13.479053
A6: Chennai | B6: South | C6: 40.6 | D6: 49.5 | E6: 47.6 | F6: 13.6 | G6: 19.2 | H6: 18.1 | I6: =D6/INDEX('PBCR Incidence Table'!$G$2:$G$33,MATCH(A6,'PBCR Incidence Table'!$A$2:$A$33,0))*100 -> 40.640394 | J6: =G6/INDEX('PBCR Incidence Table'!$L$2:$L$33,MATCH(A6,'PBCR Incidence Table'!$A$2:$A$33,0))*100 -> 13.578501
A7: Thiruvananthapuram district | B7: South | C7: 36.1 | D7: 62 | E7: 49 | F7: 10.1 | G7: 16.8 | H7: 12.5 | I7: =D7/INDEX('PBCR Incidence Table'!$G$2:$G$33,MATCH(A7,'PBCR Incidence Table'!$A$2:$A$33,0))*100 -> 36.384977 | J7: =G7/INDEX('PBCR Incidence Table'!$L$2:$L$33,MATCH(A7,'PBCR Incidence Table'!$A$2:$A$33,0))*100 -> 10.194175
A8: Bangalore | B8: South | C8: 33.4 | D8: 29.7 | E8: 38.7 | F8: 14.2 | G8: 16.3 | H8: 20.1 | I8: =D8/INDEX('PBCR Incidence Table'!$G$2:$G$33,MATCH(A8,'PBCR Incidence Table'!$A$2:$A$33,0))*100 -> 30.681818 | J8: =G8/INDEX('PBCR Incidence Table'!$L$2:$L$33,MATCH(A8,'PBCR Incidence Table'!$A$2:$A$33,0))*100 -> 13.029576
A9: Kolkata | B9: East | C9: 46.7 | D9: 51.3 | E9: 42.3 | F9: 15.4 | G9: 16.3 | H9: 13.7 | I9: =D9/INDEX('PBCR Incidence Table'!$G$2:$G$33,MATCH(A9,'PBCR Incidence Table'!$A$2:$A$33,0))*100 -> 46.678799 | J9: =G9/INDEX('PBCR Incidence Table'!$L$2:$L$33,MATCH(A9,'PBCR Incidence Table'!$A$2:$A$33,0))*100 -> 15.391879
A10: Ahmedabad urban | B10: West | C10: 56.1 | D10: 50 | E10: 54.3 | F10: 18.6 | G10: 13.9 | H10: 14.5 | I10: =D10/INDEX('PBCR Incidence Table'!$G$2:$G$33,MATCH(A10,'PBCR Incidence Table'!$A$2:$A$33,0))*100 -> 56.116723 | J10: =G10/INDEX('PBCR Incidence Table'!$L$2:$L$33,MATCH(A10,'PBCR Incidence Table'!$A$2:$A$33,0))*100 -> 18.607764
A11: Aurangabad | B11: West | C11: 55.8 | D11: 31.6 | E11: 40 | F11: 16.3 | G11: 10.2 | H11: 12.7 | I11: =D11/INDEX('PBCR Incidence Table'!$G$2:$G$33,MATCH(A11,'PBCR Incidence Table'!$A$2:$A$33,0))*100 -> 55.830389 | J11: =G11/INDEX('PBCR Incidence Table'!$L$2:$L$33,MATCH(A11,'PBCR Incidence Table'!$A$2:$A$33,0))*100 -> 16.216216
A12: Osmanabad and Beed | B12: West | C12: 41 | D12: 16.1 | E12: 16.5 | F12: 12.7 | G12: 6.7 | H12: 6.1 | I12: =D12/INDEX('PBCR Incidence Table'!$G$2:$G$33,MATCH(A12,'PBCR Incidence Table'!$A$2:$A$33,0))*100 -> 40.966921 | J12: =G12/INDEX('PBCR Incidence Table'!$L$2:$L$33,MATCH(A12,'PBCR Incidence Table'!$A$2:$A$33,0))*100 -> 12.689394
A13: Pune | B13: West | C13: 39.1 | D13: 26.4 | E13: 32.5 | F13: 15.2 | G13: 12.7 | H13: 14.6 | I13: =D13/INDEX('PBCR Incidence Table'!$G$2:$G$33,MATCH(A13,'PBCR Incidence Table'!$A$2:$A$33,0))*100 -> 39.111111 | J13: =G13/INDEX('PBCR Incidence Table'!$L$2:$L$33,MATCH(A13,'PBCR Incidence Table'!$A$2:$A$33,0))*100 -> 15.246098
... A33: West Arunachal | B33: North East | C33: 24.5 | D33: 13.9 | E33: 26.6 | F33: 11.1 | G33: 6.3 | H33: 13.7 | I33: =D33/INDEX('PBCR Incidence Table'!$G$2:$G$33,MATCH(A33,'PBCR Incidence Table'!$A$2:$A$33,0))*100 -> 24.558304 | J33: =G33/INDEX('PBCR Incidence Table'!$L$2:$L$33,MATCH(A33,'PBCR Incidence Table'!$A$2:$A$33,0))*100 -> 11.190053
A35: Source: JCO 2020, Fig. 2 - sites of cancer associated with tobacco use (lip C00; tongue C01-C02; mouth C03-C06; pharynx C10, C12-C14; oesophagus C15; larynx C32; lung C33-C34; urinary bladder C67), 2012-2016. The figure prints the rate pair as (crude, age-adjusted) on the male side and (age-adjusted, crude) on the female side; they are normalised here, which is confirmed by the recomputed shares (cols I-J) matching the printed shares (cols C, F).

Sheet Cancer Trends (APC)
A1: Cancer site | B1: Sex | C1: Registry | D1: Region | E1: Annual percentage change in age-adj. rate (APC, %) | F1: Statistically significant (P < .05) | G1: Direction | H1: Significant increase / decrease
A2: All sites | B2: Male | C2: Kamrup urban | D2: North East | E2: 3.8 | F2: Yes | G2: =IF(E2>0,"Increase",IF(E2<0,"Decrease","No change")) -> Increase | H2: =IF(F2="Yes",G2&" (significant)","Not significant") -> Increase (significant)
A3: All sites | B3: Male | C3: Thiruvananthapuram taluk | D3: South | E3: 3.2 | F3: Yes | G3: =IF(E3>0,"Increase",IF(E3<0,"Decrease","No change")) -> Increase | H3: =IF(F3="Yes",G3&" (significant)","Not significant") -> Increase (significant)
A4: All sites | B4: Male | C4: Aurangabad | D4: West | E4: 2.3 | F4: Yes | G4: =IF(E4>0,"Increase",IF(E4<0,"Decrease","No change")) -> Increase | H4: =IF(F4="Yes",G4&" (significant)","Not significant") -> Increase (significant)
A5: All sites | B5: Male | C5: Pune | D5: West | E5: 1.6 | F5: Yes | G5: =IF(E5>0,"Increase",IF(E5<0,"Decrease","No change")) -> Increase | H5: =IF(F5="Yes",G5&" (significant)","Not significant") -> Increase (significant)
A6: All sites | B6: Male | C6: Chennai | D6: South | E6: 0.9 | F6: Yes | G6: =IF(E6>0,"Increase",IF(E6<0,"Decrease","No change")) -> Increase | H6: =IF(F6="Yes",G6&" (significant)","Not significant") -> Increase (significant)
A7: All sites | B7: Male | C7: Delhi | D7: North | E7: 0.9 | F7: Yes | G7: =IF(E7>0,"Increase",IF(E7<0,"Decrease","No change")) -> Increase | H7: =IF(F7="Yes",G7&" (significant)","Not significant") -> Increase (significant)
A8: All sites | B8: Male | C8: Nagpur | D8: Central | E8: 0.9 | F8: No | G8: =IF(E8>0,"Increase",IF(E8<0,"Decrease","No change")) -> Increase | H8: =IF(F8="Yes",G8&" (significant)","Not significant") -> Not significant
A9: All sites | B9: Male | C9: Bangalore | D9: South | E9: 0.8 | F9: Yes | G9: =IF(E9>0,"Increase",IF(E9<0,"Decrease","No change")) -> Increase | H9: =IF(F9="Yes",G9&" (significant)","Not significant") -> Increase (significant)
A10: All sites | B10: Male | C10: Mizoram state | D10: North East | E10: 0.7 | F10: No | G10: =IF(E10>0,"Increase",IF(E10<0,"Decrease","No change")) -> Increase | H10: =IF(F10="Yes",G10&" (significant)","Not significant") -> Not significant
A11: All sites | B11: Male | C11: Kollam district | D11: South | E11: 0.7 | F11: No | G11: =IF(E11>0,"Increase",IF(E11<0,"Decrease","No change")) -> Increase | H11: =IF(F11="Yes",G11&" (significant)","Not significant") -> Not significant
A12: All sites | B12: Male | C12: Barshi Rural | D12: West | E12: 0.3 | F12: No | G12: =IF(E12>0,"Increase",IF(E12<0,"Decrease","No change")) -> Increase | H12: =IF(F12="Yes",G12&" (significant)","Not significant") -> Not significant
A13: All sites | B13: Male | C13: Bhopal | D13: Central | E13: 0.1 | F13: No | G13: =IF(E13>0,"Increase",IF(E13<0,"Decrease","No change")) -> Increase | H13: =IF(F13="Yes",G13&" (significant)","Not significant") -> Not significant
... A153: Stomach | B153: Female | C153: Imphal West district | D153: North East | E153: -3.5 | F153: No | G153: =IF(E153>0,"Increase",IF(E153<0,"Decrease","No change")) -> Decrease | H153: =IF(F153="Yes",G153&" (significant)","Not significant") -> Not significant
A155: Source: JCO 2020, Fig. 4 - APC in age-adjusted incidence rates (Joinpoint regression; 16 PBCRs with >=10 years of data). Values were read from the bar-chart images (label and value pairs); asterisk in the figure = significant (P < .05). Calendar years of data: Chennai 1982-2016; Mumbai 1982-2015; Bangalore 1982-2014; Barshi rural 1988-2016; Bhopal 1988-2015; Delhi 1988-2014; Kamrup urban 2003-2016; Mizoram state 2004-2016; Nagpur 2005-2016; Pune 2006-2016 (other registries as listed in the figure caption). Registries with <10 patients per year were not analysed. Thiruvananthapuram PBCR expanded to district level from 2012, so taluk data were used.

Sheet Clinical Stage
A1: Data source | B1: Population / note | C1: Cancer site | D1: Sex | E1: Localised only (%) | F1: Loco-regional (%) | G1: Distant metastasis (%) | H1: Unknown extent (%) | I1: Total (%) | J1: Advanced at diagnosis: loco-regional + distant (%) | K1: Basis / reading note
A2: India - 58 HBCRs (JCO Fig 3) | B2: N = 667,666 patients, 2012-2016 | C2: Breast | D2: Female | E2: 29 | F2: 57 | G2: 10.3 | H2: 3.7 | I2: =SUM(E2:H2) -> 100 | J2: =F2+G2 -> 67.3 | K2: Series assignment inferred (text confirms loco-regional 57.0%)
A3: India - 58 HBCRs (JCO Fig 3) | B3: N = 667,666 patients, 2012-2016 | C3: Cervix uteri | D3: Female | E3: 32.8 | F3: 60 | G3: 5.1 | H3: 2.2 | I3: =SUM(E3:H3) -> 100.1 | J3: =F3+G3 -> 65.1 | K3: Series assignment inferred (text confirms loco-regional 60.0%)
A4: India - 58 HBCRs (JCO Fig 3) | B4: N = 667,666 patients, 2012-2016 | C4: Head & neck | D4: Both sexes | E4: 25.2 | F4: 66.6 | G4: 4.8 | H4: 3.4 | I4: =SUM(E4:H4) -> 100 | J4: =F4+G4 -> 71.4 | K4: Series assignment inferred (text confirms loco-regional 66.6%)
A5: India - 58 HBCRs (JCO Fig 3) | B5: N = 667,666 patients, 2012-2016 | C5: Stomach | D5: Both sexes | E5: 18.7 | F5: 50.8 | G5: 24.7 | H5: 5.8 | I5: =SUM(E5:H5) -> 100 | J5: =F5+G5 -> 75.5 | K5: Series assignment inferred (text confirms loco-regional 50.8%; localized <1/5)
A6: India - 58 HBCRs (JCO Fig 3) | B6: N = 667,666 patients, 2012-2016 | C6: Lung | D6: Male | E6: 13.9 | F6: 37 | G6: 44 | H6: 5.1 | I6: =SUM(E6:H6) -> 100 | J6: =F6+G6 -> 81 | K6: Series assignment inferred (text confirms distant 44.0%)
A7: India - 58 HBCRs (JCO Fig 3) | B7: N = 667,666 patients, 2012-2016 | C7: Lung | D7: Female | E7: 17 | F7: 29.8 | G7: 47.6 | H7: 5.6 | I7: =SUM(E7:H7) -> 100 | J7: =F7+G7 -> 77.4 | K7: Series assignment inferred (text confirms distant 47.6%)
A8: Maharashtra - 3 HBCRs (Fact Sheet p5) | B8: Hospital data, may not represent whole state | C8: Lung | D8: Male | E8: 8 | F8: 25 | G8: 50 | H8: 17 | I8: =SUM(E8:H8) -> 100 | J8: =F8+G8 -> 75 | K8: As printed on bar chart
A9: Maharashtra - 3 HBCRs (Fact Sheet p5) | B9: Hospital data, may not represent whole state | C9: Stomach | D9: Male | E9: 11 | F9: 41 | G9: 28 | H9: 20 | I9: =SUM(E9:H9) -> 100 | J9: =F9+G9 -> 69 | K9: As printed on bar chart
A10: Maharashtra - 3 HBCRs (Fact Sheet p5) | B10: Hospital data, may not represent whole state | C10: Head & neck | D10: Male | E10: 25 | F10: 66 | G10: 1 | H10: 8 | I10: =SUM(E10:H10) -> 100 | J10: =F10+G10 -> 67 | K10: As printed on bar chart
A11: Maharashtra - 3 HBCRs (Fact Sheet p5) | B11: Hospital data, may not represent whole state | C11: Breast | D11: Female | E11: 19 | F11: 55 | G11: 13 | H11: 13 | I11: =SUM(E11:H11) -> 100 | J11: =F11+G11 -> 68 | K11: As printed on bar chart
A12: Maharashtra - 3 HBCRs (Fact Sheet p5) | B12: Hospital data, may not represent whole state | C12: Cervix uteri | D12: Female | E12: 33 | F12: 50 | G12: 7 | H12: 10 | I12: =SUM(E12:H12) -> 100 | J12: =F12+G12 -> 57 | K12: As printed on bar chart
A13: Maharashtra - 3 HBCRs (Fact Sheet p5) | B13: Hospital data, may not represent whole state | C13: Lung | D13: Female | E13: 9 | F13: 17 | G13: 56 | H13: 18 | I13: =SUM(E13:H13) -> 100 | J13: =F13+G13 -> 73 | K13: As printed on bar chart
... A15: Maharashtra - 3 HBCRs (Fact Sheet p5) | B15: Hospital data, may not represent whole state | C15: Head & neck | D15: Female | E15: 28 | F15: 63 | G15: 1 | H15: 8 | I15: =SUM(E15:H15) -> 100 | J15: =F15+G15 -> 64 | K15: As printed on bar chart
A17: Sources: JCO 2020 Fig. 3 (58 hospital-based cancer registries, patients diagnosed 2012-2016, pre-treatment clinical extent of disease) and Maharashtra Fact Sheet 2021 section C (three Maharashtra HBCRs, not representative of the whole state). Totals may differ slightly from 100 due to rounding in the source. For the JCO figure the PDF text layer lists values without series labels; series were assigned using the percentages quoted in the paper text.

Sheet Method Comparison
A1: Characteristic | B1: GLOBOCAN (refs 1,2) | C1: GBD (India State-Level Disease Burden Initiative) | D1: NCRP (IJMR 2022 estimates)
A2: Data sources | B2: PBCRs (27) from the NCRP 2012-2014 and Dindigul, Mansa, Sangrur PBCRs incidence data | C2: PBCRs (42) and Sample Registration System, cause of death data from India. Cancer registry data were used as the gold standard | D2: PBCRs (28) from the NCRP, 2020 report of 2012-2016 and Dindigul PBCR incidence data
A3: Population estimates | B3: North East States, India's rural and urban population derived from United Nation and Census of India, 2011 | C3: Not mentioned | D3: State wise population estimation based on Census of India, 2011
A4: Exclusion | B4: Hospital-Based Cancer Registry | C4: Hospital-Based Cancer Registry | D4: Hospital-Based Cancer Registry
A5: Method | B5: Weighted average of the most recent local rates applied to 2020 population | C5: Mortality estimates arrived by multiplying incidence with modelled mortality-incidence ratio | D5: The estimation of cancer incidence is based on registry data from India. Weighted average of the most recent local rates (2012-2016) applied to 2022 population
A6: Cancer measure | B6: Age specific incidence rate by site, sex and age | C6: Mortality data from vital registration used as base to calculate the different measures | D6: Age-specific incidence rate by site, sex and age
A7: Outcome | B7: Incidence and rates for India | C7: Cancer mortality, incidence and DALY's by State/India | D7: Incidence and rates for India
A9: Source: IJMR 2022, Supplementary Table II - differences in burden estimation methods for India by selected sources. GLOBOCAN = Global Cancer Observatory; GBD = Global Burden of Disease; PBCR = population-based cancer registry; NCRP = National Cancer Registry Programme; DALY = disability-adjusted life years.

Sheet MH PBCR Profile
A1: PBCR (Maharashtra) | B1: Establishment year | C1: Implementing centre / location | D1: Coverage area | E1: Area (sq km) | F1: Urban (%) | G1: Rural (%) | H1: Male - annual avg cases | I1: Female - annual avg cases | J1: Total annual avg cases | K1: Male share of cases | L1: Male crude rate /100,000 | M1: Female crude rate /100,000 | N1: Male age-adj. rate /100,000 | O1: Female age-adj. rate /100,000 | P1: Male cum. risk 0-74 (1 in N) | Q1: Female cum. risk 0-74 (1 in N)
A2: Aurangabad | B2: 1978 | C2: Indian Cancer Society, Mumbai | D2: Aurangabad City Agglomeration | E2: 148 | F2: 100 | G2: 0 | H2: =IFERROR(INDEX('PBCR Incidence Table'!$F$2:$F$33,MATCH($A2,'PBCR Incidence Table'!$A$2:$A$33,0)),"n/a") -> 385 | I2: =IFERROR(INDEX('PBCR Incidence Table'!$K$2:$K$33,MATCH($A2,'PBCR Incidence Table'!$A$2:$A$33,0)),"n/a") -> 400 | J2: =IF(ISNUMBER(H2),H2+I2,"n/a") -> 785 | K2: =IF(ISNUMBER(H2),H2/J2,"n/a") -> 0.49044586 | L2: =IFERROR(INDEX('PBCR Incidence Table'!$G$2:$G$33,MATCH($A2,'PBCR Incidence Table'!$A$2:$A$33,0)),"n/a") -> 56.6 | M2: =IFERROR(INDEX('PBCR Incidence Table'!$L$2:$L$33,MATCH($A2,'PBCR Incidence Table'!$A$2:$A$33,0)),"n/a") -> 62.9 | N2: =IFERROR(INDEX('PBCR Incidence Table'!$H$2:$H$33,MATCH($A2,'PBCR Incidence Table'!$A$2:$A$33,0)),"n/a") -> 70.9 | O2: =IFERROR(INDEX('PBCR Incidence Table'!$M$2:$M$33,MATCH($A2,'PBCR Incidence Table'!$A$2:$A$33,0)),"n/a") -> 75.1 | P2: =IFERROR(INDEX('PBCR Incidence Table'!$I$2:$I$33,MATCH($A2,'PBCR Incidence Table'!$A$2:$A$33,0)),"n/a") -> 13 | Q2: =IFERROR(INDEX('PBCR Incidence Table'!$N$2:$N$33,MATCH($A2,'PBCR Incidence Table'!$A$2:$A$33,0)),"n/a") -> 12
A3: Osmanabad and Beed | B3: 1987 | C3: Nargis Dutt Memorial Cancer Hospital, Barshi | D3: 2 Districts - Osmanabad & Beed | E3: 18262 | F3: 18.7 | G3: 81.3 | H3: =IFERROR(INDEX('PBCR Incidence Table'!$F$2:$F$33,MATCH($A3,'PBCR Incidence Table'!$A$2:$A$33,0)),"n/a") -> 909 | I3: =IFERROR(INDEX('PBCR Incidence Table'!$K$2:$K$33,MATCH($A3,'PBCR Incidence Table'!$A$2:$A$33,0)),"n/a") -> 1117 | J3: =IF(ISNUMBER(H3),H3+I3,"n/a") -> 2026 | K3: =IF(ISNUMBER(H3),H3/J3,"n/a") -> 0.44866732 | L3: =IFERROR(INDEX('PBCR Incidence Table'!$G$2:$G$33,MATCH($A3,'PBCR Incidence Table'!$A$2:$A$33,0)),"n/a") -> 39.3 | M3: =IFERROR(INDEX('PBCR Incidence Table'!$L$2:$L$33,MATCH($A3,'PBCR Incidence Table'!$A$2:$A$33,0)),"n/a") -> 52.8 | N3: =IFERROR(INDEX('PBCR Incidence Table'!$H$2:$H$33,MATCH($A3,'PBCR Incidence Table'!$A$2:$A$33,0)),"n/a") -> 39.5 | O3: =IFERROR(INDEX('PBCR Incidence Table'!$M$2:$M$33,MATCH($A3,'PBCR Incidence Table'!$A$2:$A$33,0)),"n/a") -> 49.4 | P3: =IFERROR(INDEX('PBCR Incidence Table'!$I$2:$I$33,MATCH($A3,'PBCR Incidence Table'!$A$2:$A$33,0)),"n/a") -> 23 | Q3: =IFERROR(INDEX('PBCR Incidence Table'!$N$2:$N$33,MATCH($A3,'PBCR Incidence Table'!$A$2:$A$33,0)),"n/a") -> 19
A4: Barshi Rural | B4: 1987 | C4: Nargis Dutt Memorial Cancer Hospital, Barshi | D4: Rural area of 3 Taluks namely Barshi from Solapur district and Bhum & Paranda from Osmanabad district | E4: 3713 | F4: 0 | G4: 100 | H4: =IFERROR(INDEX('PBCR Incidence Table'!$F$2:$F$33,MATCH($A4,'PBCR Incidence Table'!$A$2:$A$33,0)),"n/a") -> 145 | I4: =IFERROR(INDEX('PBCR Incidence Table'!$K$2:$K$33,MATCH($A4,'PBCR Incidence Table'!$A$2:$A$33,0)),"n/a") -> 163 | J4: =IF(ISNUMBER(H4),H4+I4,"n/a") -> 308 | K4: =IF(ISNUMBER(H4),H4/J4,"n/a") -> 0.47077922 | L4: =IFERROR(INDEX('PBCR Incidence Table'!$G$2:$G$33,MATCH($A4,'PBCR Incidence Table'!$A$2:$A$33,0)),"n/a") -> 53.9 | M4: =IFERROR(INDEX('PBCR Incidence Table'!$L$2:$L$33,MATCH($A4,'PBCR Incidence Table'!$A$2:$A$33,0)),"n/a") -> 67.2 | N4: =IFERROR(INDEX('PBCR Incidence Table'!$H$2:$H$33,MATCH($A4,'PBCR Incidence Table'!$A$2:$A$33,0)),"n/a") -> 50.6 | O4: =IFERROR(INDEX('PBCR Incidence Table'!$M$2:$M$33,MATCH($A4,'PBCR Incidence Table'!$A$2:$A$33,0)),"n/a") -> 61 | P4: =IFERROR(INDEX('PBCR Incidence Table'!$I$2:$I$33,MATCH($A4,'PBCR Incidence Table'!$A$2:$A$33,0)),"n/a") -> 17 | Q4: =IFERROR(INDEX('PBCR Incidence Table'!$N$2:$N$33,MATCH($A4,'PBCR Incidence Table'!$A$2:$A$33,0)),"n/a") -> 15
A5: Mumbai | B5: 1963 | C5: Indian Cancer Society, Mumbai | D5: Greater Mumbai (Mumbai City & Mumbai Suburban District) | E5: 603 | F5: 100 | G5: 0 | H5: =IFERROR(INDEX('PBCR Incidence Table'!$F$2:$F$33,MATCH($A5,'PBCR Incidence Table'!$A$2:$A$33,0)),"n/a") -> 6564 | I5: =IFERROR(INDEX('PBCR Incidence Table'!$K$2:$K$33,MATCH($A5,'PBCR Incidence Table'!$A$2:$A$33,0)),"n/a") -> 6865 | J5: =IF(ISNUMBER(H5),H5+I5,"n/a") -> 13429 | K5: =IF(ISNUMBER(H5),H5/J5,"n/a") -> 0.48879291 | L5: =IFERROR(INDEX('PBCR Incidence Table'!$G$2:$G$33,MATCH($A5,'PBCR Incidence Table'!$A$2:$A$33,0)),"n/a") -> 97.3 | M5: =IFERROR(INDEX('PBCR Incidence Table'!$L$2:$L$33,MATCH($A5,'PBCR Incidence Table'!$A$2:$A$33,0)),"n/a") -> 117.6 | N5: =IFERROR(INDEX('PBCR Incidence Table'!$H$2:$H$33,MATCH($A5,'PBCR Incidence Table'!$A$2:$A$33,0)),"n/a") -> 108.4 | O5: =IFERROR(INDEX('PBCR Incidence Table'!$M$2:$M$33,MATCH($A5,'PBCR Incidence Table'!$A$2:$A$33,0)),"n/a") -> 116.2 | P5: =IFERROR(INDEX('PBCR Incidence Table'!$I$2:$I$33,MATCH($A5,'PBCR Incidence Table'!$A$2:$A$33,0)),"n/a") -> 9 | Q5: =IFERROR(INDEX('PBCR Incidence Table'!$N$2:$N$33,MATCH($A5,'PBCR Incidence Table'!$A$2:$A$33,0)),"n/a") -> 8
A6: Pune | B6: 1972 | C6: Indian Cancer Society, Mumbai | D6: Pune City Corporation | E6: 613 | F6: 100 | G6: 0 | H6: =IFERROR(INDEX('PBCR Incidence Table'!$F$2:$F$33,MATCH($A6,'PBCR Incidence Table'!$A$2:$A$33,0)),"n/a") -> 1937 | I6: =IFERROR(INDEX('PBCR Incidence Table'!$K$2:$K$33,MATCH($A6,'PBCR Incidence Table'!$A$2:$A$33,0)),"n/a") -> 2164 | J6: =IF(ISNUMBER(H6),H6+I6,"n/a") -> 4101 | K6: =IF(ISNUMBER(H6),H6/J6,"n/a") -> 0.47232382 | L6: =IFERROR(INDEX('PBCR Incidence Table'!$G$2:$G$33,MATCH($A6,'PBCR Incidence Table'!$A$2:$A$33,0)),"n/a") -> 67.5 | M6: =IFERROR(INDEX('PBCR Incidence Table'!$L$2:$L$33,MATCH($A6,'PBCR Incidence Table'!$A$2:$A$33,0)),"n/a") -> 83.3 | N6: =IFERROR(INDEX('PBCR Incidence Table'!$H$2:$H$33,MATCH($A6,'PBCR Incidence Table'!$A$2:$A$33,0)),"n/a") -> 83 | O6: =IFERROR(INDEX('PBCR Incidence Table'!$M$2:$M$33,MATCH($A6,'PBCR Incidence Table'!$A$2:$A$33,0)),"n/a") -> 94 | P6: =IFERROR(INDEX('PBCR Incidence Table'!$I$2:$I$33,MATCH($A6,'PBCR Incidence Table'!$A$2:$A$33,0)),"n/a") -> 11 | Q6: =IFERROR(INDEX('PBCR Incidence Table'!$N$2:$N$33,MATCH($A6,'PBCR Incidence Table'!$A$2:$A$33,0)),"n/a") -> 10
A7: Wardha district | B7: 2010 | C7: Mahatma Gandhi Institute of Medical Sciences, Sevagram | D7: Wardha District | E7: 6309 | F7: 32.5 | G7: 67.5 | H7: =IFERROR(INDEX('PBCR Incidence Table'!$F$2:$F$33,MATCH($A7,'PBCR Incidence Table'!$A$2:$A$33,0)),"n/a") -> 478 | I7: =IFERROR(INDEX('PBCR Incidence Table'!$K$2:$K$33,MATCH($A7,'PBCR Incidence Table'!$A$2:$A$33,0)),"n/a") -> 507 | J7: =IF(ISNUMBER(H7),H7+I7,"n/a") -> 985 | K7: =IF(ISNUMBER(H7),H7/J7,"n/a") -> 0.48527919 | L7: =IFERROR(INDEX('PBCR Incidence Table'!$G$2:$G$33,MATCH($A7,'PBCR Incidence Table'!$A$2:$A$33,0)),"n/a") -> 70.4 | M7: =IFERROR(INDEX('PBCR Incidence Table'!$L$2:$L$33,MATCH($A7,'PBCR Incidence Table'!$A$2:$A$33,0)),"n/a") -> 78.7 | N7: =IFERROR(INDEX('PBCR Incidence Table'!$H$2:$H$33,MATCH($A7,'PBCR Incidence Table'!$A$2:$A$33,0)),"n/a") -> 64.5 | O7: =IFERROR(INDEX('PBCR Incidence Table'!$M$2:$M$33,MATCH($A7,'PBCR Incidence Table'!$A$2:$A$33,0)),"n/a") -> 69.9 | P7: =IFERROR(INDEX('PBCR Incidence Table'!$I$2:$I$33,MATCH($A7,'PBCR Incidence Table'!$A$2:$A$33,0)),"n/a") -> 14 | Q7: =IFERROR(INDEX('PBCR Incidence Table'!$N$2:$N$33,MATCH($A7,'PBCR Incidence Table'!$A$2:$A$33,0)),"n/a") -> 14
A8: Nagpur | B8: 1980 | C8: Indian Cancer Society, Mumbai | D8: Nagpur City Agglomeration | E8: 237 | F8: 100 | G8: 0 | H8: =IFERROR(INDEX('PBCR Incidence Table'!$F$2:$F$33,MATCH($A8,'PBCR Incidence Table'!$A$2:$A$33,0)),"n/a") -> 1190 | I8: =IFERROR(INDEX('PBCR Incidence Table'!$K$2:$K$33,MATCH($A8,'PBCR Incidence Table'!$A$2:$A$33,0)),"n/a") -> 1209 | J8: =IF(ISNUMBER(H8),H8+I8,"n/a") -> 2399 | K8: =IF(ISNUMBER(H8),H8/J8,"n/a") -> 0.49604002 | L8: =IFERROR(INDEX('PBCR Incidence Table'!$G$2:$G$33,MATCH($A8,'PBCR Incidence Table'!$A$2:$A$33,0)),"n/a") -> 89 | M8: =IFERROR(INDEX('PBCR Incidence Table'!$L$2:$L$33,MATCH($A8,'PBCR Incidence Table'!$A$2:$A$33,0)),"n/a") -> 93.1 | N8: =IFERROR(INDEX('PBCR Incidence Table'!$H$2:$H$33,MATCH($A8,'PBCR Incidence Table'!$A$2:$A$33,0)),"n/a") -> 91.1 | O8: =IFERROR(INDEX('PBCR Incidence Table'!$M$2:$M$33,MATCH($A8,'PBCR Incidence Table'!$A$2:$A$33,0)),"n/a") -> 89.8 | P8: =IFERROR(INDEX('PBCR Incidence Table'!$I$2:$I$33,MATCH($A8,'PBCR Incidence Table'!$A$2:$A$33,0)),"n/a") -> 10 | Q8: =IFERROR(INDEX('PBCR Incidence Table'!$N$2:$N$33,MATCH($A8,'PBCR Incidence Table'!$A$2:$A$33,0)),"n/a") -> 11
A9: Nagpur rural | B9: 2020 | C9: R.S.T. Regional Cancer Hospital & Research Centre, Nagpur | D9: Rural areas of Saoner and Nagpur rural of Nagpur district | E9: 1228.93 | F9: 0 | G9: 100 | H9: =IFERROR(INDEX('PBCR Incidence Table'!$F$2:$F$33,MATCH($A9,'PBCR Incidence Table'!$A$2:$A$33,0)),"n/a") -> n/a | I9: =IFERROR(INDEX('PBCR Incidence Table'!$K$2:$K$33,MATCH($A9,'PBCR Incidence Table'!$A$2:$A$33,0)),"n/a") -> n/a | J9: =IF(ISNUMBER(H9),H9+I9,"n/a") -> n/a | K9: =IF(ISNUMBER(H9),H9/J9,"n/a") -> n/a | L9: =IFERROR(INDEX('PBCR Incidence Table'!$G$2:$G$33,MATCH($A9,'PBCR Incidence Table'!$A$2:$A$33,0)),"n/a") -> n/a | M9: =IFERROR(INDEX('PBCR Incidence Table'!$L$2:$L$33,MATCH($A9,'PBCR Incidence Table'!$A$2:$A$33,0)),"n/a") -> n/a | N9: =IFERROR(INDEX('PBCR Incidence Table'!$H$2:$H$33,MATCH($A9,'PBCR Incidence Table'!$A$2:$A$33,0)),"n/a") -> n/a | O9: =IFERROR(INDEX('PBCR Incidence Table'!$M$2:$M$33,MATCH($A9,'PBCR Incidence Table'!$A$2:$A$33,0)),"n/a") -> n/a | P9: =IFERROR(INDEX('PBCR Incidence Table'!$I$2:$I$33,MATCH($A9,'PBCR Incidence Table'!$A$2:$A$33,0)),"n/a") -> n/a | Q9: =IFERROR(INDEX('PBCR Incidence Table'!$N$2:$N$33,MATCH($A9,'PBCR Incidence Table'!$A$2:$A$33,0)),"n/a") -> n/a
A10: Total - 7 registries with incidence data | H10: =SUM(H2:H9) -> 11608 | I10: =SUM(I2:I9) -> 12425 | J10: =H10+I10 -> 24033 | K10: =H10/J10 -> 0.48300254
A11: Hospital-based cancer registries (HBCRs) in Maharashtra - 5 hospitals | C11: Kokilaben Dhirubhai Ambani Hospital and Research Institute, Mumbai; Kolhapur Cancer Centre, Kolhapur; Pravara Institute of Medical Science, Loni; Rashtra Sant Tukdoji Regional Cancer Hospital and Research Centre, Nagpur; Tata Memorial Hospital, Mumbai
A13: Source: Maharashtra Fact Sheet 2021, section I.A (registry description) and the "Cancer incidence and risk" maps (pages 3-4); incidence columns H-Q are linked to sheet PBCR Incidence Table because the fact-sheet maps repeat the JCO Table 1 values for the same seven registries (verified one by one). Nagpur rural was established in 2020 and has no incidence data yet. The fact sheet also reports male/female proportions (e.g. Mumbai 48.9%/51.1%), recomputed in column K.

Sheet MH Childhood Cancer
A1: PBCR (Maharashtra) | B1: Boys 0-14 - annual avg cases | C1: Girls 0-14 - annual avg cases | D1: Boys 0-14 - AAR per million | E1: Girls 0-14 - AAR per million | F1: Boys 0-19 - annual avg cases | G1: Girls 0-19 - annual avg cases | H1: Boys 0-19 - AAR per million | I1: Girls 0-19 - AAR per million | J1: Total 0-14 cases | K1: Boys : girls ratio (0-14 cases) | L1: Total 0-19 cases | M1: Adolescent (15-19) cases
A2: Mumbai | B2: 148 | C2: 93 | D2: 107.1 | E2: 73.7 | F2: 216 | G2: 135 | H2: 108.6 | I2: 76.9 | J2: =B2+C2 -> 241 | K2: =B2/C2 -> 1.5913978 | L2: =F2+G2 -> 351 | M2: =L2-J2 -> 110
A3: Aurangabad | B3: 16 | C3: 9 | D3: 83 | E3: 51.1 | F3: 22 | G3: 13 | H3: 84.1 | I3: 54.4 | J3: =B3+C3 -> 25 | K3: =B3/C3 -> 1.7777778 | L3: =F3+G3 -> 35 | M3: =L3-J3 -> 10
A4: Nagpur | B4: 31 | C4: 20 | D4: 102 | E4: 72.2 | F4: 46 | G4: 34 | H4: 108.1 | I4: 85.4 | J4: =B4+C4 -> 51 | K4: =B4/C4 -> 1.55 | L4: =F4+G4 -> 80 | M4: =L4-J4 -> 29
A5: Wardha district | B5: 14 | C5: 8 | D5: 96.6 | E5: 60.1 | F5: 22 | G5: 14 | H5: 102.2 | I5: 69 | J5: =B5+C5 -> 22 | K5: =B5/C5 -> 1.75 | L5: =F5+G5 -> 36 | M5: =L5-J5 -> 14
A6: Pune | B6: 41 | C6: 26 | D6: 61.7 | E6: 44 | F6: 59 | G6: 37 | H6: 66.4 | I6: 47.6 | J6: =B6+C6 -> 67 | K6: =B6/C6 -> 1.5769231 | L6: =F6+G6 -> 96 | M6: =L6-J6 -> 29
A7: Osmanabad and Beed | B7: 20 | C7: 16 | D7: 29.2 | E7: 28.7 | F7: 33 | G7: 25 | H7: 34.8 | I7: 32.2 | J7: =B7+C7 -> 36 | K7: =B7/C7 -> 1.25 | L7: =F7+G7 -> 58 | M7: =L7-J7 -> 22
A8: Barshi Rural | B8: 4 | C8: 4 | D8: 51.6 | E8: 67.6 | F8: 6 | G8: 5 | H8: 62.4 | I8: 64.3 | J8: =B8+C8 -> 8 | K8: =B8/C8 -> 1 | L8: =F8+G8 -> 11 | M8: =L8-J8 -> 3
A9: Total - 7 registries | B9: =SUM(B2:B8) -> 274 | C9: =SUM(C2:C8) -> 176 | F9: =SUM(F2:F8) -> 404 | G9: =SUM(G2:G8) -> 263 | J9: =SUM(J2:J8) -> 450 | L9: =SUM(L2:L8) -> 667 | M9: =SUM(M2:M8) -> 217
A11: Source: Maharashtra Fact Sheet 2021, page 3 - age-adjusted incidence rates (AAR) of childhood cancers per million. Values were read from the map graphic. Mumbai boys 0-14 AAR is partly overlapped by the map outline and was read as 107.1. Rates for registries with very few cases (Barshi rural: 4 boys, 4 girls) are statistically unstable.

Sheet MH Sites & Tobacco
A1: Table | B1: Sex | C1: Rank / order | D1: Cancer site | E1: Value (%) | F1: Note
A2: Five leading sites (share of all cancers) | B2: Male | C2: 1 | D2: Mouth | E2: 11.1
A3: Five leading sites (share of all cancers) | B3: Male | C3: 2 | D3: Lung | E3: 8.4
A4: Five leading sites (share of all cancers) | B4: Male | C4: 3 | D4: Prostate | E4: 7
A5: Five leading sites (share of all cancers) | B5: Male | C5: 4 | D5: Tongue | E5: 6.1
A6: Five leading sites (share of all cancers) | B6: Male | C6: 5 | D6: Liver | E6: 4.9
A7: Five leading sites (share of all cancers) | B7: Female | C7: 1 | D7: Breast | E7: 29.9
A8: Five leading sites (share of all cancers) | B8: Female | C8: 2 | D8: Cervix uteri | E8: 11
A9: Five leading sites (share of all cancers) | B9: Female | C9: 3 | D9: Ovary | E9: 6.3
A10: Five leading sites (share of all cancers) | B10: Female | C10: 4 | D10: Lung | E10: 4.2
A11: Five leading sites (share of all cancers) | B11: Female | C11: 5 | D11: Mouth | E11: 3.7
A12: Tobacco-associated cancers - overall share | B12: Male | D12: All tobacco-associated sites | E12: 40.6 | F12: Share of all cancers in Maharashtra PBCRs
A13: Tobacco-associated cancers - overall share | B13: Female | D13: All tobacco-associated sites | E13: 15.6 | F13: Share of all cancers in Maharashtra PBCRs
A14: Tobacco-associated cancers - composition | B14: Male | C14: 1 | D14: Mouth | E14: 27 | F14: Others = lip, other oropharynx, hypopharynx, pharynx unspecified
A15: Tobacco-associated cancers - composition | B15: Male | C15: 2 | D15: Lung | E15: 21 | F15: Others = lip, other oropharynx, hypopharynx, pharynx unspecified
A16: Tobacco-associated cancers - composition | B16: Male | C16: 3 | D16: Tongue | E16: 15 | F16: Others = lip, other oropharynx, hypopharynx, pharynx unspecified
A17: Tobacco-associated cancers - composition | B17: Male | C17: 4 | D17: Oesophagus | E17: 11 | F17: Others = lip, other oropharynx, hypopharynx, pharynx unspecified
A18: Tobacco-associated cancers - composition | B18: Male | C18: 5 | D18: Larynx | E18: 10 | F18: Others = lip, other oropharynx, hypopharynx, pharynx unspecified
A19: Tobacco-associated cancers - composition | B19: Male | C19: 6 | D19: Others | E19: 9 | F19: Others = lip, other oropharynx, hypopharynx, pharynx unspecified
A20: Tobacco-associated cancers - composition | B20: Male | C20: 7 | D20: Urinary bladder | E20: 7 | F20: Others = lip, other oropharynx, hypopharynx, pharynx unspecified
A21: Tobacco-associated cancers - composition | B21: Female | C21: 1 | D21: Lung | E21: 27 | F21: Others = lip, other oropharynx, hypopharynx, pharynx unspecified
A22: Tobacco-associated cancers - composition | B22: Female | C22: 2 | D22: Mouth | E22: 24 | F22: Others = lip, other oropharynx, hypopharynx, pharynx unspecified
A23: Tobacco-associated cancers - composition | B23: Female | C23: 3 | D23: Oesophagus | E23: 19 | F23: Others = lip, other oropharynx, hypopharynx, pharynx unspecified
A24: Tobacco-associated cancers - composition | B24: Female | C24: 4 | D24: Tongue | E24: 13 | F24: Others = lip, other oropharynx, hypopharynx, pharynx unspecified
A25: Tobacco-associated cancers - composition | B25: Female | C25: 5 | D25: Others | E25: 8 | F25: Others = lip, other oropharynx, hypopharynx, pharynx unspecified
... A27: Tobacco-associated cancers - composition | B27: Female | C27: 7 | D27: Larynx | E27: 3 | F27: Others = lip, other oropharynx, hypopharynx, pharynx unspecified
A28: Check: composition sums (should be 100) | B28: Male | E28: =SUMIFS(E2:E27,A2:A27,"Tobacco-associated cancers - composition",B2:B27,"Male") -> 100
A29: Check: composition sums (should be 100) | B29: Female | E29: =SUMIFS(E2:E27,A2:A27,"Tobacco-associated cancers - composition",B2:B27,"Female") -> 100
A31: Source: Maharashtra Fact Sheet 2021, section I.B (leading cancer sites) and the tobacco-use donut charts. Composition percentages are printed as whole numbers. Stage-at-diagnosis charts for Maharashtra are in sheet Clinical Stage.

Sheet MH Projections
A1: Year | B1: Males (projected cases) | C1: Females (projected cases) | D1: Total (M+F) | E1: Female share | F1: India total (NCRP projection) | G1: Maharashtra share of India
A2: 2020 | B2: 54961 | C2: 61160 | D2: =B2+C2 -> 116121 | E2: =C2/D2 -> 0.52669199 | F2: ='India Trend 2015-2025'!D18 -> 1392179 | G2: =D2/F2 -> 0.083409533
A3: 2025 | B3: 61703 | C3: 68762 | D3: =B3+C3 -> 130465 | E3: =C3/D3 -> 0.52705323 | F3: ='India Trend 2015-2025'!E18 -> 1569793 | G3: =D3/F3 -> 0.083109684
A4: Change 2020 to 2025 | B4: =B3/B2-1 -> 0.1226688 | C4: =C3/C2-1 -> 0.12429693 | D4: =D3/D2-1 -> 0.12352632 | F4: =F3/F2-1 -> 0.12757986
A5: CAGR 2020-2025 | B5: =(B3/B2)^(1/5)-1 -> 0.02341159 | C5: =(C3/C2)^(1/5)-1 -> 0.023708253 | D5: =(D3/D2)^(1/5)-1 -> 0.023567883 | F5: =(F3/F2)^(1/5)-1 -> 0.024305399
A7: Source: Maharashtra Fact Sheet 2021, section I.D - projected incidence of cancer cases using 2012-2016 incidence data as reference. The fact sheet also plots estimated age-specific incidence rates (all sites, 2020) for males and females; that chart carries no printed values, so it is described in Key Findings rather than tabulated. It shows rates near 0-10 per 100,000 below age 30 and rising steeply after 40; female rates exceed male rates between roughly age 35 and 65, and male rates overtake female rates after about age 65 (75+: roughly 630 male vs 450 female per 100,000, read off the chart).

Sheet MH Socio-Health Profile
A1: Section | B1: Indicator | C1: Male | D1: Female | E1: Total / overall | F1: Unit | G1: Source in fact sheet
A2: A. Socio-demographic | B2: Population (Census 2011) | C2: 58243056 | D2: 54131277 | E2: 112374333 | F2: persons | G2: Census 2011 [4]
A3: A. Socio-demographic | B3: Gender ratio | E3: 929 | F3: females per 1,000 males | G3: Census 2011 [4]
A4: A. Socio-demographic | B4: Literacy rate | C4: 88.4 | D4: 75.9 | E4: 82.3 | F4: % | G4: Census 2011 [4]
A5: B. Health indicators | B5: Life expectancy (2016) | C5: 65.3 | D5: 69.3 | F5: years | G5: India State-Level Disease Burden Initiative [5]
A6: B. Health indicators | B6: Proportion of total disease burden from NCDs | E6: 63.1 | F6: % | G6: ISLDBI [5]
A7: B. Health indicators | B7: Neoplasms as share of NCDs' medically certified deaths | E7: 9.7 | F7: % | G7: ORGI MCCD 2018 [6]
A8: B(d). Cancer-related risk factors | B8: Current tobacco use (smoking and/or smokeless), adults over 15 years | C8: 35.5 | D8: 17 | E8: 26.6 | F8: % | G8: GATS-2 2016-17 [7]
A9: B(d). Cancer-related risk factors | B9: Alcohol use, age 15-49 years | C9: 13.9 | D9: 0.4 | F9: % | G9: NFHS-5 2019-20 [8]
A10: B(d). Cancer-related risk factors | B10: Dark green leafy vegetables at least once a week, age 15-49 | C10: 89.9 | D10: 89.5 | F10: % | G10: NFHS-5 [8]
A11: B(d). Cancer-related risk factors | B11: Fruits at least once a week, age 15-49 | C11: 52.6 | D11: 55.4 | F11: % | G11: NFHS-5 [8]
A12: B(d). Cancer-related risk factors | B12: Households using clean fuel for cooking | E12: 79.7 | F12: % | G12: NFHS-5 [8]
A13: B(d). Cancer-related risk factors | B13: Households reporting exposure to second-hand smoke | E13: 26.6 | F13: % | G13: NFHS-5 [8]
A14: B(d). Cancer-related risk factors | B14: Overweight / obesity, age 15-49 | C14: 24.7 | D14: 23.4 | F14: % | G14: NFHS-5 [8]
A15: B(e). Other NCDs | B15: Hypertension, age 15-49 | C15: 24.4 | D15: 23.1 | F15: % | G15: NFHS-5 [8]
A16: B(e). Other NCDs | B16: Raised random blood glucose level, age 15-49 | C16: 13.6 | D16: 12.4 | F16: % | G16: NFHS-5 [8]
A17: Check | B17: Gender ratio recomputed (females per 1,000 males) from population row | E17: =D2/C2*1000 -> 929.4031
A19: Source: Maharashtra Fact Sheet 2021, section II (cancer-related information). Blank = not reported for that group. Numbers in square brackets are the fact-sheet reference numbers (see Source References).

Sheet MH Health Infrastructure
A1: Category | B1: Item | C1: Count / detail | D1: Classification / note | E1: Source in fact sheet
A2: Government health facilities | B2: Sub-centres + Health and Wellness Centres - Sub Centres (HWC-SCs) | C2: 10668 | E2: NFHS-4 / Rural Health Statistics [9]
A3: Government health facilities | B3: Primary Health Centres + Health and Wellness Centres - Primary Health Centres (HWC-PHCs) | C3: 2366 | E3: [9]
A4: Government health facilities | B4: Community Health Centres | C4: 401 | E4: [9]
A5: Government health facilities | B5: District hospitals | C5: 23 | E5: [9]
A6: Medical education | B6: Number of medical colleges | C6: 57 | E6: Rural Health Statistics 2018-19 [10]
A7: Regional / tertiary cancer care centres | B7: Tata Memorial Hospital, Mumbai | C7: RCC | D7: RCC = Regional Cancer Centre | E7: NMC / PIB [11],[12]
A8: Regional / tertiary cancer care centres | B8: Rashtrasant Tukdoji Regional Cancer Hospital & Research Centre, Nagpur | C8: RCC / TCCC | D8: RCC = Regional Cancer Centre; TCCC = Tertiary Cancer Care Centre | E8: [11],[12]
A9: Regional / tertiary cancer care centres | B9: Government Medical College, Aurangabad | C9: SCI | D9: SCI = State Cancer Institute | E9: [11],[12]
A10: Regional / tertiary cancer care centres | B10: Vivekanand Foundation & Research Centre, Latur | C10: TCCC | D10: TCCC = Tertiary Cancer Care Centre | E10: [11],[12]
A11: State government health schemes | B11: Integrated Mahatma Jyotiba Phule Jan Arogya Yojana (MJPJAY) and Ayushman Bharat-Pradhan Matri Jan Arogya Yojana (AB-PMJAY) | C11: Covers medical oncology, paediatric cancer, radiation and surgical oncology | E11: National Cancer Control Programme [13]
A12: Hospital-based cancer registries | B12: Kokilaben Dhirubhai Ambani Hospital and Research Institute, Mumbai | C12: HBCR | D12: 5 hospitals in total | E12: Fact sheet I.A
A13: Hospital-based cancer registries | B13: Kolhapur Cancer Centre, Kolhapur | C13: HBCR | E13: Fact sheet I.A
A14: Hospital-based cancer registries | B14: Pravara Institute of Medical Science, Loni | C14: HBCR | E14: Fact sheet I.A
A15: Hospital-based cancer registries | B15: Rashtra Sant Tukdoji Regional Cancer Hospital and Research Centre, Nagpur | C15: HBCR | E15: Fact sheet I.A
A16: Hospital-based cancer registries | B16: Tata Memorial Hospital, Mumbai | C16: HBCR | E16: Fact sheet I.A

Sheet Data Notes
A1: # | B1: Topic | C1: Note
A2: 1 | B2: Existing state data are NCRP estimates | C2: Sums of the state columns for 2020 and 2022 equal the national NCRP estimates (1,392,179 and 1,461,427), and Maharashtra 2020 equals the NCRP Maharashtra projection. The "Observed" labels in the existing State-wise Incidence sheet are therefore best read as "NCRP-estimated". The 2026/2030/2045 columns come from the Kumar et al. 2026 model.
A3: 2 | B3: Estimates assume constant incidence rates | C3: Both NCRP papers apply 2012-2016 age-specific rates unchanged to later populations, so projected growth reflects population growth and ageing only. The Kumar model instead extrapolates a 2019-2022 trend with healthcare moderators, hence different growth paths (e.g. 2026 sum of states 1.60 million vs IJMR 2025 projection 1.57 million).
A4: 3 | B4: Registry coverage is partial | C4: PBCRs cover about 10% of India's population (NCRP coverage 16.4%); several populous states (e.g. Uttar Pradesh, Bihar) have no registry and use pooled "rest of India" rates (see column J of State-wise Incidence).
A5: 4 | B5: Figure-derived values | C5: Values read from graphics rather than printed tables: JCO Fig. 2 (tobacco shares and rates), JCO Fig. 3 (stage), JCO Fig. 4 (APC), the Maharashtra childhood-cancer map and stage charts, and the IJMR population pyramids. Labels and values were paired from the page images and cross-checked against figures quoted in the paper text (see Cross-Validation).
A6: 5 | B6: Inferred series assignments | C6: JCO Fig. 3 (national stage): series were assigned using percentages quoted in the text (e.g. breast loco-regional 57.0%; lung distant 44.0%/47.6%; stomach localised < one fifth). IJMR population pyramids: first block = 2022, second = 2011, inferred from the 8.6% to 9.7% change in the 60+ share.
A7: 6 | B7: Rate-pair order in JCO Fig. 2 | C7: The figure prints (crude, age-adjusted) on the male side and (age-adjusted, crude) on the female side. They are normalised in the workbook and verified by recomputing the printed shares.
A8: 7 | B8: Source discrepancy: childhood leukaemia | C8: IJMR abstract gives lymphoid leukaemia as 29.2% (boys) and 24.2% (girls); Table II and the results text give 29.3% and 24.3%. Table II values are used.
A9: 8 | B9: Registry names harmonised | C9: Names are aligned across sheets: "Thi'puram" is shown as Thiruvananthapuram; "Barshi rural" as Barshi Rural; Osmanabad and Beed as one registry. District rows (Imphal West, Aizawl, Papumpare, East Khasi Hills) are sub-registry rows of Manipur, Mizoram, West Arunachal and Meghalaya and should not be added to their parent registries.
A10: 9 | B10: Reference periods differ by registry | C10: JCO Table 1 pools 2012-2016, but some registries have shorter periods (e.g. Delhi 2012-14; Hyderabad 2014-16; Kolkata, Mumbai, Bhopal, Osmanabad and Beed 2012-15). The period is shown in column E of PBCR Incidence Table.
A11: 10 | B11: Sex-specific sites | C11: Cells are blank (not zero) where a site does not apply to a sex (e.g. prostate in females). Breast cancer in males is a real (small) entry: 5,649 cases in 2022.
A12: 11 | B12: Cumulative risk storage | C12: Cumulative risk is printed as "1 in N"; the workbook stores N as a number so it can be sorted and filtered. Smaller N means higher risk.
A13: 12 | B13: Maharashtra childhood data | C13: Mumbai boys 0-14 AAR (107.1) is partly overlapped by the map outline in the PDF. Barshi rural has only 4 boys and 4 girls per year, so its rates are unstable.
... A16: 15 | B16: Page references | C16: Page numbers in Key Findings are the printed journal page numbers (IJMR 598-607; JCO 1063-1075) or fact-sheet page numbers.

Sheet Article Details
A1: Field | B1: Extracted data
A2: Article title | B2: State-wise forecasting of cancer incidence in India using a moderated exponential regression model incorporating healthcare system determinants
A3: Authors | B3: Dileep Kumar; Navin Upadhyay; Himanshu Pandey
A4: Journal | B4: International Journal of Community Medicine and Public Health
A5: Citation | B5: Kumar D, Upadhyay N, Pandey H. Int J Community Med Public Health. 2026;13(4):1867-1873.
A6: Publication details | B6: April 2026; Volume 13; Issue 4; pages 1867–1873
A7: DOI | B7: https://dx.doi.org/10.18203/2394-6040.ijcmph20261025
A8: Article type | B8: Original Research Article
A9: Department / affiliation 1 | B9: Department of Obstetrics and Gynecology, BRD Medical College, Gorakhpur, Uttar Pradesh, India
A10: Department / affiliation 2 | B10: Department of Mathematics and Statistics, Deen Dayal Upadhyaya Gorakhpur University, Gorakhpur, Uttar Pradesh, India
A11: Received | B11: 11 December 2025
A12: Revised | B12: 17 March 2026
... A21: Source data | B21: National Cancer Registry Programme (ICMR-NCRP), cancer incidence data for 2019–2022

Sheet Summary & Findings
A1: Section | B1: Extracted content
A2: Background | B2: Cancer incidence varies substantially across Indian states and union territories. Accurate projections support health planning, resource allocation, and stronger health systems. Conventional forecasts often rely on historical trends and may ignore regional differences in healthcare capacity that affect detection and reporting.
A3: Aim / objective | B3: Forecast state-wise cancer incidence in India using a moderated exponential regression model that combines historical incidence trends with healthcare-system indicators.
A4: Methods overview | B4: A moderated exponential regression model was developed using ICMR-NCRP state-wise incidence data from 2019–2022. Seven healthcare moderators were considered: cancer hospitals, oncologist availability, screening coverage/early detection, CHC/PHC density, health infrastructure index, per-capita health expenditure, and hospital beds per 1,000 population.
A5: Short-term scenario | B5: 2026; time value t=7; moderator D only (CHC/PHC density).
A6: Medium-term scenario | B6: 2030; time value t=11; moderators A–D: hospital infrastructure, oncology workforce, screening efficiency, and primary-care accessibility.
A7: Long-term scenario | B7: 2045; time value t=26; all seven moderators A–G, covering diagnostic capacity, treatment availability, healthcare financing, and long-range infrastructure expansion.
A8: Results | B8: The paper reports substantial inter-state variation. Stronger health systems were associated with slower increases in the moderated projections, while weaker infrastructure was associated with more rapid growth. The authors report improved model fit and predictive accuracy compared with conventional exponential models.
A9: Conclusion | B9: Including healthcare-system factors can improve the relevance of cancer-incidence projections for policy planning and targeted health-system strengthening.
A10: Main interpretation | B10: The paper argues that healthcare infrastructure, workforce, screening, and expenditure affect observed incidence through detection/reporting as well as prevention and treatment.
A11: Reported broad trend | B11: Most regions showed annual growth of approximately 1.5%–3.5% over the 2019–2022 period, according to the article.
A12: High-burden states highlighted | B12: Uttar Pradesh, Maharashtra, West Bengal, Tamil Nadu, Karnataka, and Rajasthan.
... A22: Policy implications | B22: Strengthen early detection, diagnostic capacity, oncology workforce, screening, tertiary care, timely referral, treatment capacity, and equitable distribution of health infrastructure.

Sheet Healthcare Moderators
A1: Code | B1: Healthcare moderator | C1: Description / wording in article
A2: A | B2: Cancer hospitals | C2: Number of cancer hospitals / hospital infrastructure
A3: B | B3: Oncologists | C3: Availability or number of oncologists / oncology workforce
A4: C | B4: Screening / early detection | C4: Early detection system and screening efficiency/coverage
A5: D | B5: CHC/PHC density | C5: Primary healthcare access; community health centre / primary health centre density
A6: E | B6: Health infrastructure index | C6: Overall health infrastructure strength
A7: F | B7: Per-capita health expenditure | C7: Financial strength of the health system / health expenditure per capita
A8: G | B8: Hospital beds | C8: Hospital-bed availability; hospital beds per 1,000 population

Sheet Model & Forecasts
A1: Item | B1: Formula / explanation
A2: Moderated exponential regression | B2: ln(y_it) = α + β1 t + Σ_k [β2k X_ik + β3k (t X_ik)] + ε_it. The equation is transcribed in normalized text form from the PDF; the printed equation formatting is imperfect.
A3: Short-term 2026 | B3: ln(ŷ) = α + β1 t + β2 D + β3 (tD); t=7; D = CHC/PHC density.
A4: Medium-term 2030 | B4: t=11; moderators A, B, C, D.
A5: Long-term 2045 | B5: t=26; moderators A, B, C, D, E, F, G.
A6: Back-transformation | B6: ŷ = e^(ln ŷ), converting predictions from log scale back to incidence units.
A7: Estimation method | B7: Ordinary least squares (OLS) regression.
A8: Robust inference | B8: HC3 robust standard errors to address potential heteroscedasticity.
A9: Predictor preprocessing | B9: All predictor variables standardized before estimation.
A10: Model design note | B10: The methods describe variables as collected (or designed to be collected) for each state/UT. The workbook preserves this wording rather than assuming all moderator measurements were directly observed.

Sheet References
A1: No. | B1: Reference (transcribed from article)
A2: 1 | B2: Carmer SG. Computational aspects of exponential regression. Commun Stat Theory Methods. 1974;3(3):229-45.
A3: 2 | B3: Breslow NE, Day NE, Heseltine E. Statistical methods in cancer research: Volume I—the analysis of case-control studies. IARC Scientific Publications No. 32. International Agency for Research on Cancer. 1980.
A4: 3 | B4: Lee ET, Wang J. Statistical methods for survival data analysis. 3rd ed. Wiley; 2003.
A5: 4 | B5: Abedi H, Sadeghi M, Boroumand MA, Nezami N. Application of survival models in oncology research: a comparative study. Cancer Epidemiol. 2019;60:80-7.
A6: 5 | B6: Chhatwal J, Alagoz O, Burnside ES. Logistic regression and decision-analytic modelling of breast cancer diagnosis. Med Decision Making. 2009;29(4):414-26.
A7: 6 | B7: Falgreen S, Dybkær K, Young KH, Xu-Monette ZY, El-Galaly TC, Laursen MB, et al. Predicting response to multidrug regimens in cancer patients using cell line experiments and regularised regression models. BMC Cancer. 2015 Apr 8;15:235.
A8: 7 | B8: Prataviera F, Rotnitzky A, Robins J. Exponentiated regression models for epidemiological applications. Biom J. 2019;61(2):302-20.
A9: 8 | B9: Ramires TG, Ortega EMM, Cordeiro GM. Power exponential regression models: Properties and applications. Commun Stat Theory Methods. 2018;47(6):1344-62.
A10: 9 | B10: Tanaka H, Ishibuchi H, Yoshikawa M. Exponential possibility regression and its applications. Fuzzy Sets Syst. 1995;69(1):51-60.
A11: 10 | B11: Suleiman M, Ahmed Z, Rahman A. Simulation-assisted nonlinear models for cancer data forecasting. Stat Modell. 2025;25(1):90-112.
A12: 11 | B12: Abaoud AA, Almuqrin A. Heavy-tailed regression models for biomedical data: simulation-driven evaluation and applications. J Appl Stat. 2024;51(3):512-30.
A13: 12 | B13: Almuqrin A. Simulation-based nonlinear regression methods for medical prediction models. Commun Stat Simulat Comput. 2024;53(1):145-62.

Sheet Source References
A1: Source paper | B1: Ref no. | C1: Reference (as printed in the source)
A2: IJMR 2022 (Sathishkumar) | B2: 1 | C2: Sung H, Ferlay J, Siegel RL, Laversanne M, Soerjomataram I, Jemal A, et al. Global cancer statistics 2020: GLOBOCAN estimates of incidence and mortality worldwide for 36 cancers in 185 countries. CA Cancer J Clin 2021; 71 : 209-49.
A3: IJMR 2022 (Sathishkumar) | B3: 2 | C3: Ferlay J, Ervik M, Lam F, Colombet M, Mery L, Piñeros M, et al. Global cancer observatory: Cancer today. Lyon, France: International Agency for Research on Cancer; 2020. Available from: https://gco.iarc.fr/today, accessed on August 5, 2022.
A4: IJMR 2022 (Sathishkumar) | B4: 3 | C4: Siegel RL, Miller KD, Fuchs HE, Jemal A. Cancer statistics, 2022. CA Cancer J Clin 2022; 72 : 7-33.
A5: IJMR 2022 (Sathishkumar) | B5: 4 | C5: Bray F, Colombet M, Mery L, Piñeros M, Znaor A, Zanetti R, et al., editors. Cancer incidence in five continents volume XI. Lyon: International Agency for Research on Cancer Scientific Publications; 2017.
A6: IJMR 2022 (Sathishkumar) | B6: 5 | C6: Mathur P, Sathishkumar K, Chaturvedi M, Das P, Sudarshan KL, Santhappan S, et al. Cancer statistics, 2020: Report from National Cancer Registry Programme, India. JCO Glob Oncol 2020; 6 : 1063-75.
A7: IJMR 2022 (Sathishkumar) | B7: 6 | C7: Bray F, Parkin DM. Evaluation of data quality in the cancer registry: Principles and methods. Part I: Comparability, validity and timeliness. Eur J Cancer 2009; 45 : 747-55.
A8: IJMR 2022 (Sathishkumar) | B8: 7 | C8: Bray F, Ferlay J, Soerjomataram I, Siegel RL, Torre LA, Jemal A. Global cancer statistics 2018: GLOBOCAN estimates of incidence and mortality worldwide for 36 cancers in 185 countries. CA Cancer J Clin 2018; 68 : 394-424.
A9: IJMR 2022 (Sathishkumar) | B9: 8 | C9: ICMR-National Centre for Disease Informatics and Research (NCDIR). Report of National Cancer Registry Programme 2020. Bengaluru (India). Available from: https://ncdirindia.org/All_Reports/PBCR_Annexures/Default.aspx, accessed on June 20, 2022.
A10: IJMR 2022 (Sathishkumar) | B10: 9 | C10: World Health Organization (WHO). International statistical classification of diseases and related health problems. Geneva (Switzerland): WHO; 1994.
A11: IJMR 2022 (Sathishkumar) | B11: 10 | C11: Office of the Registrar General & Census Commissioner, India. Population Census 2011. Table C-14: Population in Five-Year Age Group by Residence and Sex. New Delhi (India); 2011. Available from: http://www.censusindia.gov.in, accessed on May 20, 2022.
A12: IJMR 2022 (Sathishkumar) | B12: 11 | C12: Segi M. Cancer mortality for selected sites in 24 countries (1950-1957). Sendai, Japan: The Department of Public Health, Tohoku University School of Medicine; 1960.
A13: IJMR 2022 (Sathishkumar) | B13: 12 | C13: Swaminathan R, Shanta V on Behalf of the TNCRP Study Group. Cancer Incidence and Mortality (Year 2016), Incidence Trend (2012-2016) and Estimates (2017-2020) for Tamil Nadu State. Tamil Nadu Cancer Registry Project, Chennai (India): Cancer Institute (W.I.A.); 2020.
... A93: Maharashtra Fact Sheet 2021 | B93: 14 | C93: Government of Maharashtra, Mahatma Jyotiba Phule Jan Arogya Yojana (MJPJAY) (www.jeevandayee.gov.in)
A95: The JCO paper numbers its references 1-47 and also lists "8a" (hospital-based registry reports) beside reference 8; here 8a is merged into reference 8 so the sheet holds 46 rows for JCO. Reference list of the Kumar et al. 2026 article is in sheet References.

Sheet Full PDF Text
A1: Source document | B1: PDF page | C1: Extracted text
A2: S4 - Kumar et al. 2026, IJCMPH (existing) | B2: 1 | C2: International Journal of Community Medicine and Public Health Kumar D et al. Int J Community Med Public Health. 2026 Apr;13(4):1867-1873 http://www.ijcmph.com pISSN 2394-6032 | eISSN 2394-6040 DOI: https://dx.doi.org/10.18203/2394-6040.ijcmph20261025 Original Research Article State-wise forecasting of cancer incidence in India using a moderated exponential regression model incorporating healthcare system determinants Dileep Kumar1, Navin Upadhyay2*, Himanshu Pandey2 1Department of Obstetrics and Gynecology BRD Medical College Gorakhpur, Uttar Pradesh, India 2Department of Mathematics and Statistics, Deen Dayal Upadhyaya Gorakhpur University, Gorakhpur, Uttar Pradesh, India Received: 11 December 2025 Revised: 17 March 2026 Accepted: 20 March 2026 *Correspondence: Navin Upadhyay, E-mail: navinupadhyayrs@gmail.com Copyright: © the author(s), publisher and licensee Medip Academy. This is an open-access article distributed under the terms of the Creative Commons Attribution Non-Commercial License, which permits unrestricted non-commercial use, distribution, and reproduction in any medium, provided the original work is properly cited. ABSTRACT Background: Cancer incidence in India varies substantially across states and union territories, posing a significant and growing public health challenge. Accurate projections of future cancer burden are essential for effective health planning, resource allocation, and strengthening health systems. However, conventional forecasting approaches largely rely on historical incidence trends and often ignore regional differences in health-care capacity, which influence disease detection and reporting. Variations in infrastructure, oncology services, screening coverage, and health expenditure can significantly affect observed cancer incidence. This study proposed a moderated forecasting framework that integrates key state-level health-care indicators to generate more realistic and policy-relevant projections. Methods: A moderated exponential regression model was developed using state-wise cancer incidence data from the National Cancer Registry Programme (ICMR-NCRP) for 2019-2022. The model incorporated multiple health system moderators, including cancer hospitals, oncologist availability, screening coverage, CHC/PHC density, health infrastructure index, per-capita health expenditure, and hospital-bed availability. Three projection scenarios were constructed: short-term (2026) using health-care facility density, medium-term (2030) incorporating infrastructure and workforce variables, and long-term (2045) including all seven moderators. Results: The moderated models revealed substantial inter-state variation in projected cancer incidence. States with stronger health systems exhibited slower increases, whereas those with weaker infrastructure showed more rapid growth. Model fit and predictive accuracy improved significantly compared to conventional exponential models. Conclusions: Incorporating health-care system factors enhances the reliability of cancer incidence projections. The proposed framework offers a robust, evidence-based tool for policy planning and targeted health system strengthening in India. Keywords: Cancer, Moderated exponential, Regression INTRODUCTION Programme (NCRP) of the Indian Council of Medical Research (ICMR), the country has witnessed a steady rise Cancer has emerged as one of the leading public health in cancer incidence over the past decade, with increasing challenges in India, contributing significantly to variation across states and union territories. These morbidity, mortality, and long-term health-system geographical disparities reflect not only differences in burden. According to the National Cancer Registry demographic and lifestyle factors but also the unequal International Journal of Community Medicine and Public Health | April 2026 | Vol 13 | Issue 4 Page 1867
A3: S4 - Kumar et al. 2026, IJCMPH (existing) | B3: 2 | C3: Kumar D et al. Int J Community Med Public Health. 2026 Apr;13(4):1867-1873 distribution of health-care resources such as cancer a strategic foundation for long-term cancer control hospitals, oncology specialists, diagnostic services, and planning in India. screening programmes. As India moves toward achieving universal health coverage, the ability to accurately Existing literature provides a strong methodological forecast the future trajectory of cancer burden- while foundation for developing advanced regression-based accounting for health-system heterogeneity- has become forecasting models for cancer incidence. Early studies essential for guiding evidence-based planning and examined computational techniques for exponential investment decisions. regression and emphasized numerical stability and accuracy- issues that are particularly important when Traditional forecasting approaches often rely solely on working with short time series such as India’s 2019-2022 historical incidence trends, assuming uniform growth state-wise cancer incidence data.1 across regions. However, cancer progression and detection are strongly influenced by health-care system In cancer epidemiology, classical statistical work capacity, including screening coverage, primary care established core principles for analyzing cancer rates and access, diagnostic infrastructure, and the availability of highlighted the need for appropriate adjustments for specialized oncology services. States with stronger health population structure and registry completeness.2 infrastructure may detect cancer earlier or manage risk Extensions of exponential modeling, such as exponential factors better, resulting in slower observed growth rates. possibility regression, further expanded regression Conversely, states with weak health-care systems frameworks to accommodate uncertainty and imprecise frequently exhibit delayed diagnosis and under-reporting, data, which is particularly relevant when dealing with followed by rapid increases in incidence as detection variability in Indian health-system indicators.3 improves. These differences necessitate a prediction model that incorporates health-care system moderators Applied research in survival analysis has emphasized the rather than depending on time trends alone. importance of selecting appropriate statistical models for oncological data.3,4 Additionally, logistic regression and To address this gap, the present study proposes a regularized regression methods have been widely used in moderated exponential regression framework for cancer diagnostics, demonstrating that incorporating forecasting state-wise cancer incidence in India. Unlike interaction terms and health-related predictors can simple exponential models that assume uniform growth, significantly improve predictive performance.5,6 this approach integrates multiple health-care moderators- such as the number of cancer hospitals, number of Further methodological developments, including oncologists, screening coverage, CHC/PHC density, exponentiated exponential regression and power health infrastructure index, health expenditure, and exponential regression models, have extended the hospital-bed availability- to estimate how these factors applicability of exponential-type models in medical data shape the rate of cancer incidence growth over time. analysis.7-9 More recent approaches based on heavy-tailed Interaction terms between time and each moderator allow distributions and simulation-based modeling frameworks the model to quantify how improvements in health-care highlight the need for flexible nonlinear structures systems can dampen or accelerate cancer growth capable of capturing complex patterns in biomedical trajectories. data.10-12 Using state-wise incidence data from NCRP (2019-2022), Together, these studies suggest that cancer incidence the study develops three moderator-specific forecasting forecasting should incorporate both exponential growth models: a short-term model for 2026 using CHC/PHC dynamics and health-system determinants to better density; a medium-term model for 2030 using four capture real-world heterogeneity across populations. moderators (A-D); and a long-term model for 2045 using However, previous research has rarely integrated multiple the complete set of seven moderators (A-G). This health-care moderators within an exponential forecasting progressive modelling structure reflects the increasing framework for state-level prediction. Therefore, the importance of comprehensive health-care capacity over present study addressed this gap by developing a longer time horizons. moderated exponential regression model that incorporates health infrastructure, workforce availability, screening The introduction of moderated exponential regression coverage, and health expenditure indicators to generate into cancer forecasting contributes to the literature in two short-, medium-, and long-term forecasts of cancer important ways. First, it captures structural disparities in incidence for Indian states and union territories. health-care delivery that drive state-wise differences in cancer incidence growth. Second, it provides policy- The present research focused on forecasting the future makers with a dynamic tool capable of linking health-care burden of cancer across Indian states and union territories investments to future cancer trends. By quantifying how by developing a moderated exponential regression model improvements in screening, infrastructure, and oncology that integrates both historical incidence trends and health- services influence incidence projections, the model offers care system indicators. Using state-wise cancer incidence data reported by the National Cancer Registry Programme International Journal of Community Medicine and Public Health | April 2026 | Vol 13 | Issue 4 Page 1868
A4: S4 - Kumar et al. 2026, IJCMPH (existing) | B4: 3 | C4: Kumar D et al. Int J Community Med Public Health. 2026 Apr;13(4):1867-1873 (ICMR-NCRP) for the years 2019 to 2022, the study first patterns in cancer incidence, a log transformation was establishes the baseline exponential growth pattern in applied to the outcome variable. The raw dependent cancer cases, assuming that incidence increases variable, denoted as y, represents the annual cancer multiplicatively over time. However, because cancer incidence for each state. For regression analysis, this detection and reporting are strongly influenced by the value was transformed using the natural logarithm, strength of health-care systems, the growth rate is not producing ln(y) as the dependent variable in the model. uniform across states. To address this variability, the This transformation is essential because exponential study incorporated a set of health-care moderators- models perform optimally when the response variable is including the number of cancer hospitals, availability of expressed on a logarithmic scale. Log transformation not oncologists, screening coverage, CHC/PHC density, only stabilizes the variance and reduces skewness in the health infrastructure index, health expenditure per capita, data but also converts an inherently exponential and hospital-bed availability. These moderators capture relationship into a linear form, thereby improving model essential features of diagnostic capacity, treatment fit, interpretability, and the validity of regression readiness, screening efficiency, and overall health-system assumptions. strength. The moderated exponential regression model is defined METHODS as: In order to forecast cancer incidence by state throughout India, this study uses a moderated exponential regression ln(𝑦 𝑖𝑡 )=𝛼+𝛽 1 +∑[𝛽 2𝑘 +𝑋 𝑖𝑘 +𝛽 3𝑘 (𝑡𝑋 𝑖𝑘 )]+ℇ 𝑖𝑡 model within a quantitative analytical framework. In 𝑘 order to comprehend how infrastructure strength affects future cancer growth rates, the methodological approach Dependent variable- The natural log of cancer incidence combines historical cancer incidence data with important was modelled. Coefficients can be interpreted as health-care system indicators. The National Cancer proportional or percentage changes in cancer incidence. Registry Programme (NCRP) of the Indian Council of Medical Research (ICMR) provided state-specific annual Baseline trend- β 1 measures the overall, underlying cancer incidence counts for all cancer sites and both sexes annual growth rate (in percent) of cancer incidence across for the years 2019, 2020, 2021, and 2022. Together, these all states and groups. data form the baseline trend used to build the exponential prediction model. Seven health-care moderator variables Moderator (fixed effect)- β 2k measures the initial, baseline were included in the mode to take into consideration difference in the ln(incidence) for moderator group k possible structural variations in detection and reporting compared to the reference group at time t=0. capacity among states: i) number of cancer hospital; ii) number of oncologist; iii) early detection system; iv) Interaction term- this is the engine of the analysis. It primary health care access (CHC/PHC); v) health captures the unique effect of the moderator k over time. infrastructure index; vi) financial strength of health system; and vii) hospital beds per 1000 population. Moderation effect- this is the most crucial coefficient. It measures the change in the growth rate of cancer These variables were collected (or designed to be incidence for group k. A positive β means group k has 3k collected) for each state/UT. cancer incidence that is growing faster than the overall trend β . 1 In order to ensure that each state contributed four observations corresponding to the annual cancer Error term- represents all unexplained variation and incidence records for 2019, 2020, 2021, and 2022, the random factors influencing cancer incidence that are not dataset was first reorganized into a state-time panel captured by time or the moderators. format. By designating t=0 for 2019, t=1 for 2020, t=2 for 2021, and t=3 for 2022, a numerical time variable was Model interpretation created to effectively model temporal progression. This allowed the regression model to capture exponential 𝛽 - Baseline average exponential growth rate. This is the 1 growth patterns over time. Because exponential models overall, inherent annual percentage change in cancer require the dependent variable to be expressed in incidence y for the reference group. logarithmic form for optimal performance, the raw cancer incidence values (denoted as y) were transformed using 𝛽 - Direct effect of moderator on incidence. This 2𝑘 the natural logarithm, producing ln(y) as the dependent measures the initial proportional difference in cancer variable for analysis. This log transformation helps incidence y for moderator group k compared to the stabilize variance, improves normality, and converts an reference group at the start of the study t=0. exponential growth trend into a linear relationship, thereby enhancing model interpretability and fitting 𝛽 - How the moderator changes the growth rate. This is 3𝑘 accuracy. To appropriately model exponential growth the differential growth rate. It measures how much faster International Journal of Community Medicine and Public Health | April 2026 | Vol 13 | Issue 4 Page 1869
A5: S4 - Kumar et al. 2026, IJCMPH (existing) | B5: 4 | C5: Kumar D et al. Int J Community Med Public Health. 2026 Apr;13(4):1867-1873 or slower the rate of cancer incidence growth is for group standard errors (HC3) were applied, ensuring more k compared to the baseline rate 𝛽 . accurate inference even when variance assumptions were 1 violated. Each health-care moderator was entered into the Forecasting framework model along with its interaction term, allowing the analysis to capture how differences in state-level health Short-Term Forecast: 2026 infrastructure influence cancer growth rates over time. All predictor variables were standardized prior to estimation Time value: t=7 to place them on a comparable scale, facilitate model convergence, and enable meaningful interpretation of Moderator used: D only (CHC/PHC density) interaction effects. Following model estimation, the predicted values- initially generated on the log scale- ln(ŷ)=α+β +β +β (tD) were exponentiated to convert them back into their 1t 2D 3 original cancer incidence units, making the results directly interpretable for policy and public health Medium-term forecast: 2030 applications. The log-predicted values were converted back: Time value: t=11 𝑦̂ =𝑒𝑙𝑛𝑦̂ Moderators used: A, B, C, D The model produced state-wise forecasts of cancer Model includes hospital infrastructure, oncology incidence for three future time periods based on workforce, screening efficiency, primary-care increasing levels of health-care moderation. Short-term accessibility. projections for 2026 were generated using health-care center density (D) as the sole moderator, while medium- Long-term forecast: 2045 term forecasts for 2030 incorporated four moderators (A- D) to capture broader variation in diagnostic and Time value: t=26 infrastructural capacity. Long-term projections for 2045 utilized all seven moderators (A-G), enabling a Moderators used: A, B, C, D, E, F, G comprehensive assessment of how health-system strength influences the exponential growth rate of cancer This comprehensive model captures: diagnostic capacity, incidence across states. For each of the three moderated treatment availability, health-system financing, long- exponential regression models, detailed model summaries range infrastructure expansion. were generated, followed by interpretation tables that quantified the individual and combined impact of the Model estimation moderators on predicted incidence levels. These outputs collectively provide an integrated understanding of how The model was estimated using ordinary least squares health-care infrastructure, workforce availability, and (OLS) regression, incorporating several enhancements to system readiness shape the future burden of cancer in improve reliability and interpretability. To address India. potential heteroscedasticity in the panel data, robust Table 1: State-wise observed (2019-2022) and predicted (2026-2045) cancer incidence data for India. State/UT 2019 2020 2021 2022 Pred 2026 Pred 2030 Pred 2045 Jammu and Kashmir 12,396 12,726 13,060 13,395 14,857 16,475 24,277 Ladakh 279 286 294 302 336 373 556 Himachal Pradesh 8,589 8,799 8,978 9,164 9,992 10,887 15,021 Punjab 37,744 38,636 39,521 40,435 44,322 48,578 68,516 Chandigarh 994 1,024 1,053 1,088 1,225 1,381 2,162 Uttaranchal 11,216 11,482 11,779 12,065 13,305 14,671 21,170 Haryana 28,453 29,219 30,015 30,851 34,356 38,269 57,344 Delhi 24,436 25,178 25,969 26,735 30,163 34,017 53,405 Rajasthan 69,156 70,987 72,825 74,725 82,850 91,854 135,242 Uttar Pradesh 196,652 201,319 206,088 210,958 231,671 254,411 361,432 Bihar 101,014 103,711 106,435 109,274 121,330 134,721 199,495 Sikkim 443 445 465 496 570 664 1,180 Arunachal Pradesh 1,015 1,035 1,064 1,087 1,194 1,310 1,859 Nagaland 1,719 1,768 1,805 1,854 2,046 2,259 3,275 Manipur 1,844 1,899 2,022 2,097 2,512 3,006 5,889 Continued. International Journal of Community Medicine and Public Health | April 2026 | Vol 13 | Issue 4 Page 1870
A6: S4 - Kumar et al. 2026, IJCMPH (existing) | B6: 5 | C6: Kumar D et al. Int J Community Med Public Health. 2026 Apr;13(4):1867-1873 State/UT 2019 2020 2021 2022 Pred 2026 Pred 2030 Pred 2045 Mizoram 1,783 1,837 1,919 1,985 2,534 2,817 3,990 Tripura 2,507 2,574 2,623 2,715 2,936 3,187 4,554 Meghalaya 2,808 2,879 2,943 3,025 3,295 3,548 4,937 Assam 36,948 37,880 38,834 39,787 42,332 46,106 65,623 West Bengal 105,814 108,394 110,972 113,581 120,444 130,956 187,575 Jharkhand 33,045 33,961 34,910 35,860 38,798 43,330 64,198 Orissa 49,604 50,692 51,829 52,960 57,804 63,085 87,562 Chhattisgarh 27,113 27,828 28,529 29,253 32,371 35,816 52,330 Madhya Pradesh 75,911 77,888 79,871 81,901 90,634 100,286 146,572 Gujarat 67,841 69,660 71,507 73,382 81,492 90,485 133,987 Daman 118 124 135 150 204 282 943 Dadra and Nagar Haveli 186 206 219 238 328 452 1,504 Maharashtra 113,374 116,121 118,906 121,717 133,825 147,116 209,831 Telangana 46,464 47,620 48,775 49,983 55,083 60,706 87,401 Andhra Pradesh 68,883 70,424 71,970 73,536 80,241 87,546 121,375 Karnataka 83,824 85,968 88,126 90,349 99,844 110,330 160,451 Goa 1,591 1,618 1,652 1,700 1,850 2,020 2,808 Lakshadweep 27 27 28 28 30 32 39 Kerala 56,148 57,155 58,139 59,143 63,388 67,929 88,051 Tamil Nadu 86,596 88,866 91,184 93,536 103,676 114,902 168,953 Pondicherry 1,523 1,577 1,623 1,679 1,909 2,170 3,514 Andaman and Nicobar Islands 357 366 380 393 447 509 830 RESULTS the results underscore significant inter-state variation, with northern and eastern states exhibiting steeper Analysis of the NCRP cancer incidence data from 2019 to increases compared with southern and northeastern 2022 revealed a consistent upward trend across all Indian regions. The projections highlight the urgency for states and union territories, with most regions showing stronger cancer prevention, early detection, and health- annual growth ranging from 1.5% to 3.5%. High- system strengthening, particularly in high-burden states. population states such as Uttar Pradesh, Maharashtra, The results also justify the need for moderated West Bengal, Tamil Nadu, Karnataka, and Rajasthan exponential models incorporating health-care system contributed disproportionately to the national cancer determinants to generate more realistic and policy- burden, while smaller states and UTs like Ladakh, relevant forecasts. Sikkim, Daman, and Lakshadweep exhibited lower absolute case counts but still demonstrated steady increases. The exponential regression model fitted separately for each state indicated a strong linear pattern in the log-transformed data, confirming the suitability of an exponential growth assumption for short- and medium- term projections. Using this model, cancer incidence forecasts for 2026 show substantial increases in all states, with Uttar Pradesh reaching approximately 231,671 cases, followed by Maharashtra (133,825) and West Bengal (120,444). The 2030 projections further amplify these trends, with Uttar Pradesh rising to 254,411 cases, Maharashtra to 147,116, and Tamil Nadu and Karnataka surpassing 110,000 cases each. Long-term forecasting for 2045 revealed a dramatic escalation in cancer burden due to compounded exponential growth, with Uttar Pradesh projected to reach 361,432 cases, Maharashtra 209,831, West Bengal 187,575, and Tamil Nadu and Karnataka exceeding 160,000 cases each. Smaller northeastern states such as Figure 1: Heatmap showing the observed (2019–2022) Manipur, Nagaland, and Mizoram show high relative and predicted (2026–2045) cancer population across growth rates despite modest absolute numbers. Overall, Indian states using log₁₀-transformed values. International Journal of Community Medicine and Public Health | April 2026 | Vol 13 | Issue 4 Page 1871
A7: S4 - Kumar et al. 2026, IJCMPH (existing) | B7: 6 | C7: Kumar D et al. Int J Community Med Public Health. 2026 Apr;13(4):1867-1873 regression reveal a consistent and worrying upward trajectory across virtually all states and union territories. Short-term projections to 2026 and medium-term projections to 2030 indicate substantial absolute increases in case-loads concentrated in high-population states- most notably Uttar Pradesh, Maharashtra, West Bengal, Tamil Nadu, Karnataka, and Rajasthan- while long-term projections to 2045 show dramatic compounding of these differences. These patterns reflect both population size and differential capacity for early detection and reporting. The exponential model’s strong fit on log-transformed counts suggests that multiplicative growth captures the recent dynamics of recorded incidence for the 2019-2022 window; nevertheless, the pure exponential projections also underscore limitations when used alone because they do not explicitly account for health-system factors that alter detection rates or incidence through prevention and Figure 2: Observed cancer population (2019-2022) case finding. Incorporating health-care moderators is and model-predicted values (2026-2045) for all therefore critical for policy-relevant forecasting. The States/UTs, illustrating temporal trends and projected conceptual moderation strategy- introducing interaction increases across regions. terms between time and health-system indicators- permits the growth rate itself to vary by state characteristics. This approach recognizes, for example, that increases in screening coverage or specialist density may initially raise observed incidence (through better detection) but ultimately reduce later-stage incidence and mortality by enabling earlier treatment. Models that include CHC/PHC density, cancer hospitals, oncologist counts, screening coverage, health infrastructure index, health expenditure and hospital-bed availability can disentangle detection artifacts from genuine epidemiologic trends and provide more stable policy-sensitive forecasts. Interaction coefficients (time × moderator) are of particular interest: a negative interaction indicates that higher moderator levels are associated with slower growth, highlighting areas where strengthening the health system could dampen future burden. Regional heterogeneity in projections also carries programmatic implications. Northeastern states, despite smaller absolute numbers, show high relative growth rates- signaling either emerging detection gains or genuine epidemiologic shifts that warrant targeted surveillance and capacity building. High-burden large states require scale-up of tertiary care, human resources, and population-level screening to manage rising absolute numbers. The modeling exercise identifies both “quantity” challenges (volume of cases requiring treatment centers and beds) and “quality” challenges Figure 3: State-wise bar charts displaying observed (screening effectiveness, timely referral, oncology (2019–2022) and predicted (2026–2045) cancer workforce competence). Sensitivity analysis and population values for all Indian States/UTs. diagnostics suggest that while the log-linear exponential model is a reasonable starting point, model validation The figure highlights inter-state variation in historical should include checks for heteroskedasticity, cancer burden and projected future increases. overdispersion, and model misspecification; where these arise, alternatives such as exponentiated/power- DISCUSSION exponential families, negative-binomial or hierarchical models, and Bayesian frameworks should be considered. The analysis of state-wise cancer incidence in India Finally, the results stress the need for integrated policy (2019-2022) and its extrapolation via exponential responses. Forecasts must be interpreted alongside International Journal of Community Medicine and Public Health | April 2026 | Vol 13 | Issue 4 Page 1872
A8: S4 - Kumar et al. 2026, IJCMPH (existing) | B8: 7 | C8: Kumar D et al. Int J Community Med Public Health. 2026 Apr;13(4):1867-1873 demographic projections (aging populations), risk-factor exponential regression is an effective method for trends (tobacco, obesity, pollution), and improvements in predicting cancer trends and provides policymakers registry coverage. A moderated forecasting framework looking to improve cancer-control tactics and allocate links health-system investments to expected incidence resources effectively with useful information. trajectories and thus provides a pragmatic decision- support tool for allocating screening programs, workforce Funding: No funding sources development, and infrastructure expansion. Despite Conflict of interest: None declared providing a moderated framework for forecasting cancer Ethical approval: The study was approved by the incidence, this study has certain limitations. First, the Institutional Ethics Committee analysis relies on secondary data obtained from the National Cancer Registry Programme (ICMR-NCRP) for REFERENCES the period 2019-2022, which may not fully capture underreporting or regional variations in cancer 1. Carmer SG. Computational aspects of exponential registration coverage. Second, the forecasting model regression. Commun Stat Theory Methods. assumes that the moderating health-care indicators- such 1974;3(3):229-45. as health infrastructure, screening coverage, and oncology 2. Breslow NE, Day NE, Heseltine E. Statistical workforce- remain relatively stable over time, whereas in methods in cancer research: Volume I- the analysis reality these factors may change due to policy of case-control studies. IARC Scientific Publications interventions, technological advancements, or health No. 32. International Agency for Research on system reforms. Third, the model considers only selected Cancer. 1980. state-level health-care indicators and does not incorporate 3. Lee ET, Wang J. (2003). Statistical methods for other potentially important determinants such as lifestyle survival data analysis. 3rd edn. Wiley; 2003. risk factors, environmental exposure, demographic 4. Abedi H, Sadeghi M, Boroumand MA, Nezami N. transitions, and socioeconomic inequalities that may Application of survival models in oncology influence cancer incidence. Finally, the projections are research: a comparative study. Cancer Epidemiol. based on aggregated state-level data, which may mask 2019;60:80-7. intra-state disparities between urban and rural 5. Chhatwal J, Alagoz O, Burnside ES. Logistic populations. Therefore, while the proposed moderated regression and decision-analytic modelling of breast exponential regression model improves predictive cancer diagnosis. Med Decision Making. capability, the projections should be interpreted as 2009;29(4):414-26. indicative estimates rather than precise forecasts, and 6. Falgreen S, Dybkær K, Young KH, Xu-Monette ZY, future studies may benefit from incorporating longer El-Galaly TC, Laursen MB, et al. Predicting time-series data and additional epidemiological and response to multidrug regimens in cancer patients socioeconomic variables. using cell line experiments and regularised regression models. BMC Cancer. 2015 Apr CONCLUSION 8;15:235.. 7. Prataviera F, Rotnitzky A, Robins J. Exponentiated regression models for epidemiological applications. The current study showed that cancer incidence in India is Biometr J. 2019;61(2):302-20. rising steadily in almost every state and union territory, 8. Ramires TG, Ortega EMM, Cordeiro GM. Power with particularly significant increases predicted in high- exponential regression models: Properties and population areas like Uttar Pradesh, Maharashtra, West applications. Commun Stat Theory Methods. Bengal, Tamil Nadu, Karnataka, and Rajasthan. By using 2018;47(6):1344-62. an exponential regression framework to analyze NCRP 9. Tanaka H, Ishibuchi H, Yoshikawa M. Exponential data from 2019 to 2022, the research reveals that short- possibility regression and its applications. Fuzzy term and long-term cancer trends follow a clear Sets Syst. 1995;69(1):51-60. multiplicative growth pattern. However, the analysis also 10. Suleiman M, Ahmed Z, Rahman A. Simulation- reveals that relying only on historical incidence does not assisted nonlinear models for cancer data fully capture the underlying drivers of regional variation. forecasting. Stat Modell. 2025;25(1):90-112. These moderators contribute to the explanation of why 11. Abaoud AA, Almuqrin A. Heavy‐tailed regression some states see faster growth because of inadequate models for biomedical data: simulation‐driven screening or restricted access to treatment, while others evaluation and applications. J Appl Stat. exhibit slower growth because of more robust health 2024;51(3):512-30. systems. In order to reduce future cancer burdens, the 12. Almuqrin A. Simulation-based nonlinear regression results emphasize the significance of investing in early methods for medical prediction models. Commun detection, diagnostic capacity, oncology workforce Stat Simulat Comput. 2024;53(1):145-62. development, and equitable distribution of health infrastructure. Overall, the study shows that moderated Cite this article as: Kumar D, Upadhyay N, Pandey H. State-wise forecasting of cancer incidence in India using a moderated exponential regression model incorporating healthcare system determinants. Int J Community Med Public Health 2026;13:1867-73. International Journal of Community Medicine and Public Health | April 2026 | Vol 13 | Issue 4 Page 1873
A9: S1 - Sathishkumar et al. 2022, IJMR | B9: 1 | C9: Indian J Med Res 156, October & November 2022, pp 598-607 Quick Response Code: DOI: 10.4103/ijmr.ijmr_1821_22 Cancer incidence estimates for 2022 & projection for 2025: Result from National Cancer Registry Programme, India Krishnan Sathishkumar, Meesha Chaturvedi, Priyanka Das, S. Stephen & Prashant Mathur National Centre for Disease Informatics & Research, Indian Council of Medical Research, Bengaluru, Karnataka, India Received August 20, 2022 Background & objectives: Information on recent cancer statistics is important for planning, monitoring and evaluating cancer control activities. This article aims to provide an update on the cancer incidence estimates in India by sex, age groups and anatomical sites for the year 2022. Methods: The National Cancer Registry Programme Report 2020, reported the cancer incidence from 28 Population-Based Cancer Registries (PBCRs) for the years 2012-2016. This was used as the basis to calculate cancer estimates in India. Information pertaining to the population at risk was extracted from the Census of India (2001 and 2011) for the estimation of age–sex stratified population. PBCRs were categorised into the respective State and regions of the country to understand the epidemiology of cancer. The age-specific incidence rate for each specific anatomical site of cancer was applied to the estimated population to derive the number of cancer cases in India for 2022. Results: The estimated number of incident cases of cancer in India for the year 2022 was found to be 14,61,427 (crude rate:100.4 per 100,000). In India, one in nine people are likely to develop cancer in his/her lifetime. Lung and breast cancers were the leading sites of cancer in males and females, respectively. Among the childhood (0-14 yr) cancers, lymphoid leukaemia (boys: 29.2% and girls: 24.2%) was the leading site. The incidence of cancer cases is estimated to increase by 12.8 per cent in 2025 as compared to 2020. Interpretation & conclusions: The cancer incidence is continuing to increase in India. The new estimates will be helpful in planning cancer prevention and control activities through the intervention of early detection, risk reduction and management. Key words Cancer - estimates - incidence - India - National Cancer Registry Programme - projection According to the Global Cancer Observatory India would increase to 2.08 million, accounting for a (GLOBOCAN) estimates, there were 19.3 million rise of 57.5 per cent in 2040 from 20202. incident cancer cases worldwide for the year 20201. Planning, monitoring and evaluation of cancer India ranked third after China and the United States of control activities requires recent statistics in any region. America2. GLOBOCAN predicted that cancer cases in This is usually achieved through the Population-Based © 2022 Indian Journal of Medical Research, published by Wolters Kluwer - Medknow for Director-General, Indian Council of Medical Research 598
A10: S1 - Sathishkumar et al. 2022, IJMR | B10: 2 | C10: SATHISHKUMAR et al: CANCER INCIDENCE ESTIMATES FOR 2022 599 Cancer Registries (PBCRs). Cancer is not a nationally anatomical sites across the 28 PBCRs in India from notable disease in India. Thus, the data collection from the year 2012 to 20168. The anatomical sites follow PBCRs involves active retrospective data abstraction, the International Statistical Classification of Diseases laborious and a complex process of analysis and and Related Health Problems (ICD-10, 10th revision)9. reporting. Trained registry staff typically go to different The population at risk was extracted from the Census resource centers (hospitals, vital statistics departments of India, Registrar General and General Census and diagnostic laboratories) for collecting data on a Commissioner of India for the years 2001 and 2011 by standardized core form3. This delays the process of State/Union Territory (UT) and sex10. real-time reporting and bringing out the most recent cancer statistics. Globally, there is usually a lag of 2-4 yr Estimation of Cancer Incidence in India for 2022: between actual cancer registry data and the publication Crude incidence rate (CR) per 100,000 was calculated of results (e.g. US cancer registry, GLOBOCAN)3,4. by dividing the total number of cases by the total Thus, providing estimates at periodic intervals is the population. Age-specific incidence rate (ASIR) per best way for informing cancer prevention and control 100,000 was derived by dividing the number of cancer programmes. Hence, efforts to provide timely cancer cases by the total population in that particular age estimates based on the recently available data for group. Age-adjusted rate (AAR) was the weighted formulating appropriate cancer control measures are average of ASIR and world standard population11. In proposed5,6. the absence of any other competing cause of death, cumulative risk refers to the likelihood that a given In India, the systematic collection of data on individual will be diagnosed with cancer during his or cancer through the PBCRs and Hospital-Based Cancer her lifetime between the ages of 0 and 74 years. This Registries is in existence since 1981 under the National was expressed as ‘1 in how many’ are likely to develop Cancer Registry Programme (NCRP), National Centre cancer during their lifetime. for Disease Informatics and Research (NCDIR) of the Indian Council of Medical Research (ICMR-NCDIR), The PBCRs with a minimum three years’ data and Bengaluru. incidence rate, consistent with previous years, were One of the primary objectives of NCRP is to included for estimation. The coverage of PBCRs is generate reliable data on the magnitude and patterns varied across India, with full/less/no coverage among of cancer in India and provide future estimates. Our the States/UTs. The North-East (NE) region has better previous publication estimated 1.39 million new representativeness over the rest of India, with four NE (incident) cancer cases in the year 20205. The present States (Sikkim, Manipur, Mizoram and Tripura) having article is aimed to provide detailed estimates of cancer 100 per cent PBCR coverage and each NE State with at incidence in India by sex, age groups and anatomical least one fully functional PBCR. Of the 28 PBCRs rural, sites for the year 2022 and the projected rise in cases urban and semi-urban distributions were one (3.5%), for 2025, using the same datasets and methodology5. 12 (42.9%) and 15 (53.6%), respectively. There was no In addition, five-year and broad age group-wise cancer sampling method used in selecting PBCRs. The PBCRs estimates were also calculated for the year 2022. of the respective State/region were used to differentiate Noticeably, GLOBOCAN followed a similar approach between rural and urban settings wherever feasible. for 2020 after publishing the 2018 cancer estimates1,7. For example, Chennai and Dindigul PBCRs’ rates were used to describe Tamil Nadu State urban and rural rate, Material & Methods respectively12. Patiala PBCRs cover both urban and The present study was carried out at ICMR- rural areas and have been used for the Punjab State8. National Centre for Disease Informatics & Research, For regions with less/no PBCR coverage, the pooled Bengaluru, Karnataka, India. The study used secondary incidence rates (combination of rural and urban) were data for analyses and was granted exemption from used for the rest of India except for Delhi, Punjab review approval by the Institutional Ethics Committee district, Maharashtra and the southern region. of ICMR-NCDIR (Ref: NCDIR/IEC/3060/2022). First, the representation of PBCRs by Data sources: NCRP reports 2020 described cancer State/region wise was assigned for estimating cancer incidence by sex, 16 age groups (0-4, 5-9, 10-14, burden (Supplementary Table I). Then, the Indian 15-19, 20-24, 25-29, 30-34, 35-39, 40-44, 45-49, States/UT-wise population by five-year age groups till 50-54, 55-59, 60-64, 65-69, 70-74 and 75+; in yrs) and 2022 were calculated using the difference distribution
A11: S1 - Sathishkumar et al. 2022, IJMR | B11: 3 | C11: 600 INDIAN J MED RES, OCTOBER & NOVEMBER 2022 method from the 2001 to 2011 census growth rate13. year 2022. In the childhood group (0-14 yr) lymphoid Thereafter, the ASIR of each specific anatomical leukaemia is the leading site for both boys (29.3%) site from 2012 to 2016 was applied to the estimated and girls (24.3%), followed by the brain nervous population to derive the number of cancer cases in system (NS) (boys: 12.4% and girls: 14.3%). In the India for 2022. Cancer estimates for each specific adolescent and young adult group (15-39 yr), among anatomical site were added to get the total estimate males, the leading sites are mouth (12.0%), tongue of all site cancer (ICD 10: C00-C97). The pooled age, (8.8%), brain NS (7.0%), myeloid leukaemia (6.5%) sex- and site-specific incidence rates were computed and non-Hodgkin lymphoma (NHL) (5.9%); among using the population-weighted average of the rates females, breast (27.3%), thyroid (12.2%), ovary from the PBCRs. The estimation of cancer incidence (7.3%), cervix (7.1%) and myeloid leukaemia (3.7%). was done assuming that the 28 PBCRs represent the In 40-64 years’ age group, among males, the leading country with a constant incidence rate over time. sites included the lung (11.0%), mouth (10.9%) and The same process has been executed to estimate the tongue (7.3%). Among females, the leading sites were cancer cases for the year 2025. The statistical analysis breast (33.0%), cervix (12.3%) and ovary (6.5%); this and graphs were generated using in-house software age group had a high incidence of cases in both males Population-Based Cancer Registry Data Management (3,41,230) and females (4,25,918). Above 65 yr of age, (PBCRDM) version 2.1 and Microsoft Excel. prostate (12.3%) was the second-leading site after lung (13.1%) in males. Above 40 yr of age, lung cancer was Results the top most common cancer among males while breast Table I presents the estimated cancer incidence, cancer topped in females. number of cases, crude rate and cumulative risk by Fig. 2 presents the estimated cancer cases and sex and anatomical sites in India for the year 2022. ASIR by five-year age group and gender for India The estimated number of cancer cases and crude in 2022. The ASIR for all sites of cancer started incidence rate in India for the year 2022 was 14,61,427 increasing from 25 years of age in both males and (100.4 per 100,000), with a greater number of female females. However, the ASIR among females aged cases 7,49,251 (105.4 per 100,000) estimated compared 25-59 yr was higher than in males. Above 60 yr, the to that in males 7,12,176 (95.6 per 100,000). The male ASIR was higher than females and it peaked at estimated AAR for all sites of cancer in India would 75+ yr with 710.6 per 100,000. While in females, the be 107.0 per 100,000. The leading five sites with the ASIR dropped to 451.7 per 100,000 at 75+ yr. The highest cancer burden in both sexes were organs of the highest number of cancer cases were in the 60-64 yr digestive system (2,88,054), breast (2,21,757), genital age group (males: 1,06,296 and females: 1,05,139). system (2,18,319), oral cavity and pharynx (1,98,438) and respiratory system (1,43,062). The cumulative Table III provides the estimated leading sites of risk to develop cancer in his/her lifetime between 0 cancer cases by different periods (2015, 2020 and and 74 yr was one in every nine persons for all sites 2025) for leading sites of cancer. While in males, all of cancer in both sexes, one in 67 for lung cancers in site - cancers are likely to increase to 7,63,575 in 2025 males and one in 29 for breast cancer in females. from 6,01,737 in 2015, in females all site - cancers are likely to increase to 8,06,218 in 2025 from 6,27,202 in Fig. 1 presents the estimated top five leading sites 2015. The projected leading cancer cases of the lung of cancer; among males these were lung (10.6%), and breast would be 81,219 and 2,32,832 among males mouth (8.4%), prostate (6.1%), tongue (5.9%) and and females, respectively, for the year 2025. Cancer stomach (4.8%). The estimated top five leading sites of cases considered together for all sites are expected to cancer among females included breast (28.8%), cervix increase by 27.7 per cent from 2015 to 2025. (10.6%), ovary (6.2%), corpus uteri (3.7%) and lung (3.7%). Liver cancer (3.9%) was among the leading ten Discussion cancers in males and not in females, whereas thyroid In India, the incidence of cancer cases is likely to (3.6%) and gallbladder (2.7%) cancers were in top ten increase from 1.46 million in 2022 to 1.57 million in among females but not in males. 2025. The national average for the year 2022 of crude Table II provides gender disaggregated, estimated rate of incidence per 100,000 is 100.4; for males, 95.6 top five leading sites of cancer (%) in India by age and females, 105.4. Lung and breast cancers in males group (0-14, 15-39, 40-64, 65+ age group) for the and females, respectively, remain to be the leading sites
A12: S1 - Sathishkumar et al. 2022, IJMR | B12: 4 | C12: Table I. Estimated number, incidence rate and cumulative risk for all cancer sites in India by sex‑2022 Site Male Female Both sexes Cases CR AAR Cum‑risk Cases CR AAR Cum‑risk Cases CR AAR Cum‑risk All sites 712,176 95.6 105.7 1 in 9 749,251 105.4 109.0 1 in 9 1,461,427 100.4 107.0 1 in 9 Oral cavity and pharynx 145,844 19.6 21.2 1 in 42 52,594 7.4 7.7 1 in 115 198,438 13.6 14.4 1 in 62 Tongue 41,845 5.6 6.0 1 in 147 14,611 2.1 2.1 1 in 400 56,456 3.9 4.1 1 in 215 Mouth 60,164 8.1 8.6 1 in 103 23,675 3.3 3.5 1 in 241 83,839 5.8 6.1 1 in 144 Pharynx 3177 0.4 0.5 1 in 1793 1168 0.2 0.2 1 in 5482 4345 0.3 0.3 1 in 2704 Other oral cavity 40,658 5.5 6.1 1 in 137 13,140 1.8 1.9 1 in 475 53,798 3.7 4.0 1 in 213 Digestive system 172,025 23.1 25.9 1 in 32 116,029 16.3 17.0 1 in 50 288,054 19.8 21.4 1 in 39 Oesophagus 34,272 4.6 5.2 1 in 159 21,300 3.0 3.1 1 in 263 55,572 3.8 4.2 1 in 198 Stomach 34,353 4.6 5.2 1 in 160 18,353 2.6 2.7 1 in 319 52,706 3.6 3.9 1 in 213 Small intestine 2255 0.3 0.3 1 in 2498 1533 0.2 0.2 1 in 3877 3788 0.3 0.3 1 in 3041 Colon 21,595 2.9 3.2 1 in 260 16,512 2.3 2.4 1 in 348 38,107 2.6 2.8 1 in 298 Rectum 22,985 3.1 3.4 1 in 244 15,767 2.2 2.3 1 in 372 38,752 2.7 2.8 1 in 295 Anus, anal canal 3037 0.4 0.4 1 in 1865 2131 0.3 0.3 1 in 2682 5168 0.4 0.4 1 in 2200 Liver and intrahepatic bile duct 28,020 3.8 4.3 1 in 189 11,306 1.6 1.7 1 in 514 39,326 2.7 3.0 1 in 276 Gallbladder and other biliary 12,997 1.7 1.9 1 in 423 20,570 2.9 3.0 1 in 283 33,567 2.3 2.5 1 in 339 Pancreas 12,511 1.7 1.9 1 in 429 8557 1.2 1.3 1 in 656 21,068 1.4 1.6 1 in 519 Respiratory system 108,848 14.6 16.2 1 in 48 34,214 4.8 4.8 1 in 165 143,062 9.8 10.4 1 in 74 Larynx 28,542 3.8 4.3 1 in 184 3498 0.5 0.5 1 in 1629 32,040 2.2 2.4 1 in 331 Lung and bronchus 75474 10.1 11.6 1 in 67 27,897 3.9 4.1 1 in 209 103,371 7.1 7.8 1 in 101 Other respiratory organs 4832 0.6 0.3 1 in 1274 2819 0.4 0.2 1 in 2149 7651 0.5 0.2 1 in 1602 Bones and joints 8426 1.1 1.1 1 in 1011 6087 0.9 0.8 1 in 1365 14,513 1.0 1.0 1 in 1160 Soft tissue 8380 1.1 1.2 1 in 844 6895 1.0 1.0 1 in 1050 15,275 1.0 1.1 1 in 936 Skin (excluding basal and squamous) 11,745 1.6 1.7 1 in 510 9412 1.3 1.4 1 in 641 21,157 1.5 1.5 1 in 569 Melanoma of the skin 3145 0.4 0.5 1 in 1909 2479 0.3 0.4 1 in 2288 5624 0.4 0.4 1 in 2081 SATHISHKUMAR et al: CANCER INCIDENCE ESTIMATES FOR 2022 Other non‑epithelial skin 8600 1.2 1.3 1 in 696 6933 1.0 1.0 1 in 891 15,533 1.1 1.1 1 in 782 Breast 5649 0.8 0.8 1 in 1021 216,108 30.4 31.2 1 in 29 221,757 15.2 16.0 1 in 56 Genital system 54,625 7.3 8.4 1 in 105 163,694 23.0 23.9 1 in 37 218,319 15.0 16.0 1 in 53 Uterine cervix ‑ ‑ ‑ ‑ 79,103 11.1 11.6 1 in 75 79,103 11.1 11.6 1 in 75 Uterine corpus ‑ ‑ ‑ ‑ 27,922 3.9 4.2 1 in 190 27,922 3.9 4.2 1 in 190 Ovary ‑ ‑ ‑ ‑ 46,126 6.5 6.7 1 in 133 46,126 6.5 6.7 1 in 133 Vulva ‑ ‑ ‑ ‑ 2258 0.3 0.3 1 in 2454 2258 0.3 0.3 1 in 2454 Contd... 601
A13: S1 - Sathishkumar et al. 2022, IJMR | B13: 5 | C13: 602 Site Male Female Both sexes Cases CR AAR Cum‑risk Cases CR AAR Cum‑risk Cases CR AAR Cum‑risk Vagina and other genital, female ‑ ‑ ‑ ‑ 7961 1.1 1.2 1 in 747 7961 1.1 1.2 1 in 747 Placenta ‑ ‑ ‑ ‑ 324 0.0 0.0 1 in 31,252 324 0.0 0.0 1 in 31,252 Prostate 43,691 5.9 6.8 1 in 125 ‑ ‑ ‑ ‑ 43,691 5.9 6.8 1 in 125 Testis 4521 0.6 0.6 1 in 2092 ‑ ‑ ‑ ‑ 4521 0.6 0.6 1 in 2092 Penis and other genital, male 6413 0.8 1.0 1 in 917 ‑ ‑ ‑ ‑ 6413 0.8 1.0 1 in 917 Urinary system 34,942 4.7 5.3 1 in 158 11,861 1.7 1.8 1 in 500 46,803 3.2 3.5 1 in 240 Urinary bladder 21,523 2.9 3.3 1 in 250 5713 0.8 0.8 1 in 1011 27,236 1.9 2.0 1 in 402 Kidney and renal pelvis 12,963 1.7 2.0 1 in 442 5930 0.8 0.9 1 in 1036 18,893 1.3 1.4 1 in 619 Ureter and other urinary organs 456 0.1 0.1 1 in 10,755 218 0.0 0.0 1 in 21,739 674 0.0 0.1 1 in 14,422 Eye and orbit 1326 0.2 0.2 1 in 6887 977 0.1 0.2 1 in 9049 2303 0.2 0.2 1 in 7799 Brain and other nervous system 20,811 2.8 2.9 1 in 341 13,296 1.9 1.9 1 in 546 34,107 2.3 2.4 1 in 419 Endocrine system 9682 1.3 1.4 1 in 708 27,847 3.9 3.8 1 in 280 37,529 2.6 2.5 1 in 402 Thyroid 8967 1.2 1.2 1 in 758 27,253 3.8 3.7 1 in 285 36,220 2.5 2.4 1 in 416 Adrenal gland 715 0.1 0.1 1 in 10,776 594 0.1 0.1 1 in 13,920 1309 0.1 0.1 1 in 12,146 Lymphoma 34,116 4.6 4.9 1 in 197 21,233 3.0 3.1 1 in 296 55,349 3.8 4.0 1 in 236 Hodgkin lymphoma 7561 1.0 1.0 1 in 1150 4113 0.6 0.6 1 in 1866 11,674 0.8 0.8 1 in 1416 Non‑Hodgkin lymphoma 26,497 3.6 3.8 1 in 238 17,070 2.4 2.5 1 in 352 43,567 3.0 3.2 1 in 284 Malig Imn.Prol D 58 0.0 0.0 1 in 103,646 50 0.0 0.0 1 in 163,299 108 0.0 0.0 1 in 127,221 Multiple myeloma 11,261 1.5 1.7 1 in 465 8165 1.1 1.2 1 in 646 19,426 1.3 1.5 1 in 541 INDIAN J MED RES, OCTOBER & NOVEMBER 2022 Leukaemia 33,604 4.5 4.8 1 in 239 21,969 3.1 3.2 1 in 352 55,573 3.8 4.0 1 in 284 Lymphoid leukaemia 14,546 2.0 2.1 1 in 609 7638 1.1 1.2 1 in 1137 22,184 1.5 1.7 1 in 790 Myeloid leukaemia 15,531 2.1 2.2 1 in 474 11,788 1.7 1.7 1 in 616 27,319 1.9 1.9 1 in 536 Leukaemia unspecified 3527 0.5 0.5 1 in 2292 2543 0.4 0.4 1 in 2974 6070 0.4 0.4 1 in 2585 Other and unspecified primary sites 50,892 6.8 7.6 1 in 114 38,870 5.5 5.7 1 in 153 89,762 6.2 6.6 1 in 131 Cum‑risk, cumulative risk of developing cancer in 0‑74 yr of age; CR, crude rate; AAR, age‑adjusted rate; Malig Imn.Prol D, malignant immunoproliferative diseases
